Workbook
Name bbg_id: 'Bonds Universe'!#REF!
Name bbg_id: '[1]Reference Portfolio'!$E$5:$E$117
Name data: '[1]Reference Portfolio'!$C$5:$AE$117
Name er: 'Bonds Universe'!#REF!
Name F: '[2]Summary Sheet'!$A$3
Name g: '[3]Summary Sheet'!$A$3
Name GIFDATE: '[4]GIF Summary '!$B$1
Name GIFReportDate: '[5]Summary Sheet'!$A$3
Name GIFSHEETNEWDATE: [6]SUMMARY!$D$5
Name header: '[1]Reference Portfolio'!$C$4:$AE$4
Name month: '[7]Summary Sheet'!$G$3
Name New_GIF_Date: '[4]GIF Summary '!$I$1
Name ny: 'Bonds Universe'!#REF!
Name Previous_Month: '[4]GIF Summary '!$O$2
Name Previous_Year: '[4]GIF Summary '!$N$2
Name reportdate: '[4]Summary - Liabilities'!$A$2
Name s_header: '[8]2015 HP'!$C$17:$HU$17
Name sankore_id: 'Bonds Universe'!#REF!
Name solver_adj: 'Eurobond Trade Tracker'!#REF!
Name solver_adj: 'NGN Domestic Trade Tracker'!#REF!
Name solver_cvg: 0.0001
Name solver_cvg: 0.0001
Name solver_drv: 1
Name solver_drv: 1
Name solver_eng: 1
Name solver_eng: 1
Name solver_est: 1
Name solver_est: 1
Name solver_itr: 2147483647
Name solver_itr: 2147483647
Name solver_mip: 2147483647
Name solver_mip: 2147483647
Name solver_mni: 30
Name solver_mni: 30
Name solver_mrt: 0.075
Name solver_mrt: 0.075
Name solver_msl: 2
Name solver_msl: 2
Name solver_neg: 2
Name solver_neg: 2
Name solver_nod: 2147483647
Name solver_nod: 2147483647
Name solver_num: 0
Name solver_num: 0
Name solver_nwt: 1
Name solver_nwt: 1
Name solver_opt: 'Eurobond Trade Tracker'!#REF!
Name solver_opt: 'NGN Domestic Trade Tracker'!#REF!
Name solver_pre: 0.000001
Name solver_pre: 0.000001
Name solver_rbv: 1
Name solver_rbv: 1
Name solver_rlx: 2
Name solver_rlx: 2
Name solver_rsd: 0
Name solver_rsd: 0
Name solver_scl: 1
Name solver_scl: 1
Name solver_sho: 2
Name solver_sho: 2

Sheet Prev. Dashboard
B4: Average Gap | F4: Average Gap on Transactions | I4: Average Gap Per Trader | M4: Average Gap Per CP
B5: Month | C5: Per Month | D5: YTD
B6: 43861 | F6: Buy | G6: =AVERAGEIF('Eurobond Trade Tracker'!$F:$F,'Prev. Dashboard'!F6,'Eurobond Trade Tracker'!#REF!) -> #ERROR! | I6: Kamil | J6: Buy | K6: =AVERAGEIFS('Eurobond Trade Tracker'!#REF!,'Eurobond Trade Tracker'!$E:$E,'Prev. Dashboard'!$I$6,'Eurobond Trade Tracker'!$F:$F,'Prev. Dashboard'!J6) -> #ERROR!
B7: =EOMONTH(B6,1) -> 43890 | F7: Sell | G7: =AVERAGEIF('Eurobond Trade Tracker'!$F:$F,'Prev. Dashboard'!F7,'Eurobond Trade Tracker'!#REF!) -> #ERROR! | J7: Sell | K7: =AVERAGEIFS('Eurobond Trade Tracker'!#REF!,'Eurobond Trade Tracker'!$E:$E,'Prev. Dashboard'!$I$6,'Eurobond Trade Tracker'!$F:$F,'Prev. Dashboard'!J7) -> #ERROR!
B8: =EOMONTH(B7,1) -> 43921 | J8: Total | K8: =AVERAGEIF('Eurobond Trade Tracker'!E:E,'Prev. Dashboard'!I6,'Eurobond Trade Tracker'!#REF!) -> #ERROR!
B9: =EOMONTH(B8,1) -> 43951 | I9: Kingsley | J9: Buy | K9: =AVERAGEIFS('Eurobond Trade Tracker'!#REF!,'Eurobond Trade Tracker'!$E:$E,'Prev. Dashboard'!$I$9,'Eurobond Trade Tracker'!$F:$F,'Prev. Dashboard'!J9) -> #ERROR!
B10: =EOMONTH(B9,1) -> 43982 | J10: Sell | K10: =AVERAGEIFS('Eurobond Trade Tracker'!#REF!,'Eurobond Trade Tracker'!$E:$E,'Prev. Dashboard'!$I$9,'Eurobond Trade Tracker'!$F:$F,'Prev. Dashboard'!J10) -> #ERROR!
B11: =EOMONTH(B10,1) -> 44012 | J11: Total | K11: =AVERAGEIF('Eurobond Trade Tracker'!E:E,'Prev. Dashboard'!I9,'Eurobond Trade Tracker'!#REF!) -> #ERROR!
B12: =EOMONTH(B11,1) -> 44043 | I12: TOTAL | K12: =AVERAGE('Eurobond Trade Tracker'!#REF!) -> #ERROR!
B13: =EOMONTH(B12,1) -> 44074
B14: =EOMONTH(B13,1) -> 44104
B15: =EOMONTH(B14,1) -> 44135
B16: =EOMONTH(B15,1) -> 44165
B17: =EOMONTH(B16,1) -> 44196
B20: CP
B21: Comercio/Access
B22: Comercio/FBN Merchant
B23: Comercio/Stanbic
B24: Commercio
B25: FBN Bank (UK)
B26: FBN Market
B27: FBN UK
B28: First Bank Merchant
B29: Aztran/Globus bank
B30: Coronation Merchant Bank
B31: First Bank UK
... B62: Aztran/Providus

Sheet Dashboard
B3: Average GAP per Trader and Transaction
B4: Trader | C4: Buy | D4: Sell | E4: Total
B5: Rasheed
B6: Adedayo
B7: Total
B10: Average GAP per month
B11: Month | C11: Per month | D11: YTD
B12: 44227
B13: =EOMONTH(B12,1) -> 44255
B14: =EOMONTH(B13,1) -> 44286
B15: =EOMONTH(B14,1) -> 44316
B16: =EOMONTH(B15,1) -> 44347
B17: =EOMONTH(B16,1) -> 44377
B18: =EOMONTH(B17,1) -> 44408
B19: =EOMONTH(B18,1) -> 44439
B20: =EOMONTH(B19,1) -> 44469
B21: =EOMONTH(B20,1) -> 44500
B22: =EOMONTH(B21,1) -> 44530
B23: =EOMONTH(B22,1) -> 44561
B26: Average GAP per Counterparty
B27: Counterparty | C27: No of trades YTD | D27: Average GAP
B28: FBN UK
B29: FSDH
B30: Parthian
B31: Parthian Partners/UBA
B32: Parthian/Access Bank
B33: Parthian/UBA Custody
B34: Rencap
B35: Stanbic Nominees
B36: Zedcap/UBA Custody
B37: Zedcap/UBA GIS
B38: Zedcrest Capital/UBA
B39: Zenith
... B47: Chapelhill/FSDH

Sheet Eurobond Trade Tracker
E1: 0.07625 | F1: 828000 | G1: =#REF!*100/#REF! -> #REF! | M1: Modified | N1: Actual | O1: =TODAY()-40 -> 46227 | P1: =COUPNCD(O1,#REF!,2,0) -> #REF! | S1: 794774
H2: =COUPNCD(#REF!,#REF!,2,0) -> #REF! | I2: =(#REF!*#REF!)/2 -> #REF! | K2: 46532 | L2: Angola 2028 | M2: 47102 | N2: 46882 | Q2: =(#REF!*#REF!)/2 -> #REF! | U2: Sell | V2: PR004
J3: =COUNTA(#REF!) -> 1 | L3: Ghana 2032 | M3: 48330 | N3: 48299 | O3: 31567.5 | U3: Buy | V3: Bid code
L4: Ghana 2027 | M4: 46533 | N4: 46472
A6: S/N | B6: CP | C6: Settlement Bank | D6: Portfolio | E6: Trader | F6: Direction | G6: Name of Asset | H6: Coupon Rate | I6: Maturity Date | J6: Trade Date | K6: Settlement Date | L6: Ytm | M6: Price | N6: Face Value | O6: Consideration | P6: Principal | Q6: Accrued Interest | R6: Consideration | S6: ISIN | T6: Status | U6: Bloomberg Yield
B7: Access bank | C7: Stanbic | D7: GIF$ | E7: Victor | F7: Sell | G7: NGERIA 7.696 02/23/38 | H7: =IFERROR(VLOOKUP($G7,'Bonds Universe'!$D:$H,2,FALSE), "") -> 0.07696 | I7: =IFERROR(VLOOKUP($G7,'Bonds Universe'!$D:$H,3,FALSE), "") -> 50459 | J7: 45554 | K7: 45555 | L7: =IFERROR(YIELD(K7,I7,H7,M7,100,2,0),"") -> 0.1030339 | M7: 81.25 | N7: 400000 | O7: =IFERROR((N7*M7/100)+ACCRINT(COUPPCD(K7,I7,2,0),COUPNCD(K7,I7,2,0),K7,H7,N7,2,0),N7*M7/100) -> 327308.8 | P7: =N7*M7/100 -> 325000 | Q7: =IFERROR(ACCRINT(COUPPCD(K7,I7,2,0),COUPNCD(K7,I7,2,0),K7,H7,N7,2,0),"") -> 2308.8
B8: Rencap | C8: Mauritius | D8: SADF$ | E8: Victor | F8: Buy | G8: ETI 10.125% 10/15/2029 | H8: 0.10125 | I8: 47406 | J8: 45572 | K8: 45580 | L8: =IFERROR(YIELD(K8,I8,H8,M8,100,2,0),"") -> 0.10374872 | M8: 99.044 | N8: 4200000 | O8: =IFERROR((N8*M8/100)+ACCRINT(COUPPCD(K8,I8,2,0),COUPNCD(K8,I8,2,0),K8,H8,N8,2,0),N8*M8/100) -> 4159848 | P8: =N8*M8/100 -> 4159848 | Q8: =IFERROR(ACCRINT(COUPPCD(K8,I8,2,0),COUPNCD(K8,I8,2,0),K8,H8,N8,2,0),"") -> 0
B9: Access bank | C9: Mauritius | D9: SADF$ | E9: Dapo | F9: Sell | G9: SEPLAT 7.75 01/04/26 | H9: =IFERROR(VLOOKUP($G9,'Bonds Universe'!$D:$H,2,FALSE), "") -> 0.0775 | I9: =IFERROR(VLOOKUP($G9,'Bonds Universe'!$D:$H,3,FALSE), "") -> 46113 | J9: 45573 | K9: 45575 | L9: =IFERROR(YIELD(K9,I9,H9,M9,100,2,0),"") -> 0.080036529 | M9: 99.65 | N9: 2000000 | O9: =IFERROR((N9*M9/100)+ACCRINT(COUPPCD(K9,I9,2,0),COUPNCD(K9,I9,2,0),K9,H9,N9,2,0),N9*M9/100) -> 1996875 | P9: =N9*M9/100 -> 1993000 | Q9: =IFERROR(ACCRINT(COUPPCD(K9,I9,2,0),COUPNCD(K9,I9,2,0),K9,H9,N9,2,0),"") -> 3875
B10: Access bank | C10: Mauritius | D10: SADF$ | E10: Dapo | F10: Sell | G10: SEPLAT 7.75 01/04/26 | H10: =IFERROR(VLOOKUP($G10,'Bonds Universe'!$D:$H,2,FALSE), "") -> 0.0775 | I10: =IFERROR(VLOOKUP($G10,'Bonds Universe'!$D:$H,3,FALSE), "") -> 46113 | J10: 45574 | K10: 45576 | L10: =IFERROR(YIELD(K10,I10,H10,M10,100,2,0),"") -> 0.080405929 | M10: 99.6 | N10: 3000000 | O10: =IFERROR((N10*M10/100)+ACCRINT(COUPPCD(K10,I10,2,0),COUPNCD(K10,I10,2,0),K10,H10,N10,2,0),N10*M10/100) -> 2994458.3 | P10: =N10*M10/100 -> 2988000 | Q10: =IFERROR(ACCRINT(COUPPCD(K10,I10,2,0),COUPNCD(K10,I10,2,0),K10,H10,N10,2,0),"") -> 6458.3333
B11: Access bank | C11: Mauritius | D11: SADF$ | E11: Dapo | F11: Sell | G11: SEPLAT 7.75 01/04/26 | H11: =IFERROR(VLOOKUP($G11,'Bonds Universe'!$D:$H,2,FALSE), "") -> 0.0775 | I11: =IFERROR(VLOOKUP($G11,'Bonds Universe'!$D:$H,3,FALSE), "") -> 46113 | J11: 45575 | K11: 45581 | L11: =IFERROR(YIELD(K11,I11,H11,M11,100,2,0),"") -> 0.079677092 | M11: 99.7 | N11: 1280000 | O11: =IFERROR((N11*M11/100)+ACCRINT(COUPPCD(K11,I11,2,0),COUPNCD(K11,I11,2,0),K11,H11,N11,2,0),N11*M11/100) -> 1280293.3 | P11: =N11*M11/100 -> 1276160 | Q11: =IFERROR(ACCRINT(COUPPCD(K11,I11,2,0),COUPNCD(K11,I11,2,0),K11,H11,N11,2,0),"") -> 4133.3333
B12: Access bank | C12: Stanbic | D12: GIF$ | E12: Dapo | F12: Sell | G12: SEPLAT 7.75 01/04/26 | H12: =IFERROR(VLOOKUP($G12,'Bonds Universe'!$D:$H,2,FALSE), "") -> 0.0775 | I12: =IFERROR(VLOOKUP($G12,'Bonds Universe'!$D:$H,3,FALSE), "") -> 46113 | J12: 45575 | K12: 45581 | L12: =IFERROR(YIELD(K12,I12,H12,M12,100,2,0),"") -> 0.079677092 | M12: 99.7 | N12: 450000 | O12: =IFERROR((N12*M12/100)+ACCRINT(COUPPCD(K12,I12,2,0),COUPNCD(K12,I12,2,0),K12,H12,N12,2,0),N12*M12/100) -> 450103.12 | P12: =N12*M12/100 -> 448650 | Q12: =IFERROR(ACCRINT(COUPPCD(K12,I12,2,0),COUPNCD(K12,I12,2,0),K12,H12,N12,2,0),"") -> 1453.125
A13: SMA Mr Ajene | B13: Access bank | C13: Stanbic | D13: GIF$ | E13: Victor | F13: Buy | G13: ANGOL 8.75 04/14/2032 | H13: =IFERROR(VLOOKUP($G13,'Bonds Universe'!$D:$H,2,FALSE), "") -> 0.0875 | I13: =IFERROR(VLOOKUP($G13,'Bonds Universe'!$D:$H,3,FALSE), "") -> 48318 | J13: 45581 | K13: 45583 | L13: =IFERROR(YIELD(K13,I13,H13,M13,100,2,0),"") -> 0.10620442 | M13: 90.5 | N13: 200000 | O13: =IFERROR((N13*M13/100)+ACCRINT(COUPPCD(K13,I13,2,0),COUPNCD(K13,I13,2,0),K13,H13,N13,2,0),N13*M13/100) -> 181194.44 | P13: =N13*M13/100 -> 181000 | Q13: =IFERROR(ACCRINT(COUPPCD(K13,I13,2,0),COUPNCD(K13,I13,2,0),K13,H13,N13,2,0),"") -> 194.44444
B14: BCP Securities | C14: Mauritius | D14: SADF$ | E14: Dapo | F14: Buy | G14: EGYPT 8 7/8 05/29/50 | H14: =IFERROR(VLOOKUP($G14,'Bonds Universe'!$D:$H,2,FALSE), "") -> 0.08875 | I14: =IFERROR(VLOOKUP($G14,'Bonds Universe'!$D:$H,3,FALSE), "") -> 54937 | J14: 45586 | K14: 45588 | L14: =IFERROR(YIELD(K14,I14,H14,M14,100,2,0),"") -> 0.10891836 | M14: 82.69 | N14: 1000000 | O14: =IFERROR((N14*M14/100)+ACCRINT(COUPPCD(K14,I14,2,0),COUPNCD(K14,I14,2,0),K14,H14,N14,2,0),N14*M14/100) -> 862400 | P14: =N14*M14/100 -> 826900 | Q14: =IFERROR(ACCRINT(COUPPCD(K14,I14,2,0),COUPNCD(K14,I14,2,0),K14,H14,N14,2,0),"") -> 35500
B15: Access bank | C15: Stanbic | D15: GIF$ | E15: Dapo | F15: Buy | G15: ANGOL 9 3/8 05/08/48 | H15: =IFERROR(VLOOKUP($G15,'Bonds Universe'!$D:$H,2,FALSE), "") -> 0.09375 | I15: =IFERROR(VLOOKUP($G15,'Bonds Universe'!$D:$H,3,FALSE), "") -> 54186 | J15: 45583 | K15: 45587 | L15: =IFERROR(YIELD(K15,I15,H15,M15,100,2,0),"") -> 0.11100067 | M15: 85.67 | N15: 600000 | O15: =IFERROR((N15*M15/100)+ACCRINT(COUPPCD(K15,I15,2,0),COUPNCD(K15,I15,2,0),K15,H15,N15,2,0),N15*M15/100) -> 539645 | P15: =N15*M15/100 -> 514020 | Q15: =IFERROR(ACCRINT(COUPPCD(K15,I15,2,0),COUPNCD(K15,I15,2,0),K15,H15,N15,2,0),"") -> 25625
B16: Access bank | C16: Mauritius | D16: SADF$ | E16: Dapo | F16: Buy | G16: ANGOL 9 3/8 05/08/48 | H16: =IFERROR(VLOOKUP($G16,'Bonds Universe'!$D:$H,2,FALSE), "") -> 0.09375 | I16: =IFERROR(VLOOKUP($G16,'Bonds Universe'!$D:$H,3,FALSE), "") -> 54186 | J16: 45586 | K16: 45588 | L16: =IFERROR(YIELD(K16,I16,H16,M16,100,2,0),"") -> 0.11109815 | M16: 85.6 | N16: 1700000 | O16: =IFERROR((N16*M16/100)+ACCRINT(COUPPCD(K16,I16,2,0),COUPNCD(K16,I16,2,0),K16,H16,N16,2,0),N16*M16/100) -> 1528246.9 | P16: =N16*M16/100 -> 1455200 | Q16: =IFERROR(ACCRINT(COUPPCD(K16,I16,2,0),COUPNCD(K16,I16,2,0),K16,H16,N16,2,0),"") -> 73046.875
B17: First Bank UK | C17: Mauritius | D17: SADF$ | E17: Dapo | F17: Buy | G17: ANGOL 9 1/8 11/26/49 | H17: =IFERROR(VLOOKUP($G17,'Bonds Universe'!$D:$H,2,FALSE), "") -> 0.09125 | I17: =IFERROR(VLOOKUP($G17,'Bonds Universe'!$D:$H,3,FALSE), "") -> 54753 | J17: 45593 | K17: 45595 | L17: =IFERROR(YIELD(K17,I17,H17,M17,100,2,0),"") -> 0.11048432 | M17: 83.75 | N17: 450000 | O17: =IFERROR((N17*M17/100)+ACCRINT(COUPPCD(K17,I17,2,0),COUPNCD(K17,I17,2,0),K17,H17,N17,2,0),N17*M17/100) -> 394440.62 | P17: =N17*M17/100 -> 376875 | Q17: =IFERROR(ACCRINT(COUPPCD(K17,I17,2,0),COUPNCD(K17,I17,2,0),K17,H17,N17,2,0),"") -> 17565.625
B18: Access bank | C18: Stanbic | D18: GIF$ | E18: Dapo | F18: Buy | G18: ANGOL 9 1/8 11/26/49 | H18: =IFERROR(VLOOKUP($G18,'Bonds Universe'!$D:$H,2,FALSE), "") -> 0.09125 | I18: =IFERROR(VLOOKUP($G18,'Bonds Universe'!$D:$H,3,FALSE), "") -> 54753 | J18: 45593 | K18: 45595 | L18: =IFERROR(YIELD(K18,I18,H18,M18,100,2,0),"") -> 0.1105533 | M18: 83.7 | N18: 600000 | O18: =IFERROR((N18*M18/100)+ACCRINT(COUPPCD(K18,I18,2,0),COUPNCD(K18,I18,2,0),K18,H18,N18,2,0),N18*M18/100) -> 525620.83 | P18: =N18*M18/100 -> 502200 | Q18: =IFERROR(ACCRINT(COUPPCD(K18,I18,2,0),COUPNCD(K18,I18,2,0),K18,H18,N18,2,0),"") -> 23420.833
B19: Access bank | C19: Stanbic | D19: GIF$ | E19: Dapo | F19: Buy | G19: ANGOL 9 1/8 11/26/49 | H19: =IFERROR(VLOOKUP($G19,'Bonds Universe'!$D:$H,2,FALSE), "") -> 0.09125 | I19: =IFERROR(VLOOKUP($G19,'Bonds Universe'!$D:$H,3,FALSE), "") -> 54753 | J19: 45593 | K19: 45595 | L19: =IFERROR(YIELD(K19,I19,H19,M19,100,2,0),"") -> 0.11020908 | M19: 83.95 | N19: 400000 | O19: =IFERROR((N19*M19/100)+ACCRINT(COUPPCD(K19,I19,2,0),COUPNCD(K19,I19,2,0),K19,H19,N19,2,0),N19*M19/100) -> 351413.89 | P19: =N19*M19/100 -> 335800 | Q19: =IFERROR(ACCRINT(COUPPCD(K19,I19,2,0),COUPNCD(K19,I19,2,0),K19,H19,N19,2,0),"") -> 15613.889
A20: SMA Woodlake | B20: Access bank | C20: Stanbic | D20: GIF$ | E20: Dapo | F20: Sell | G20: GHANA 5 07/03/29 | H20: 0.05 | I20: 47302 | J20: 45601 | K20: 45603 | L20: =IFERROR(YIELD(K20,I20,H20,M20,100,2,0),"") -> 0.089760798 | M20: 85.125 | N20: 411158 | O20: =IFERROR((N20*M20/100)+ACCRINT(COUPPCD(K20,I20,2,0),COUPNCD(K20,I20,2,0),K20,H20,N20,2,0),N20*M20/100) -> 357079.3 | P20: =N20*M20/100 -> 349998.25 | Q20: =IFERROR(ACCRINT(COUPPCD(K20,I20,2,0),COUPNCD(K20,I20,2,0),K20,H20,N20,2,0),"") -> 7081.0544
A21: SMA Woodlake | B21: Access bank | C21: Stanbic | D21: GIF$ | E21: Dapo | F21: Sell | G21: GHANA 5 07/03/35 | H21: 0.05 | I21: 49493 | J21: 45601 | K21: 45603 | L21: =IFERROR(YIELD(K21,I21,H21,M21,100,2,0),"") -> 0.097861083 | M21: 68.75 | N21: 591252 | O21: =IFERROR((N21*M21/100)+ACCRINT(COUPPCD(K21,I21,2,0),COUPNCD(K21,I21,2,0),K21,H21,N21,2,0),N21*M21/100) -> 416668.42 | P21: =N21*M21/100 -> 406485.75 | Q21: =IFERROR(ACCRINT(COUPPCD(K21,I21,2,0),COUPNCD(K21,I21,2,0),K21,H21,N21,2,0),"") -> 10182.673
A22: SMA Woodlake | B22: Access bank | C22: Stanbic | D22: GIF$ | E22: Dapo | F22: Sell | G22: GHANA 0 01/03/30 | H22: 0 | I22: 47486 | J22: 45601 | K22: 45603 | L22: =IFERROR(YIELD(K22,I22,H22,M22,100,2,0),"") -> 0.057920687 | M22: 74.5 | N22: 96188.35 | O22: 65690.78 | P22: 65690.78 | Q22: =IFERROR(ACCRINT(COUPPCD(K22,I22,2,0),COUPNCD(K22,I22,2,0),K22,H22,N22,2,0),"")
A23: Sankore & Woodlake | B23: Access bank | C23: Stanbic | D23: GIF$ | E23: Dapo | F23: Sell | G23: GHANA 0 07/03/26 | H23: 0 | I23: 46206 | J23: 45602 | K23: 45604 | L23: =IFERROR(YIELD(K23,I23,H23,M23,100,2,0),"") -> 0.054475304 | M23: 91.5 | N23: 75720 | O23: 55427.04 | P23: 55427.04 | Q23: =IFERROR(ACCRINT(COUPPCD(K23,I23,2,0),COUPNCD(K23,I23,2,0),K23,H23,N23,2,0),"")
A24: Sankore & Chidi | B24: Access bank | C24: Stanbic | D24: GIF$ | E24: Dapo | F24: Sell | G24: GHANA 5 07/03/29 | H24: 0.05 | I24: 47302 | J24: 45602 | K24: 45604 | L24: =IFERROR(YIELD(K24,I24,H24,M24,100,2,0),"") -> 0.090151008 | M24: 85 | N24: 78408 | O24: =IFERROR((N24*M24/100)+ACCRINT(COUPPCD(K24,I24,2,0),COUPNCD(K24,I24,2,0),K24,H24,N24,2,0),N24*M24/100) -> 68008.05 | P24: =N24*M24/100 -> 66646.8 | Q24: =IFERROR(ACCRINT(COUPPCD(K24,I24,2,0),COUPNCD(K24,I24,2,0),K24,H24,N24,2,0),"") -> 1361.25
A25: Sankore & Chidi | B25: Access bank | C25: Stanbic | D25: GIF$ | E25: Dapo | F25: Sell | G25: GHANA 5 07/03/35 | H25: 0.05 | I25: 49493 | J25: 45602 | K25: 45604 | L25: =IFERROR(YIELD(K25,I25,H25,M25,100,2,0),"") -> 0.097870472 | M25: 68.75 | N25: 112752 | O25: =IFERROR((N25*M25/100)+ACCRINT(COUPPCD(K25,I25,2,0),COUPNCD(K25,I25,2,0),K25,H25,N25,2,0),N25*M25/100) -> 79474.5 | P25: =N25*M25/100 -> 77517 | Q25: =IFERROR(ACCRINT(COUPPCD(K25,I25,2,0),COUPNCD(K25,I25,2,0),K25,H25,N25,2,0),"") -> 1957.5
A26: Sankore & Chidi | B26: BCP Securities | C26: Stanbic | D26: GIF$ | E26: Dapo | F26: Sell | G26: GHANA 0 01/03/30 | H26: 0 | I26: 47486 | J26: 45603 | K26: 45608 | L26: =IFERROR(YIELD(K26,I26,H26,M26,100,2,0),"") -> 0.055412587 | M26: 75.5 | N26: 24093 | O26: =IFERROR((N26*M26/100)+ACCRINT(COUPPCD(K26,I26,2,0),COUPNCD(K26,I26,2,0),K26,H26,N26,2,0),N26*M26/100)*0.9167 -> 16674.97 | P26: =N26*M26/100 -> 18190.215 | Q26: =IFERROR(ACCRINT(COUPPCD(K26,I26,2,0),COUPNCD(K26,I26,2,0),K26,H26,N26,2,0),"")
B27: Access bank | C27: Mauritius | D27: SADF$ | E27: Dapo | F27: Sell | G27: ETINL 8 3/4 06/17/31 | H27: =IFERROR(VLOOKUP($G27,'Bonds Universe'!$D:$H,2,FALSE), "") -> 0.0875 | I27: =IFERROR(VLOOKUP($G27,'Bonds Universe'!$D:$H,3,FALSE), "") -> 48016 | J27: 45616 | K27: 45618 | L27: =IFERROR(YIELD(K27,I27,H27,M27,100,2,0),"") -> 0.089522752 | M27: 99 | N27: 5654000 | O27: =IFERROR((N27*M27/100)+ACCRINT(COUPPCD(K27,I27,2,0),COUPNCD(K27,I27,2,0),K27,H27,N27,2,0),N27*M27/100) -> 5810466.6 | P27: =N27*M27/100 -> 5597460 | Q27: =IFERROR(ACCRINT(COUPPCD(K27,I27,2,0),COUPNCD(K27,I27,2,0),K27,H27,N27,2,0),"") -> 213006.6
B28: Access bank | C28: Mauritius | D28: SADF$ | E28: Dapo | F28: Buy | G28: EGYPT 8 1/2 01/31/47 | H28: =IFERROR(VLOOKUP($G28,'Bonds Universe'!$D:$H,2,FALSE), "") -> 0.085 | I28: =IFERROR(VLOOKUP($G28,'Bonds Universe'!$D:$H,3,FALSE), "") -> 53723 | J28: 45616 | K28: 45621 | L28: =IFERROR(YIELD(K28,I28,H28,M28,100,2,0),"") -> 0.11060411 | M28: 78.95 | N28: 5315000 | O28: =IFERROR((N28*M28/100)+ACCRINT(COUPPCD(K28,I28,2,0),COUPNCD(K28,I28,2,0),K28,H28,N28,2,0),N28*M28/100) -> 4340509.5 | P28: =N28*M28/100 -> 4196192.5 | Q28: =IFERROR(ACCRINT(COUPPCD(K28,I28,2,0),COUPNCD(K28,I28,2,0),K28,H28,N28,2,0),"") -> 144317.01
B29: Access bank | C29: Mauritius | D29: SADF$ | E29: Dapo | F29: Buy | G29: ANGOL 9 3/8 05/08/48 | H29: =IFERROR(VLOOKUP($G29,'Bonds Universe'!$D:$H,2,FALSE), "") -> 0.09375 | I29: =IFERROR(VLOOKUP($G29,'Bonds Universe'!$D:$H,3,FALSE), "") -> 54186 | J29: 45616 | K29: 45621 | L29: =IFERROR(YIELD(K29,I29,H29,M29,100,2,0),"") -> 0.11390667 | M29: 83.61 | N29: 1733000 | O29: 1521169.6 | P29: =N29*M29/100 -> 1448961.3 | Q29: =IFERROR(ACCRINT(COUPPCD(K29,I29,2,0),COUPNCD(K29,I29,2,0),K29,H29,N29,2,0),"") -> 7672.1354
B30: Access bank | C30: Stanbic | D30: GIF$ | E30: Dapo | F30: Buy | G30: ANGOL 9 3/8 05/08/48 | H30: =IFERROR(VLOOKUP($G30,'Bonds Universe'!$D:$H,2,FALSE), "") -> 0.09375 | I30: =IFERROR(VLOOKUP($G30,'Bonds Universe'!$D:$H,3,FALSE), "") -> 54186 | J30: 45616 | K30: 45621 | L30: =IFERROR(YIELD(K30,I30,H30,M30,100,2,0),"") -> 0.11390667 | M30: 83.61 | N30: 545000 | O30: 478382.83 | P30: =N30*M30/100 -> 455674.5 | Q30: =IFERROR(ACCRINT(COUPPCD(K30,I30,2,0),COUPNCD(K30,I30,2,0),K30,H30,N30,2,0),"") -> 2412.7604
B31: BCP Securities | C31: Stanbic | D31: GIF$ | E31: Dapo | F31: Buy | G31: ANGOL 9 3/8 05/08/48 | H31: =IFERROR(VLOOKUP($G31,'Bonds Universe'!$D:$H,2,FALSE), "") -> 0.09375 | I31: =IFERROR(VLOOKUP($G31,'Bonds Universe'!$D:$H,3,FALSE), "") -> 54186 | J31: 45625 | K31: 45629 | L31: =IFERROR(YIELD(K31,I31,H31,M31,100,2,0),"") -> 0.11334855 | M31: 84 | N31: 1135000 | O31: 1003056.2 | P31: =N31*M31/100 -> 953400 | Q31: =IFERROR(ACCRINT(COUPPCD(K31,I31,2,0),COUPNCD(K31,I31,2,0),K31,H31,N31,2,0),"") -> 7389.3229
B32: Access bank | C32: Mauritius | D32: SADF$ | E32: Dapo | F32: Sell | G32: ETINL 8 3/4 06/17/31 | H32: =IFERROR(VLOOKUP($G32,'Bonds Universe'!$D:$H,2,FALSE), "") -> 0.0875 | I32: =IFERROR(VLOOKUP($G32,'Bonds Universe'!$D:$H,3,FALSE), "") -> 48016 | J32: 45644 | K32: 45646 | L32: =IFERROR(YIELD(K32,I32,H32,M32,100,2,0),"") -> 0.089665404 | M32: 98.95 | N32: 750000 | O32: =IFERROR((N32*M32/100)+ACCRINT(COUPPCD(K32,I32,2,0),COUPNCD(K32,I32,2,0),K32,H32,N32,2,0),N32*M32/100) -> 742671.88 | P32: =N32*M32/100 -> 742125 | Q32: =IFERROR(ACCRINT(COUPPCD(K32,I32,2,0),COUPNCD(K32,I32,2,0),K32,H32,N32,2,0),"") -> 546.875
B33: Access bank | C33: Mauritius | D33: SADF$ | E33: Oise | F33: Sell | G33: NIGERIA 6.125 9/28/28 | H33: =IFERROR(VLOOKUP($G33,'Bonds Universe'!$D:$H,2,FALSE), "") -> 0.06125 | I33: =IFERROR(VLOOKUP($G33,'Bonds Universe'!$D:$H,3,FALSE), "") -> 47024 | J33: 45694 | K33: 45695 | L33: =IFERROR(YIELD(K33,I33,H33,M33,100,2,0),"") -> 0.087152931 | M33: 92.05 | N33: 4070000 | O33: =IFERROR((N33*M33/100)+ACCRINT(COUPPCD(K33,I33,2,0),COUPNCD(K33,I33,2,0),K33,H33,N33,2,0),N33*M33/100) -> 3835763 | P33: =N33*M33/100 -> 3746435 | Q33: =IFERROR(ACCRINT(COUPPCD(K33,I33,2,0),COUPNCD(K33,I33,2,0),K33,H33,N33,2,0),"") -> 89328.021
B34: Access bank | C34: Mauritius | D34: SADF$ | E34: Oise | F34: Sell | G34: ETI 10.125% 10/15/2029 | H34: 0.10125 | I34: 47406 | J34: 45694 | K34: 45695 | L34: =IFERROR(YIELD(K34,I34,H34,M34,100,2,0),"") -> 0.088196676 | M34: 104.9 | N34: 4200000 | O34: =IFERROR((N34*M34/100)+ACCRINT(COUPPCD(K34,I34,2,0),COUPNCD(K34,I34,2,0),K34,H34,N34,2,0),N34*M34/100) -> 4538100 | P34: =N34*M34/100 -> 4405800 | Q34: =IFERROR(ACCRINT(COUPPCD(K34,I34,2,0),COUPNCD(K34,I34,2,0),K34,H34,N34,2,0),"") -> 132300
B35: Access bank | C35: Mauritius | D35: SADF$ | E35: Oise | F35: Sell | G35: ETINL 8 3/4 06/17/31 | H35: =IFERROR(VLOOKUP($G35,'Bonds Universe'!$D:$H,2,FALSE), "") -> 0.0875 | I35: =IFERROR(VLOOKUP($G35,'Bonds Universe'!$D:$H,3,FALSE), "") -> 48016 | J35: 45695 | K35: 45699 | L35: =IFERROR(YIELD(K35,I35,H35,M35,100,2,0),"") -> 0.089082496 | M35: 99.225 | N35: 4095000 | O35: =IFERROR((N35*M35/100)+ACCRINT(COUPPCD(K35,I35,2,0),COUPNCD(K35,I35,2,0),K35,H35,N35,2,0),N35*M35/100) -> 4117010.6 | P35: =N35*M35/100 -> 4063263.8 | Q35: =IFERROR(ACCRINT(COUPPCD(K35,I35,2,0),COUPNCD(K35,I35,2,0),K35,H35,N35,2,0),"") -> 53746.875
A36: Ram Lokan | B36: FBN UK | C36: Stanbic | D36: SMA | E36: William | F36: Buy | G36: ECOBANK 7.125% 02/16/2026 | H36: 0.07125 | I36: 46069 | J36: 45699 | K36: 45701 | L36: =IFERROR(YIELD(K36,I36,H36,M36,100,2,0),"") -> 0.081770697 | M36: 99 | N36: 394000 | O36: =IFERROR((N36*M36/100)+ACCRINT(COUPPCD(K36,I36,2,0),COUPNCD(K36,I36,2,0),K36,H36,N36,2,0),N36*M36/100) -> 403862.31 | P36: =N36*M36/100 -> 390060 | Q36: =IFERROR(ACCRINT(COUPPCD(K36,I36,2,0),COUPNCD(K36,I36,2,0),K36,H36,N36,2,0),"") -> 13802.312
A37: Ram Lokan | B37: FBN UK | C37: Stanbic | D37: SMA | E37: William | F37: Sell | G37: ECOBANK 7.125% 02/16/2026 | H37: 0.07125 | I37: 46069 | J37: 45699 | K37: 45701 | L37: =IFERROR(YIELD(K37,I37,H37,M37,100,2,0),"") -> 0.081770697 | M37: 99 | N37: 200000 | O37: =IFERROR((N37*M37/100)+ACCRINT(COUPPCD(K37,I37,2,0),COUPNCD(K37,I37,2,0),K37,H37,N37,2,0),N37*M37/100) -> 205006.25 | P37: =N37*M37/100 -> 198000 | Q37: =IFERROR(ACCRINT(COUPPCD(K37,I37,2,0),COUPNCD(K37,I37,2,0),K37,H37,N37,2,0),"") -> 7006.25
B38: Access bank | C38: Stanbic | D38: GIF$ | E38: Oise | F38: Sell | G38: ANGOL 9 1/8 11/26/49 | H38: =IFERROR(VLOOKUP($G38,'Bonds Universe'!$D:$H,2,FALSE), "") -> 0.09125 | I38: =IFERROR(VLOOKUP($G38,'Bonds Universe'!$D:$H,3,FALSE), "") -> 54753 | J38: 45708 | K38: 45712 | L38: =IFERROR(YIELD(K38,I38,H38,M38,100,2,0),"") -> 0.11399256 | M38: 81.3 | N38: 1000000 | O38: =IFERROR((N38*M38/100)+ACCRINT(COUPPCD(K38,I38,2,0),COUPNCD(K38,I38,2,0),K38,H38,N38,2,0),N38*M38/100) -> 835305.56 | P38: =N38*M38/100 -> 813000 | Q38: =IFERROR(ACCRINT(COUPPCD(K38,I38,2,0),COUPNCD(K38,I38,2,0),K38,H38,N38,2,0),"") -> 22305.556
B39: FBN UK | C39: Stanbic | D39: GIF$ | E39: Oise | F39: Sell | G39: ANGOL 9 3/8 05/08/48 | H39: =IFERROR(VLOOKUP($G39,'Bonds Universe'!$D:$H,2,FALSE), "") -> 0.09375 | I39: =IFERROR(VLOOKUP($G39,'Bonds Universe'!$D:$H,3,FALSE), "") -> 54186 | J39: 45708 | K39: 45712 | L39: =IFERROR(YIELD(K39,I39,H39,M39,100,2,0),"") -> 0.11462903 | M39: 83.125 | N39: 2280000 | O39: 1936218.8 | P39: =N39*M39/100 -> 1895250 | Q39: =IFERROR(ACCRINT(COUPPCD(K39,I39,2,0),COUPNCD(K39,I39,2,0),K39,H39,N39,2,0),"") -> 62937.5
B40: FBN UK | C40: Stanbic | D40: GIF$ | E40: Oise | F40: Sell | G40: ACCESS 9 1/8 PERP | H40: =IFERROR(VLOOKUP($G40,'Bonds Universe'!$D:$H,2,FALSE), "") -> 0.09125 | I40: =IFERROR(VLOOKUP($G40,'Bonds Universe'!$D:$H,3,FALSE), "") -> 46210 | J40: 45708 | K40: 45712 | L40: =IFERROR(YIELD(K40,I40,H40,M40,100,2,0),"") -> 0.083232058 | M40: 101 | N40: 291000 | O40: =IFERROR((N40*M40/100)+ACCRINT(COUPPCD(K40,I40,2,0),COUPNCD(K40,I40,2,0),K40,H40,N40,2,0),N40*M40/100) -> 297376.74 | P40: =N40*M40/100 -> 293910 | Q40: =IFERROR(ACCRINT(COUPPCD(K40,I40,2,0),COUPNCD(K40,I40,2,0),K40,H40,N40,2,0),"") -> 3466.7396
B41: Access bank | C41: Mauritius | D41: SADF$ | E41: Oise | F41: Sell | G41: NGERIA 9.248 01/21/49 | H41: =IFERROR(VLOOKUP($G41,'Bonds Universe'!$D:$H,2,FALSE), "") -> 0.09248 | I41: =IFERROR(VLOOKUP($G41,'Bonds Universe'!$D:$H,3,FALSE), "") -> 54444 | J41: 45719 | K41: 45721 | L41: =IFERROR(YIELD(K41,I41,H41,M41,100,2,0),"") -> 0.098710526 | M41: 94.3 | N41: 260000 | O41: =IFERROR((N41*M41/100)+ACCRINT(COUPPCD(K41,I41,2,0),COUPNCD(K41,I41,2,0),K41,H41,N41,2,0),N41*M41/100) -> 248118.81 | P41: =N41*M41/100 -> 245180 | Q41: =IFERROR(ACCRINT(COUPPCD(K41,I41,2,0),COUPNCD(K41,I41,2,0),K41,H41,N41,2,0),"") -> 2938.8089
B42: FBN UK | C42: Mauritius | D42: SADF$ | E42: Oise | F42: Sell | G42: ANGOL 9 3/8 05/08/48 | H42: =IFERROR(VLOOKUP($G42,'Bonds Universe'!$D:$H,2,FALSE), "") -> 0.09375 | I42: =IFERROR(VLOOKUP($G42,'Bonds Universe'!$D:$H,3,FALSE), "") -> 54186 | J42: 45723 | K42: 45727 | L42: =IFERROR(YIELD(K42,I42,H42,M42,100,2,0),"") -> 0.1191332 | M42: 80.125 | N42: 2000000 | O42: 1647291.7 | P42: =N42*M42/100 -> 1602500 | Q42: =IFERROR(ACCRINT(COUPPCD(K42,I42,2,0),COUPNCD(K42,I42,2,0),K42,H42,N42,2,0),"") -> 64062.5
B43: FBN UK | C43: Mauritius | D43: SADF$ | E43: Oise | F43: Sell | G43: EGYPT 8 1/2 01/31/47 | H43: =IFERROR(VLOOKUP($G43,'Bonds Universe'!$D:$H,2,FALSE), "") -> 0.085 | I43: =IFERROR(VLOOKUP($G43,'Bonds Universe'!$D:$H,3,FALSE), "") -> 53723 | J43: 45723 | K43: 45727 | L43: =IFERROR(YIELD(K43,I43,H43,M43,100,2,0),"") -> 0.11232953 | M43: 77.875 | N43: 2000000 | O43: =IFERROR((N43*M43/100)+ACCRINT(COUPPCD(K43,I43,2,0),COUPNCD(K43,I43,2,0),K43,H43,N43,2,0),N43*M43/100) -> 1576861.1 | P43: =N43*M43/100 -> 1557500 | Q43: =IFERROR(ACCRINT(COUPPCD(K43,I43,2,0),COUPNCD(K43,I43,2,0),K43,H43,N43,2,0),"") -> 19361.111
B44: FBN UK | C44: Mauritius | D44: SADF$ | E44: Oise | F44: Sell | G44: EGYPT 8 7/8 05/29/50 | H44: =IFERROR(VLOOKUP($G44,'Bonds Universe'!$D:$H,2,FALSE), "") -> 0.08875 | I44: =IFERROR(VLOOKUP($G44,'Bonds Universe'!$D:$H,3,FALSE), "") -> 54937 | J44: 45723 | K44: 45727 | L44: =IFERROR(YIELD(K44,I44,H44,M44,100,2,0),"") -> 0.11242059 | M44: 80.25 | N44: 1000000 | O44: =IFERROR((N44*M44/100)+ACCRINT(COUPPCD(K44,I44,2,0),COUPNCD(K44,I44,2,0),K44,H44,N44,2,0),N44*M44/100) -> 827645.83 | P44: =N44*M44/100 -> 802500 | Q44: =IFERROR(ACCRINT(COUPPCD(K44,I44,2,0),COUPNCD(K44,I44,2,0),K44,H44,N44,2,0),"") -> 25145.833
B45: FBN UK | C45: Mauritius | D45: SADF$ | E45: Oise | F45: Sell | G45: ANGOL 9 1/8 11/26/49 | H45: =IFERROR(VLOOKUP($G45,'Bonds Universe'!$D:$H,2,FALSE), "") -> 0.09125 | I45: =IFERROR(VLOOKUP($G45,'Bonds Universe'!$D:$H,3,FALSE), "") -> 54753 | J45: 45723 | K45: 45727 | L45: =IFERROR(YIELD(K45,I45,H45,M45,100,2,0),"") -> 0.11859299 | M45: 78.25 | N45: 450000 | O45: =IFERROR((N45*M45/100)+ACCRINT(COUPPCD(K45,I45,2,0),COUPNCD(K45,I45,2,0),K45,H45,N45,2,0),N45*M45/100) -> 364101.56 | P45: =N45*M45/100 -> 352125 | Q45: =IFERROR(ACCRINT(COUPPCD(K45,I45,2,0),COUPNCD(K45,I45,2,0),K45,H45,N45,2,0),"") -> 11976.562
B46: FBN UK | C46: Mauritius | D46: SADF$ | E46: Oise | F46: Sell | G46: ACCESS 9 1/8 PERP | H46: =IFERROR(VLOOKUP($G46,'Bonds Universe'!$D:$H,2,FALSE), "") -> 0.09125 | I46: =IFERROR(VLOOKUP($G46,'Bonds Universe'!$D:$H,3,FALSE), "") -> 46210 | J46: 45723 | K46: 45727 | L46: =IFERROR(YIELD(K46,I46,H46,M46,100,2,0),"") -> 0.091059619 | M46: 100 | N46: 1000000 | O46: =IFERROR((N46*M46/100)+ACCRINT(COUPPCD(K46,I46,2,0),COUPNCD(K46,I46,2,0),K46,H46,N46,2,0),N46*M46/100) -> 1016222.2 | P46: =N46*M46/100 -> 1000000 | Q46: =IFERROR(ACCRINT(COUPPCD(K46,I46,2,0),COUPNCD(K46,I46,2,0),K46,H46,N46,2,0),"") -> 16222.222
A47: Fractional Trade | B47: Access bank | C47: Mauritius | D47: SADF$ | E47: Oise | F47: Sell | G47: NGERIA 7.875 02/16/32 | H47: =IFERROR(VLOOKUP($G47,'Bonds Universe'!$D:$H,2,FALSE), "") -> 0.07875 | I47: =IFERROR(VLOOKUP($G47,'Bonds Universe'!$D:$H,3,FALSE), "") -> 48260 | J47: 45723 | K47: 45727 | L47: =IFERROR(YIELD(K47,I47,H47,M47,100,2,0),"") -> 0.096536766 | M47: 91.15 | N47: 315000 | O47: =IFERROR((N47*M47/100)+ACCRINT(COUPPCD(K47,I47,2,0),COUPNCD(K47,I47,2,0),K47,H47,N47,2,0),N47*M47/100) -> 288845.16 | P47: =N47*M47/100 -> 287122.5 | Q47: =IFERROR(ACCRINT(COUPPCD(K47,I47,2,0),COUPNCD(K47,I47,2,0),K47,H47,N47,2,0),"") -> 1722.6562
A48: Fractional Trade | B48: Access bank | C48: Mauritius | D48: SADF$ | E48: Oise | F48: Buy | G48: NGERIA 7.875 02/16/32 | H48: =IFERROR(VLOOKUP($G48,'Bonds Universe'!$D:$H,2,FALSE), "") -> 0.07875 | I48: =IFERROR(VLOOKUP($G48,'Bonds Universe'!$D:$H,3,FALSE), "") -> 48260 | J48: 45723 | K48: 45727 | L48: =IFERROR(YIELD(K48,I48,H48,M48,100,2,0),"") -> 0.096536766 | M48: 91.15 | N48: 200000 | O48: =IFERROR((N48*M48/100)+ACCRINT(COUPPCD(K48,I48,2,0),COUPNCD(K48,I48,2,0),K48,H48,N48,2,0),N48*M48/100) -> 183393.75 | P48: =N48*M48/100 -> 182300 | Q48: =IFERROR(ACCRINT(COUPPCD(K48,I48,2,0),COUPNCD(K48,I48,2,0),K48,H48,N48,2,0),"") -> 1093.75
B49: FBN UK | C49: Mauritius | D49: SADF$ | E49: Oise | F49: Sell | G49: ETINL 8 3/4 06/17/31 | H49: 0.0875 | I49: =IFERROR(VLOOKUP($G49,'Bonds Universe'!$D:$H,3,FALSE), "") -> 48016 | J49: 45726 | K49: 45728 | L49: =IFERROR(YIELD(K49,I49,H49,M49,100,2,0),"") -> 0.086925232 | M49: 100.25 | N49: 810000 | O49: =IFERROR((N49*M49/100)+ACCRINT(COUPPCD(K49,I49,2,0),COUPNCD(K49,I49,2,0),K49,H49,N49,2,0),N49*M49/100) -> 828759.38 | P49: =N49*M49/100 -> 812025 | Q49: =IFERROR(ACCRINT(COUPPCD(K49,I49,2,0),COUPNCD(K49,I49,2,0),K49,H49,N49,2,0),"") -> 16734.375
B50: FBN UK | C50: Mauritius | D50: SADF$ | E50: Oise | F50: Sell | G50: ACCESS 9 1/8 PERP | H50: 0.09125 | I50: =IFERROR(VLOOKUP($G50,'Bonds Universe'!$D:$H,3,FALSE), "") -> 46210 | J50: 45726 | K50: 45728 | L50: =IFERROR(YIELD(K50,I50,H50,M50,100,2,0),"") -> 0.094139616 | M50: 99.625 | N50: 1000000 | O50: =IFERROR((N50*M50/100)+ACCRINT(COUPPCD(K50,I50,2,0),COUPNCD(K50,I50,2,0),K50,H50,N50,2,0),N50*M50/100) -> 1012725.7 | P50: =N50*M50/100 -> 996250 | Q50: =IFERROR(ACCRINT(COUPPCD(K50,I50,2,0),COUPNCD(K50,I50,2,0),K50,H50,N50,2,0),"") -> 16475.694
B51: FBN UK | C51: Mauritius | D51: SADF$ | E51: Oise | F51: Sell | G51: ANGOL 8 3/4 04/14/32 | H51: 0.0875 | I51: 48318 | J51: 45726 | K51: 45728 | L51: =IFERROR(YIELD(K51,I51,H51,M51,100,2,0),"") -> 0.11504164 | M51: 86.875 | N51: 600000 | O51: =IFERROR((N51*M51/100)+ACCRINT(COUPPCD(K51,I51,2,0),COUPNCD(K51,I51,2,0),K51,H51,N51,2,0),N51*M51/100) -> 542833.33 | P51: =N51*M51/100 -> 521250 | Q51: =IFERROR(ACCRINT(COUPPCD(K51,I51,2,0),COUPNCD(K51,I51,2,0),K51,H51,N51,2,0),"") -> 21583.333
B52: FBN UK | C52: Mauritius | D52: SADF$ | E52: Oise | F52: Sell | G52: EGYPT 8 1/2 01/31/47 | H52: 0.085 | I52: 53723 | J52: 45726 | K52: 45728 | L52: =IFERROR(YIELD(K52,I52,H52,M52,100,2,0),"") -> 0.11328586 | M52: 77.25 | N52: 1000000 | O52: =IFERROR((N52*M52/100)+ACCRINT(COUPPCD(K52,I52,2,0),COUPNCD(K52,I52,2,0),K52,H52,N52,2,0),N52*M52/100) -> 782416.67 | P52: =N52*M52/100 -> 772500 | Q52: =IFERROR(ACCRINT(COUPPCD(K52,I52,2,0),COUPNCD(K52,I52,2,0),K52,H52,N52,2,0),"") -> 9916.6667
B53: FBN UK | C53: Mauritius | D53: SADF$ | E53: Oise | F53: Sell | G53: ANGOL 9 3/8 05/08/48 | H53: 0.09375 | I53: 54186 | J53: 45726 | K53: 45728 | L53: =IFERROR(YIELD(K53,I53,H53,M53,100,2,0),"") -> 0.12030231 | M53: 79.375 | N53: 1000000 | O53: 816406.25 | P53: =N53*M53/100 -> 793750 | Q53: 22656.25
B54: FBN UK | C54: Mauritius | D54: SADF$ | E54: Oise | F54: Sell | G54: EGYPT 8 1/2 01/31/47 | H54: 0.085 | I54: 53723 | J54: 45726 | K54: 45728 | L54: =IFERROR(YIELD(K54,I54,H54,M54,100,2,0),"") -> 0.11405992 | M54: 76.75 | N54: 1000000 | O54: =IFERROR((N54*M54/100)+ACCRINT(COUPPCD(K54,I54,2,0),COUPNCD(K54,I54,2,0),K54,H54,N54,2,0),N54*M54/100) -> 777416.67 | P54: =N54*M54/100 -> 767500 | Q54: =IFERROR(ACCRINT(COUPPCD(K54,I54,2,0),COUPNCD(K54,I54,2,0),K54,H54,N54,2,0),"") -> 9916.6667
B55: FBN UK | C55: Mauritius | D55: SADF$ | E55: Oise | F55: Sell | G55: ANGOL 9 3/8 05/08/48 | H55: 0.09375 | I55: 54186 | J55: 45726 | K55: 45728 | L55: =IFERROR(YIELD(K55,I55,H55,M55,100,2,0),"") -> 0.12030231 | M55: 79.375 | N55: 1000000 | O55: 816406.25 | P55: =N55*M55/100 -> 793750 | Q55: =IFERROR(ACCRINT(COUPPCD(K55,I55,2,0),COUPNCD(K55,I55,2,0),K55,H55,N55,2,0),"") -> 32291.667
B56: Access bank | C56: Mauritius | D56: SADF$ | E56: Oise | F56: Sell | G56: NGERIA 7.696 02/23/38 | H56: =IFERROR(VLOOKUP($G56,'Bonds Universe'!$D:$H,2,FALSE), "") -> 0.07696 | I56: =IFERROR(VLOOKUP($G56,'Bonds Universe'!$D:$H,3,FALSE), "") -> 50459 | J56: 45726 | K56: 45728 | L56: =IFERROR(YIELD(K56,I56,H56,M56,100,2,0),"") -> 0.10065759 | M56: 83.05 | N56: 1000000 | O56: =IFERROR((N56*M56/100)+ACCRINT(COUPPCD(K56,I56,2,0),COUPNCD(K56,I56,2,0),K56,H56,N56,2,0),N56*M56/100) -> 834561.78 | P56: =N56*M56/100 -> 830500 | Q56: =IFERROR(ACCRINT(COUPPCD(K56,I56,2,0),COUPNCD(K56,I56,2,0),K56,H56,N56,2,0),"") -> 4061.7778
B57: Access bank | C57: Mauritius | D57: SADF$ | E57: Oise | F57: Sell | G57: NGERIA 8 3/8 3/24/29 | H57: =IFERROR(VLOOKUP($G57,'Bonds Universe'!$D:$H,2,FALSE), "") -> 0.08375 | I57: =IFERROR(VLOOKUP($G57,'Bonds Universe'!$D:$H,3,FALSE), "") -> 47201 | J57: 45726 | K57: 45728 | L57: =IFERROR(YIELD(K57,I57,H57,M57,100,2,0),"") -> 0.088536522 | M57: 98.4 | N57: 2070000 | O57: =IFERROR((N57*M57/100)+ACCRINT(COUPPCD(K57,I57,2,0),COUPNCD(K57,I57,2,0),K57,H57,N57,2,0),N57*M57/100) -> 2117782.5 | P57: =N57*M57/100 -> 2036880 | Q57: =IFERROR(ACCRINT(COUPPCD(K57,I57,2,0),COUPNCD(K57,I57,2,0),K57,H57,N57,2,0),"") -> 80902.5
B58: FBN UK | C58: Mauritius | D58: SADF$ | E58: Oise | F58: Sell | G58: ACCESS 9 1/8 PERP | H58: 0.09125 | I58: =IFERROR(VLOOKUP($G58,'Bonds Universe'!$D:$H,3,FALSE), "") -> 46210 | J58: 45727 | K58: 45729 | L58: =IFERROR(YIELD(K58,I58,H58,M58,100,2,0),"") -> 0.10036892 | M58: 98.875 | N58: 1000000 | O58: =IFERROR((N58*M58/100)+ACCRINT(COUPPCD(K58,I58,2,0),COUPNCD(K58,I58,2,0),K58,H58,N58,2,0),N58*M58/100) -> 1005479.2 | P58: =N58*M58/100 -> 988750 | Q58: =IFERROR(ACCRINT(COUPPCD(K58,I58,2,0),COUPNCD(K58,I58,2,0),K58,H58,N58,2,0),"") -> 16729.167
B59: BCP Securities | C59: Mauritius | D59: SADF$ | E59: Oise | F59: Sell | G59: NGERIA 8 3/8 3/24/29 | H59: 0.08375 | I59: =IFERROR(VLOOKUP($G59,'Bonds Universe'!$D:$H,3,FALSE), "") -> 47201 | J59: 45727 | K59: 45729 | L59: =IFERROR(YIELD(K59,I59,H59,M59,100,2,0),"") -> 0.090443957 | M59: 97.775 | N59: 1000000 | O59: =IFERROR((N59*M59/100)+ACCRINT(COUPPCD(K59,I59,2,0),COUPNCD(K59,I59,2,0),K59,H59,N59,2,0),N59*M59/100) -> 1017066 | P59: =N59*M59/100 -> 977750 | Q59: =IFERROR(ACCRINT(COUPPCD(K59,I59,2,0),COUPNCD(K59,I59,2,0),K59,H59,N59,2,0),"") -> 39315.972
B60: BCP Securities | C60: Mauritius | D60: SADF$ | E60: Oise | F60: Sell | G60: NGERIA 7.696 02/23/38 | H60: 0.07696 | I60: =IFERROR(VLOOKUP($G60,'Bonds Universe'!$D:$H,3,FALSE), "") -> 50459 | J60: 45727 | K60: 45729 | L60: =IFERROR(YIELD(K60,I60,H60,M60,100,2,0),"") -> 0.10194239 | M60: 82.25 | N60: 1000000 | O60: =IFERROR((N60*M60/100)+ACCRINT(COUPPCD(K60,I60,2,0),COUPNCD(K60,I60,2,0),K60,H60,N60,2,0),N60*M60/100) -> 826775.56 | P60: =N60*M60/100 -> 822500 | Q60: =IFERROR(ACCRINT(COUPPCD(K60,I60,2,0),COUPNCD(K60,I60,2,0),K60,H60,N60,2,0),"") -> 4275.5556
B61: BCP Securities | C61: Mauritius | D61: SADF$ | E61: Oise | F61: Sell | G61: ANGOL 9 3/8 05/08/48 | H61: 0.09375 | I61: =IFERROR(VLOOKUP($G61,'Bonds Universe'!$D:$H,3,FALSE), "") -> 54186 | J61: 45727 | K61: 45729 | L61: =IFERROR(YIELD(K61,I61,H61,M61,100,2,0),"") -> 0.12050004 | M61: 79.25 | N61: 1933000 | O61: 1576200.4 | P61: =N61*M61/100 -> 1531902.5 | Q61: 44297.92
B62: BCP Securities | C62: Mauritius | D62: SADF$ | E62: Oise | F62: Sell | G62: EGYPT 8 1/2 01/31/47 | H62: 0.085 | I62: =IFERROR(VLOOKUP($G62,'Bonds Universe'!$D:$H,3,FALSE), "") -> 53723 | J62: 45727 | K62: 45729 | L62: =IFERROR(YIELD(K62,I62,H62,M62,100,2,0),"") -> 0.11328639 | M62: 77.25 | N62: 1315000 | O62: =IFERROR((N62*M62/100)+ACCRINT(COUPPCD(K62,I62,2,0),COUPNCD(K62,I62,2,0),K62,H62,N62,2,0),N62*M62/100) -> 1029188.4 | P62: =N62*M62/100 -> 1015837.5 | Q62: =IFERROR(ACCRINT(COUPPCD(K62,I62,2,0),COUPNCD(K62,I62,2,0),K62,H62,N62,2,0),"") -> 13350.903
B63: Access bank | C63: Mauritius | D63: SADF$ | E63: Oise | F63: Sell | G63: NGERIA 7.696 02/23/38 | H63: 0.07696 | I63: =IFERROR(VLOOKUP($G63,'Bonds Universe'!$D:$H,3,FALSE), "") -> 50459 | J63: 45727 | K63: 45729 | L63: =IFERROR(YIELD(K63,I63,H63,M63,100,2,0),"") -> 0.10170058 | M63: 82.4 | N63: 820000 | O63: =IFERROR((N63*M63/100)+ACCRINT(COUPPCD(K63,I63,2,0),COUPNCD(K63,I63,2,0),K63,H63,N63,2,0),N63*M63/100) -> 679185.96 | P63: =N63*M63/100 -> 675680 | Q63: =IFERROR(ACCRINT(COUPPCD(K63,I63,2,0),COUPNCD(K63,I63,2,0),K63,H63,N63,2,0),"") -> 3505.9556
B64: Access bank | C64: Mauritius | D64: SADF$ | E64: Oise | F64: Sell | G64: NGERIA 8 3/8 3/24/29 | H64: 0.08375 | I64: =IFERROR(VLOOKUP($G64,'Bonds Universe'!$D:$H,3,FALSE), "") -> 47201 | J64: 45727 | K64: 45729 | L64: =IFERROR(YIELD(K64,I64,H64,M64,100,2,0),"") -> 0.090443957 | M64: 97.775 | N64: 1000000 | O64: =IFERROR((N64*M64/100)+ACCRINT(COUPPCD(K64,I64,2,0),COUPNCD(K64,I64,2,0),K64,H64,N64,2,0),N64*M64/100) -> 1017066 | P64: =N64*M64/100 -> 977750 | Q64: =IFERROR(ACCRINT(COUPPCD(K64,I64,2,0),COUPNCD(K64,I64,2,0),K64,H64,N64,2,0),"") -> 39315.972
B65: FBN UK | C65: Mauritius | D65: SADF$ | E65: Oise | F65: Sell | G65: ACCESS 9 1/8 PERP | H65: 0.09125 | I65: =IFERROR(VLOOKUP($G65,'Bonds Universe'!$D:$H,3,FALSE), "") -> 46210 | J65: 45729 | K65: 45733 | L65: =IFERROR(YIELD(K65,I65,H65,M65,100,2,0),"") -> 0.10718704 | M65: 98.077 | N65: 1000000 | O65: =IFERROR((N65*M65/100)+ACCRINT(COUPPCD(K65,I65,2,0),COUPNCD(K65,I65,2,0),K65,H65,N65,2,0),N65*M65/100) -> 998513.06 | P65: =N65*M65/100 -> 980770 | Q65: =IFERROR(ACCRINT(COUPPCD(K65,I65,2,0),COUPNCD(K65,I65,2,0),K65,H65,N65,2,0),"") -> 17743.056
B66: FBN UK | C66: Mauritius | D66: SADF$ | E66: Oise | F66: Sell | G66: ACCESS 9 1/8 PERP | H66: 0.09125 | I66: 46210 | J66: 45728 | K66: 45730 | L66: =IFERROR(YIELD(K66,I66,H66,M66,100,2,0),"") -> 0.1088064 | M66: 97.875 | N66: 1000000 | O66: =IFERROR((N66*M66/100)+ACCRINT(COUPPCD(K66,I66,2,0),COUPNCD(K66,I66,2,0),K66,H66,N66,2,0),N66*M66/100) -> 995732.64 | P66: =N66*M66/100 -> 978750 | Q66: =IFERROR(ACCRINT(COUPPCD(K66,I66,2,0),COUPNCD(K66,I66,2,0),K66,H66,N66,2,0),"") -> 16982.639
B67: Access bank | C67: Mauritius | D67: SADF$ | E67: Oise | F67: Sell | G67: ACCESS 9 1/8 PERP | H67: 0.09125 | I67: 46210 | J67: 45730 | K67: 45734 | L67: =IFERROR(YIELD(K67,I67,H67,M67,100,2,0),"") -> 0.11001194 | M67: 97.75 | N67: 1600000 | O67: =IFERROR((N67*M67/100)+ACCRINT(COUPPCD(K67,I67,2,0),COUPNCD(K67,I67,2,0),K67,H67,N67,2,0),N67*M67/100) -> 1592794.4 | P67: =N67*M67/100 -> 1564000 | Q67: =IFERROR(ACCRINT(COUPPCD(K67,I67,2,0),COUPNCD(K67,I67,2,0),K67,H67,N67,2,0),"") -> 28794.444
A68: Fractional Trade | B68: Access bank | C68: Stanbic | D68: SMA | E68: William | F68: Buy | G68: NGERIA 10.375 12/09/34 | H68: 0.10375 | I68: 49287 | J68: 45742 | K68: 45744 | L68: =IFERROR(YIELD(K68,I68,H68,M68,100,2,0),"") -> 0.099701153 | M68: 102.45 | N68: 388000 | O68: =IFERROR((N68*M68/100)+ACCRINT(COUPPCD(K68,I68,2,0),COUPNCD(K68,I68,2,0),K68,H68,N68,2,0),N68*M68/100) -> 409694.32 | P68: =N68*M68/100 -> 397506 | Q68: =IFERROR(ACCRINT(COUPPCD(K68,I68,2,0),COUPNCD(K68,I68,2,0),K68,H68,N68,2,0),"") -> 12188.319
A69: Fractional Trade | B69: Access bank | C69: Stanbic | D69: SMA | E69: William | F69: Sell | G69: NGERIA 10.375 12/09/34 | H69: 0.10375 | I69: 49287 | J69: 45742 | K69: 45744 | L69: =IFERROR(YIELD(K69,I69,H69,M69,100,2,0),"") -> 0.099701153 | M69: 102.45 | N69: 200000 | O69: =IFERROR((N69*M69/100)+ACCRINT(COUPPCD(K69,I69,2,0),COUPNCD(K69,I69,2,0),K69,H69,N69,2,0),N69*M69/100) -> 211182.64 | P69: =N69*M69/100 -> 204900 | Q69: =IFERROR(ACCRINT(COUPPCD(K69,I69,2,0),COUPNCD(K69,I69,2,0),K69,H69,N69,2,0),"") -> 6282.6389
B70: Access bank | C70: Stanbic | D70: SADF$ | E70: Fareed | F70: Buy | G70: NGERIA 8.747 01/21/31 | H70: 0.08747 | I70: 47869 | J70: 45744 | K70: 45748 | L70: =IFERROR(YIELD(K70,I70,H70,M70,100,2,0),"") -> 0.095814348 | M70: 96.325 | N70: 1100000 | O70: =IFERROR((N70*M70/100)+ACCRINT(COUPPCD(K70,I70,2,0),COUPNCD(K70,I70,2,0),K70,H70,N70,2,0),N70*M70/100) -> 1078283.9 | P70: =N70*M70/100 -> 1059575 | Q70: =IFERROR(ACCRINT(COUPPCD(K70,I70,2,0),COUPNCD(K70,I70,2,0),K70,H70,N70,2,0),"") -> 18708.861
B71: BCP Securities | C71: Stanbic | D71: SADF$ | E71: Fareed | F71: Buy | G71: NGERIA 8 3/8 3/24/29 | H71: 0.08375 | I71: 47201 | J71: 45744 | K71: 45749 | L71: =IFERROR(YIELD(K71,I71,H71,M71,100,2,0),"") -> 0.091685514 | M71: 97.4 | N71: 1100000 | O71: =IFERROR((N71*M71/100)+ACCRINT(COUPPCD(K71,I71,2,0),COUPNCD(K71,I71,2,0),K71,H71,N71,2,0),N71*M71/100) -> 1073447.2 | P71: =N71*M71/100 -> 1071400 | Q71: =IFERROR(ACCRINT(COUPPCD(K71,I71,2,0),COUPNCD(K71,I71,2,0),K71,H71,N71,2,0),"") -> 2047.2222
B72: FBN UK | C72: Stanbic | D72: SMA | E72: William | F72: Buy | G72: SEPLAT 9.125 03/21/30 | H72: 0.09125 | I72: 47563 | J72: 45751 | K72: 45755 | L72: =IFERROR(YIELD(K72,I72,H72,M72,100,2,0),"") -> 0.093474595 | M72: 99.125 | N72: 475000 | O72: =IFERROR((N72*M72/100)+ACCRINT(COUPPCD(K72,I72,2,0),COUPNCD(K72,I72,2,0),K72,H72,N72,2,0),N72*M72/100) -> 472890.54 | P72: =N72*M72/100 -> 470843.75 | Q72: =IFERROR(ACCRINT(COUPPCD(K72,I72,2,0),COUPNCD(K72,I72,2,0),K72,H72,N72,2,0),"") -> 2046.7882
B73: FBN UK | C73: Stanbic | D73: SMA | E73: William | F73: Buy | G73: SEPLAT 9.125 03/21/30 | H73: 0.09125 | I73: 47563 | J73: 45751 | K73: 45755 | L73: =IFERROR(YIELD(K73,I73,H73,M73,100,2,0),"") -> 0.092830173 | M73: 99.375 | N73: 335000 | O73: =IFERROR((N73*M73/100)+ACCRINT(COUPPCD(K73,I73,2,0),COUPNCD(K73,I73,2,0),K73,H73,N73,2,0),N73*M73/100) -> 334349.77 | P73: =N73*M73/100 -> 332906.25 | Q73: =IFERROR(ACCRINT(COUPPCD(K73,I73,2,0),COUPNCD(K73,I73,2,0),K73,H73,N73,2,0),"") -> 1443.5243
B74: Access bank | C74: Stanbic | D74: SADF$ | E74: Fareed | F74: Buy | G74: NGERIA 8 3/8 3/24/29 | H74: 0.08375 | I74: 47201 | J74: 45744 | K74: 45748 | L74: =IFERROR(YIELD(K74,I74,H74,M74,100,2,0),"") -> 0.091837587 | M74: 97.35 | N74: 3000000 | O74: =IFERROR((N74*M74/100)+ACCRINT(COUPPCD(K74,I74,2,0),COUPNCD(K74,I74,2,0),K74,H74,N74,2,0),N74*M74/100) -> 2925385.4 | P74: =N74*M74/100 -> 2920500 | Q74: =IFERROR(ACCRINT(COUPPCD(K74,I74,2,0),COUPNCD(K74,I74,2,0),K74,H74,N74,2,0),"") -> 4885.4167
B75: Access bank | C75: Stanbic | D75: SADF$ | E75: Fareed | F75: Buy | G75: ANGOL 8.75 04/14/2032 | H75: 0.0875 | I75: =IFERROR(VLOOKUP($G75,'Bonds Universe'!$D:$H,3,FALSE), "") -> 48318 | J75: 45754 | K75: 45756 | L75: =IFERROR(YIELD(K75,I75,H75,M75,100,2,0),"") -> 0.140032 | M75: 77 | N75: 1000000 | O75: 812534.72 | P75: =N75*M75/100 -> 770000 | Q75: =IFERROR(ACCRINT(COUPPCD(K75,I75,2,0),COUPNCD(K75,I75,2,0),K75,H75,N75,2,0),"") -> 42534.722
B76: KNG | C76: Stanbic | D76: SADF$ | E76: Fareed | F76: Buy | G76: NGERIA 7.875 02/16/32 | H76: 0.07875 | I76: 48260 | J76: 45754 | K76: 45756 | L76: =IFERROR(YIELD(K76,I76,H76,M76,100,2,0),"") -> 0.11806287 | M76: 81.85 | N76: 1000000 | O76: =IFERROR((N76*M76/100)+ACCRINT(COUPPCD(K76,I76,2,0),COUPNCD(K76,I76,2,0),K76,H76,N76,2,0),N76*M76/100) -> 830093.75 | P76: =N76*M76/100 -> 818500 | Q76: =IFERROR(ACCRINT(COUPPCD(K76,I76,2,0),COUPNCD(K76,I76,2,0),K76,H76,N76,2,0),"") -> 11593.75
B77: KNG | C77: Stanbic | D77: SADF$ | E77: Fareed | F77: Buy | G77: ANGOL 8 1/4 05/09/28 | H77: 0.0825 | I77: =IFERROR(VLOOKUP($G77,'Bonds Universe'!$D:$H,3,FALSE), "") -> 46882 | J77: 45754 | K77: 45756 | L77: =IFERROR(YIELD(K77,I77,H77,M77,100,2,0),"") -> 0.14785565 | M77: 84.25 | N77: 1000000 | O77: 868625 | P77: =N77*M77/100 -> 842500 | Q77: =IFERROR(ACCRINT(COUPPCD(K77,I77,2,0),COUPNCD(K77,I77,2,0),K77,H77,N77,2,0),"") -> 34375
B78: FBN UK | C78: Stanbic | D78: SADF$ | E78: Fareed | F78: Buy | G78: ANGOL 9 1/2 11/12/25 | H78: =IFERROR(VLOOKUP($G78,'Bonds Universe'!$D:$H,2,FALSE), "") -> 0.095 | I78: =IFERROR(VLOOKUP($G78,'Bonds Universe'!$D:$H,3,FALSE), "") -> 45973 | J78: 45755 | K78: 45757 | L78: =IFERROR(YIELD(K78,I78,H78,M78,100,2,0),"") -> 0.15435796 | M78: 96.75 | N78: 1000000 | O78: =IFERROR((N78*M78/100)+ACCRINT(COUPPCD(K78,I78,2,0),COUPNCD(K78,I78,2,0),K78,H78,N78,2,0),N78*M78/100) -> 1006555.6 | P78: =N78*M78/100 -> 967500 | Q78: =IFERROR(ACCRINT(COUPPCD(K78,I78,2,0),COUPNCD(K78,I78,2,0),K78,H78,N78,2,0),"") -> 39055.556
B79: FBN UK | C79: Stanbic | D79: SADF$ | E79: Fareed | F79: Buy | G79: KENINT 9 1/2 03/05/36 | H79: 0.095 | I79: 49739 | J79: 45755 | K79: 45757 | L79: =IFERROR(YIELD(K79,I79,H79,M79,100,2,0),"") -> 0.1199857 | M79: 85 | N79: 1000000 | O79: =IFERROR((N79*M79/100)+ACCRINT(COUPPCD(K79,I79,2,0),COUPNCD(K79,I79,2,0),K79,H79,N79,2,0),N79*M79/100) -> 859236.11 | P79: =N79*M79/100 -> 850000 | Q79: =IFERROR(ACCRINT(COUPPCD(K79,I79,2,0),COUPNCD(K79,I79,2,0),K79,H79,N79,2,0),"") -> 9236.1111
B80: FBN UK | C80: Stanbic | D80: SADF$ | E80: Fareed | F80: Buy | G80: ANGOL 8 1/4 05/09/28 | H80: 0.0825 | I80: =IFERROR(VLOOKUP($G80,'Bonds Universe'!$D:$H,3,FALSE), "") -> 46882 | J80: 45755 | K80: 45757 | L80: =IFERROR(YIELD(K80,I80,H80,M80,100,2,0),"") -> 0.14217635 | M80: 85.5 | N80: 1000000 | O80: 881354.17 | P80: =N80*M80/100 -> 855000 | Q80: =IFERROR(ACCRINT(COUPPCD(K80,I80,2,0),COUPNCD(K80,I80,2,0),K80,H80,N80,2,0),"") -> 34604.167
B81: FBN UK | C81: Stanbic | D81: SADF$ | E81: Fareed | F81: Buy | G81: KENINT 9 1/2 03/05/36 | H81: 0.095 | I81: 49739 | J81: 45755 | K81: 45757 | L81: =IFERROR(YIELD(K81,I81,H81,M81,100,2,0),"") -> 0.1199857 | M81: 85 | N81: 1000000 | O81: =IFERROR((N81*M81/100)+ACCRINT(COUPPCD(K81,I81,2,0),COUPNCD(K81,I81,2,0),K81,H81,N81,2,0),N81*M81/100) -> 859236.11 | P81: =N81*M81/100 -> 850000 | Q81: =IFERROR(ACCRINT(COUPPCD(K81,I81,2,0),COUPNCD(K81,I81,2,0),K81,H81,N81,2,0),"") -> 9236.1111
B82: FBN UK | C82: Stanbic | D82: SADF$ | E82: Fareed | F82: Buy | G82: KENINT 9 1/2 03/05/36 | H82: 0.095 | I82: 49739 | J82: 45755 | K82: 45757 | L82: =IFERROR(YIELD(K82,I82,H82,M82,100,2,0),"") -> 0.11836178 | M82: 85.875 | N82: 1100000 | O82: =IFERROR((N82*M82/100)+ACCRINT(COUPPCD(K82,I82,2,0),COUPNCD(K82,I82,2,0),K82,H82,N82,2,0),N82*M82/100) -> 954784.72 | P82: =N82*M82/100 -> 944625 | Q82: =IFERROR(ACCRINT(COUPPCD(K82,I82,2,0),COUPNCD(K82,I82,2,0),K82,H82,N82,2,0),"") -> 10159.722
B83: FBN UK | C83: Stanbic | D83: SADF$ | E83: Fareed | F83: Buy | G83: NGERIA 8 1/4 09/28/51 | H83: 0.0825 | I83: 55424 | J83: 45755 | K83: 45757 | L83: =IFERROR(YIELD(K83,I83,H83,M83,100,2,0),"") -> 0.11373469 | M83: 74 | N83: 2600000 | O83: =IFERROR((N83*M83/100)+ACCRINT(COUPPCD(K83,I83,2,0),COUPNCD(K83,I83,2,0),K83,H83,N83,2,0),N83*M83/100) -> 1931150 | P83: =N83*M83/100 -> 1924000 | Q83: =IFERROR(ACCRINT(COUPPCD(K83,I83,2,0),COUPNCD(K83,I83,2,0),K83,H83,N83,2,0),"") -> 7150
B84: BCP Securities | C84: Stanbic | D84: SADF$ | E84: Fareed | F84: Buy | G84: ANGOL 8 1/4 05/09/28 | H84: 0.0825 | I84: 46882 | J84: 45755 | K84: 45757 | L84: =IFERROR(YIELD(K84,I84,H84,M84,100,2,0),"") -> 0.14158602 | M84: 85.63 | N84: 1900000 | O84: 1677042.9 | P84: =N84*M84/100 -> 1626970 | Q84: =IFERROR(ACCRINT(COUPPCD(K84,I84,2,0),COUPNCD(K84,I84,2,0),K84,H84,N84,2,0),"") -> 65747.917
B85: KNG | C85: Stanbic | D85: SADF$ | E85: Fareed | F85: Buy | G85: ANGOL 8 1/4 05/09/28 | H85: 0.0825 | I85: 46882 | J85: 45755 | K85: 45757 | L85: =IFERROR(YIELD(K85,I85,H85,M85,100,2,0),"") -> 0.14331475 | M85: 85.25 | N85: 2000000 | O85: 1757708.3 | P85: =N85*M85/100 -> 1705000 | Q85: =IFERROR(ACCRINT(COUPPCD(K85,I85,2,0),COUPNCD(K85,I85,2,0),K85,H85,N85,2,0),"") -> 69208.333
B86: FBN UK | C86: Stanbic | D86: SADF$ | E86: Fareed | F86: Buy | G86: ACCESS 9 1/8 PERP | H86: 0.09125 | I86: =IFERROR(VLOOKUP($G86,'Bonds Universe'!$D:$H,3,FALSE), "") -> 46210 | J86: 45757 | K86: 45761 | L86: =IFERROR(YIELD(K86,I86,H86,M86,100,2,0),"") -> 0.13172351 | M86: 95.5 | N86: 500000 | O86: =IFERROR((N86*M86/100)+ACCRINT(COUPPCD(K86,I86,2,0),COUPNCD(K86,I86,2,0),K86,H86,N86,2,0),N86*M86/100) -> 489793.4 | P86: =N86*M86/100 -> 477500 | Q86: =IFERROR(ACCRINT(COUPPCD(K86,I86,2,0),COUPNCD(K86,I86,2,0),K86,H86,N86,2,0),"") -> 12293.403
B87: FBN UK | C87: Stanbic | D87: SADF$ | E87: Fareed | F87: Buy | G87: KENINT 9 1/2 03/05/36 | H87: 0.095 | I87: 49739 | J87: 45755 | K87: 45757 | L87: =IFERROR(YIELD(K87,I87,H87,M87,100,2,0),"") -> 0.1199857 | M87: 85 | N87: 1000000 | O87: =IFERROR((N87*M87/100)+ACCRINT(COUPPCD(K87,I87,2,0),COUPNCD(K87,I87,2,0),K87,H87,N87,2,0),N87*M87/100) -> 859236.11 | P87: =N87*M87/100 -> 850000 | Q87: =IFERROR(ACCRINT(COUPPCD(K87,I87,2,0),COUPNCD(K87,I87,2,0),K87,H87,N87,2,0),"") -> 9236.1111
B88: FBN UK | C88: Stanbic | D88: SADF$ | E88: Fareed | F88: Buy | G88: ANGOL 8 1/4 05/09/28 | H88: 0.0825 | I88: 46882 | J88: 45755 | K88: 45757 | L88: =IFERROR(YIELD(K88,I88,H88,M88,100,2,0),"") -> 0.1416087 | M88: 85.625 | N88: 2000000 | O88: 1765208.3 | P88: =N88*M88/100 -> 1712500 | Q88: =IFERROR(ACCRINT(COUPPCD(K88,I88,2,0),COUPNCD(K88,I88,2,0),K88,H88,N88,2,0),"") -> 69208.333
B89: FBN UK | C89: Mauritius | D89: SADF$ | E89: Fareed | F89: Buy | G89: ANGOL 8.75 04/14/2032 | H89: 0.0875 | I89: 48318 | J89: 45771 | K89: 45775 | L89: =IFERROR(YIELD(K89,I89,H89,M89,100,2,0),"") -> 0.13329811 | M89: 79.625 | N89: 1000000 | O89: =IFERROR((N89*M89/100)+ACCRINT(COUPPCD(K89,I89,2,0),COUPNCD(K89,I89,2,0),K89,H89,N89,2,0),N89*M89/100) -> 799652.78 | P89: =N89*M89/100 -> 796250 | Q89: =IFERROR(ACCRINT(COUPPCD(K89,I89,2,0),COUPNCD(K89,I89,2,0),K89,H89,N89,2,0),"") -> 3402.7778
B90: FBN UK | C90: Stanbic | D90: SADF$ | E90: Fareed | F90: Buy | G90: ANGOL 8.75 04/14/2032 | H90: 0.0875 | I90: 48318 | J90: 45771 | K90: 45775 | L90: =IFERROR(YIELD(K90,I90,H90,M90,100,2,0),"") -> 0.13362458 | M90: 79.5 | N90: 1000000 | O90: =IFERROR((N90*M90/100)+ACCRINT(COUPPCD(K90,I90,2,0),COUPNCD(K90,I90,2,0),K90,H90,N90,2,0),N90*M90/100) -> 798402.78 | P90: =N90*M90/100 -> 795000 | Q90: =IFERROR(ACCRINT(COUPPCD(K90,I90,2,0),COUPNCD(K90,I90,2,0),K90,H90,N90,2,0),"") -> 3402.7778
B91: KNG | C91: Mauritius | D91: SADF$ | E91: Fareed | F91: Buy | G91: ANGOL 8.75 04/14/2032 | H91: 0.0875 | I91: 48318 | J91: 45771 | K91: 45775 | L91: =IFERROR(YIELD(K91,I91,H91,M91,100,2,0),"") -> 0.13427952 | M91: 79.25 | N91: 1000000 | O91: =IFERROR((N91*M91/100)+ACCRINT(COUPPCD(K91,I91,2,0),COUPNCD(K91,I91,2,0),K91,H91,N91,2,0),N91*M91/100) -> 795902.78 | P91: =N91*M91/100 -> 792500 | Q91: =IFERROR(ACCRINT(COUPPCD(K91,I91,2,0),COUPNCD(K91,I91,2,0),K91,H91,N91,2,0),"") -> 3402.7778
B92: Aztran | C92: Stanbic | D92: SADF$ | E92: Fareed | F92: Buy | G92: ANGOL 8.75 04/14/2032 | H92: 0.0875 | I92: 48318 | J92: 45771 | K92: 45775 | L92: =IFERROR(YIELD(K92,I92,H92,M92,100,2,0),"") -> 0.13493715 | M92: 79 | N92: 1000000 | O92: =IFERROR((N92*M92/100)+ACCRINT(COUPPCD(K92,I92,2,0),COUPNCD(K92,I92,2,0),K92,H92,N92,2,0),N92*M92/100) -> 793402.78 | P92: =N92*M92/100 -> 790000 | Q92: =IFERROR(ACCRINT(COUPPCD(K92,I92,2,0),COUPNCD(K92,I92,2,0),K92,H92,N92,2,0),"") -> 3402.7778
A93: Repo with StoneX | B93: StoneX | C93: Stanbic | D93: SADF$ | E93: Fareed | F93: Sell | G93: NGERIA 7.875 02/16/32 | H93: 0.07875 | I93: 48260 | J93: 45782 | K93: 45783 | L93: =IFERROR(YIELD(K93,I93,H93,M93,100,2,0),"") -> 0.10607513 | M93: 87 | N93: 200000 | O93: 139203.2 | Q93: =IFERROR(ACCRINT(COUPPCD(K93,I93,2,0),COUPNCD(K93,I93,2,0),K93,H93,N93,2,0),"") -> 3500
A94: Repo with StoneX | B94: StoneX | C94: Stanbic | D94: SADF$ | E94: Fareed | F94: Buy | G94: NGERIA 7.875 02/16/32 | H94: 0.07875 | I94: 48260 | J94: 45782 | K94: 45784 | L94: =IFERROR(YIELD(K94,I94,H94,M94,100,2,0),"") -> 0.10608343 | M94: 87 | N94: 200000 | O94: 139207.07 | Q94: =IFERROR(ACCRINT(COUPPCD(K94,I94,2,0),COUPNCD(K94,I94,2,0),K94,H94,N94,2,0),"") -> 3543.75
B95: KNG | C95: Stanbic | D95: SADF$ | E95: Fareed | F95: Buy | G95: NGERIA 10.375 12/09/34 | H95: 0.10375 | I95: 49287 | J95: 45785 | K95: 45789 | L95: =IFERROR(YIELD(K95,I95,H95,M95,100,2,0),"") -> 0.11059657 | M95: 96 | N95: 750000 | O95: =IFERROR((N95*M95/100)+ACCRINT(COUPPCD(K95,I95,2,0),COUPNCD(K95,I95,2,0),K95,H95,N95,2,0),N95*M95/100) -> 753070.31 | P95: =N95*M95/100 -> 720000 | Q95: =IFERROR(ACCRINT(COUPPCD(K95,I95,2,0),COUPNCD(K95,I95,2,0),K95,H95,N95,2,0),"") -> 33070.312
B96: FBN Bank (UK) | C96: Stanbic | D96: SADF$ | E96: Fareed | F96: Buy | G96: ANGOL 8.75 04/14/2032 | H96: 0.0875 | I96: 48318 | J96: 45789 | K96: 45791 | L96: =IFERROR(YIELD(K96,I96,H96,M96,100,2,0),"") -> 0.12896364 | M96: 81.375 | N96: 4300000 | O96: =IFERROR((N96*M96/100)+ACCRINT(COUPPCD(K96,I96,2,0),COUPNCD(K96,I96,2,0),K96,H96,N96,2,0),N96*M96/100) -> 3530479.2 | P96: =N96*M96/100 -> 3499125 | Q96: =IFERROR(ACCRINT(COUPPCD(K96,I96,2,0),COUPNCD(K96,I96,2,0),K96,H96,N96,2,0),"") -> 31354.167
B97: FBN Bank (UK) | C97: Stanbic | D97: SADF$ | E97: Fareed | F97: Buy | G97: KENINT 9 1/2 03/05/36 | H97: 0.095 | I97: 49739 | J97: 45789 | K97: 45791 | L97: =IFERROR(YIELD(K97,I97,H97,M97,100,2,0),"") -> 0.10934905 | M97: 91 | N97: 3500000 | O97: =IFERROR((N97*M97/100)+ACCRINT(COUPPCD(K97,I97,2,0),COUPNCD(K97,I97,2,0),K97,H97,N97,2,0),N97*M97/100) -> 3248729.2 | P97: =N97*M97/100 -> 3185000 | Q97: =IFERROR(ACCRINT(COUPPCD(K97,I97,2,0),COUPNCD(K97,I97,2,0),K97,H97,N97,2,0),"") -> 63729.167
B98: FBN Bank (UK) | C98: Stanbic | D98: SADF$ | E98: Fareed | F98: Buy | G98: ANGOL 8.75 04/14/2032 | H98: 0.0875 | I98: 48318 | J98: 45789 | K98: 45791 | L98: =IFERROR(YIELD(K98,I98,H98,M98,100,2,0),"") -> 0.12896364 | M98: 81.375 | N98: 3000000 | O98: =IFERROR((N98*M98/100)+ACCRINT(COUPPCD(K98,I98,2,0),COUPNCD(K98,I98,2,0),K98,H98,N98,2,0),N98*M98/100) -> 2463125 | P98: =N98*M98/100 -> 2441250 | Q98: =IFERROR(ACCRINT(COUPPCD(K98,I98,2,0),COUPNCD(K98,I98,2,0),K98,H98,N98,2,0),"") -> 21875
B99: FBN Bank (UK) | C99: Stanbic | D99: SADF$ | E99: Fareed | F99: Buy | G99: KENINT 9 1/2 03/05/36 | H99: 0.095 | I99: 49739 | J99: 45789 | K99: 45791 | L99: =IFERROR(YIELD(K99,I99,H99,M99,100,2,0),"") -> 0.10977654 | M99: 90.75 | N99: 3700000 | O99: =IFERROR((N99*M99/100)+ACCRINT(COUPPCD(K99,I99,2,0),COUPNCD(K99,I99,2,0),K99,H99,N99,2,0),N99*M99/100) -> 3425120.8 | P99: =N99*M99/100 -> 3357750 | Q99: =IFERROR(ACCRINT(COUPPCD(K99,I99,2,0),COUPNCD(K99,I99,2,0),K99,H99,N99,2,0),"") -> 67370.833
B100: Access bank | C100: Stanbic | D100: SADF$ | E100: Fareed | F100: Buy | G100: ANGOL 8.75 04/14/2032 | H100: 0.0875 | I100: 48318 | J100: 45786 | K100: 45791 | L100: =IFERROR(YIELD(K100,I100,H100,M100,100,2,0),"") -> 0.13726159 | M100: 78.2 | N100: 1000000 | O100: =IFERROR((N100*M100/100)+ACCRINT(COUPPCD(K100,I100,2,0),COUPNCD(K100,I100,2,0),K100,H100,N100,2,0),N100*M100/100) -> 789291.67 | P100: =N100*M100/100 -> 782000 | Q100: =IFERROR(ACCRINT(COUPPCD(K100,I100,2,0),COUPNCD(K100,I100,2,0),K100,H100,N100,2,0),"") -> 7291.6667
A101: Repo with StoneX | B101: StoneX | C101: Stanbic | D101: SADF$ | E101: Fareed | F101: Sell | G101: ACCESS 9 1/8 PERP | H101: 0.09125 | I101: =IFERROR(VLOOKUP($G101,'Bonds Universe'!$D:$H,3,FALSE), "") -> 46210 | J101: 45790 | K101: 45791 | L101: =IFERROR(YIELD(K101,I101,H101,M101,100,2,0),"") -> 0.15037907 | M101: 93.94 | N101: 500000 | O101: =IFERROR((N101*M101/100)+ACCRINT(COUPPCD(K101,I101,2,0),COUPNCD(K101,I101,2,0),K101,H101,N101,2,0),N101*M101/100)*0.65 -> 315767.07 | P101: =N101*M101/100 -> 469700 | Q101: =IFERROR(ACCRINT(COUPPCD(K101,I101,2,0),COUPNCD(K101,I101,2,0),K101,H101,N101,2,0),"") -> 16095.486
...

Sheet Ghana Domestic Trade Tracker
L1: =TODAY() -> 46267 | M1: 44196 | N1: 364 | O1: =N1/2 -> 182
A5: S/N | B5: CP | C5: Settlement Bank | D5: Portfolio | E5: Trader | F5: Direction | G5: Name of Asset | H5: ISIN | I5: Coupon Rate | J5: Issue Date | K5: Last Coupon date | L5: No of Days | M5: Maturity Date | N5: Trade Date | O5: Settlement Date | P5: Ytm | Q5: Price | R5: Face Value | S5: Principal | T5: Accrued Interest | U5: Settlement Cost | V5: CSD Cost | W5: Net Consideration Paid | X5: Settlement Cost | Z5: FX | AA5: Status
A6: 1 | B6: I.C Securities/Access Bank Ghana | C6: Mauritius | D6: SADF GHC | E6: Kamil | F6: Buy | G6: GOG-BD-16/01/23 20.75 | J6: 43850 | K6: =J6+$O$1 -> 44032 | L6: =O6-K6 -> 148 | N6: 44179 | O6: 44180 | P6: =IFERROR(YIELD(O6,M6,I6,Q6,100,2,0),"") | Q6: 102.839 | R6: 3587000 | S6: =R6*Q6/100 -> 3688834.9 | T6: =R6*I6*(L6/$N$1) -> 0 | U6: =S6+T6 -> 3688834.9 | V6: =U6*0.01% -> 368.88349 | W6: =IF(F6="Buy",U6+V6,U6-V6) -> 3689203.8 | X6: 3991477.8 | Y6: =X6-U6 -> 302642.84 | AA6: Settled
A7: 2 | B7: I.C Securities/Access Bank Ghana | C7: Mauritius | D7: SADF GHC | E7: Kamil | F7: Buy | G7: GOG-BD-06/03/23 20.75 | J7: 43899 | K7: =J7+$O$1 -> 44081 | L7: =O7-K7 -> 99 | N7: 44179 | O7: 44180 | P7: =IFERROR(YIELD(O7,M7,I7,Q7,100,2,0),"") | Q7: 103.216 | R7: 3628000 | S7: =R7*Q7/100 -> 3744676.5 | T7: =R7*I7*(L7/$N$1) -> 0 | U7: =S7+T7 -> 3744676.5 | V7: =U7*0.01% -> 374.46765 | W7: =IF(F7="Buy",U7+V7,U7-V7) -> 3745050.9 | X7: 3949427.9 | Y7: =X7-U7 -> 204751.4 | AA7: Settled
A8: 3 | B8: I.C Securities/Access Bank Ghana | C8: Mauritius | D8: SADF GHC | E8: Kamil | F8: Buy | G8: GOG-BD-27/11/23 19.25 | J8: 44165 | K8: =J8 -> 44165 | L8: =O8-K8 -> 17 | N8: 44180 | O8: 44182 | P8: =IFERROR(YIELD(O8,M8,I8,Q8,100,2,0),"") | Q8: 100.95 | R8: 3889000 | S8: =R8*Q8/100 -> 3925945.5 | T8: =R8*I8*(L8/$N$1) -> 0 | U8: =S8+T8 -> 3925945.5 | V8: =U8*0.01% -> 392.59455 | W8: =IF(F8="Buy",U8+V8,U8-V8) -> 3926338.1 | X8: 3960889.7 | Y8: =X8-U8 -> 34944.17 | AA8: Settled
A9: 1 | B9: I.C Securities/Access Bank Ghana | C9: Mauritius | D9: SADF GHC | E9: Rasheed | F9: Buy | G9: GOG-BD 13/10/25 19.85 | I9: =IFERROR(VLOOKUP($G9,'Bonds Universe'!$D:$H,2,FALSE),"") -> 0.1985 | J9: 44123 | K9: =J9 -> 44123 | L9: =O9-K9 -> 106 | M9: =IFERROR(VLOOKUP($G9,'Bonds Universe'!$D:$H,3,FALSE),"") -> 45943 | N9: 44223 | O9: 44229 | P9: =IFERROR(YIELD(O9,M9,I9,Q9,100,2,0),"") -> 0.18196042 | Q9: 104.9749 | R9: 3763000 | S9: =R9*Q9/100 -> 3950205.5 | T9: =R9*I9*(L9/$N$1) -> 217520.01 | U9: =S9+T9 -> 4167725.5 | V9: =U9*0.01% -> 416.77255 | W9: =IF(F9="Buy",U9+V9,U9-V9) -> 4168142.3 | X9: 4167725.5 | Y9: =X9-U9 -> 0.0047582411 | AA9: Settled | AB9: 5.77 | AC9: =X9/AB9 -> 722309.45 | AF9: =(X9*100)/R9 -> 110.75539 | AG9: =(#REF!*100)/R9 -> #REF!
A10: 2 | B10: I.C Securities/Access Bank Ghana | C10: Mauritius | D10: SADF GHC | E10: Rasheed | F10: Buy | G10: GOG-BD 18/01/27 19.25 | I10: =IFERROR(VLOOKUP($G10,'Bonds Universe'!$D:$H,2,FALSE),"") -> 0.1925 | J10: 44221 | K10: =J10 -> 44221 | L10: =O10-K10 -> 8 | M10: =IFERROR(VLOOKUP($G10,'Bonds Universe'!$D:$H,3,FALSE),"") -> 46405 | N10: 44223 | O10: 44229 | P10: =IFERROR(YIELD(O10,M10,I10,Q10,100,2,0),"") -> 0.18943067 | Q10: 101.0386 | R10: 8216450 | S10: =R10*Q10/100 -> 8301786 | T10: =R10*I10*(L10/$N$1) -> 34761.904 | U10: =S10+T10 -> 8336548 | V10: =U10*0.01% -> 833.6548 | W10: =IF(F10="Buy",U10+V10,U10-V10) -> 8337381.6 | X10: 8336547.9 | Y10: =X10-U10 -> -0.0035461551 | AA10: Settled | AB10: 5.84 | AC10: =X10/AB10 -> 1427491.1 | AD10: 1429469.6 | AE10: =X10/AD10 -> 5.8319168 | AF10: =(X10*100)/R10 -> 101.46168 | AG10: =(#REF!*100)/R10 -> #REF!
A11: 3 | B11: I.C Securities/Access Bank Ghana | C11: Mauritius | D11: SADF GHC | E11: Rasheed | F11: Buy | G11: GOG-BD 08/11/27 20.50 | I11: =IFERROR(VLOOKUP($G11,'Bonds Universe'!$D:$H,2,FALSE),"") -> 0.205 | J11: 44151 | K11: =J11 -> 44151 | L11: =O11-K11 -> 78 | M11: =IFERROR(VLOOKUP($G11,'Bonds Universe'!$D:$H,3,FALSE),"") -> 46699 | N11: 44223 | O11: 44229 | P11: =IFERROR(YIELD(O11,M11,I11,Q11,100,2,0),"") -> 0.19095998 | Q11: 105.096 | R11: 7613850 | S11: =R11*Q11/100 -> 8001851.8 | T11: =R11*I11*(L11/$N$1) -> 334465.55 | U11: =S11+T11 -> 8336317.3 | V11: =U11*0.01% -> 833.63174 | W11: =IF(F11="Buy",U11+V11,U11-V11) -> 8337151 | X11: 8336317.4 | Y11: =X11-U11 -> 0.0004285723 | AA11: Settled | AB11: 5.77 | AC11: =X11/AB11 -> 1444769 | AE11: 5.8319168 | AF11: =(X11*100)/R11 -> 109.48886 | AG11: =(#REF!*100)/R11 -> #REF!
A12: 4 | B12: I.C Securities/Access Bank Ghana | C12: Mauritius | D12: SADF GHC | E12: Rasheed | F12: Buy | G12: GOG-BD 09/08/27 20.00 | I12: =IFERROR(VLOOKUP($G12,'Bonds Universe'!$D:$H,2,FALSE),"") -> 0.2 | J12: 44060 | K12: =J12+O1 -> 44242 | L12: =O12-K12 -> 14 | M12: =IFERROR(VLOOKUP($G12,'Bonds Universe'!$D:$H,3,FALSE),"") -> 46608 | N12: 44251 | O12: 44256 | P12: =IFERROR(YIELD(O12,M12,I12,Q12,100,2,0),"") -> 0.18693416 | Q12: 104.7305 | R12: 10000000 | S12: =R12*Q12/100 -> 10473050 | T12: =R12*I12*(L12/$N$1) -> 76923.077 | U12: =S12+T12 -> 10549973 | V12: =U12*0.01% -> 1054.9973 | W12: =IF(F12="Buy",U12+V12,U12-V12) -> 10551028 | X12: 10549973 | Y12: =X12-U12 -> 0.0030769221 | AA12: Settled | AB12: 5.77 | AC12: =X12/AB12 -> 1828418.2 | AF12: =(X12*100)/R12 -> 105.49973 | AG12: =(#REF!*100)/R12 -> #REF!
A13: 5 | B13: I.C Securities/Access Bank Ghana | C13: Mauritius | D13: SADF GHC | E13: Rasheed | F13: Buy | G13: GOG-BD 08/11/27 20.50 | I13: =IFERROR(VLOOKUP($G13,'Bonds Universe'!$D:$H,2,FALSE),"") -> 0.205 | J13: 44151 | K13: =J13+O2 -> 44151 | L13: =O13-K13 -> 105 | M13: =IFERROR(VLOOKUP($G13,'Bonds Universe'!$D:$H,3,FALSE),"") -> 46699 | N13: 44251 | O13: 44256 | P13: =IFERROR(YIELD(O13,M13,I13,Q13,100,2,0),"") -> 0.18697818 | Q13: 106.6138 | R13: 5000000 | S13: =R13*Q13/100 -> 5330690 | T13: =R13*I13*(L13/$N$1) -> 295673.08 | U13: =S13+T13 -> 5626363.1 | V13: =U13*0.01% -> 562.63631 | W13: =IF(F13="Buy",U13+V13,U13-V13) -> 5626925.7 | X13: 5626363.1 | Y13: =X13-U13 -> 0.0030769231 | AA13: Settled | AB13: 5.77 | AC13: =X13/AB13 -> 975106.25 | AF13: =(X13*100)/R13 -> 112.52726 | AG13: =(#REF!*100)/R13 -> #REF!
A14: 6 | B14: I.C Securities/Access Bank Ghana | C14: Mauritius | D14: SADF GHC | E14: Rasheed | F14: Buy | G14: GOG-BD 29/05/28 17.50 | I14: =IFERROR(VLOOKUP($G14,'Bonds Universe'!$D:$H,2,FALSE),"") -> 0.175 | J14: 43262 | K14: =J14+(2*N1)+O1 -> 44172 | L14: =O14-K14 -> 84 | M14: =IFERROR(VLOOKUP($G14,'Bonds Universe'!$D:$H,3,FALSE),"") -> 46902 | N14: 44251 | O14: 44256 | P14: =IFERROR(YIELD(O14,M14,I14,Q14,100,2,0),"") -> 0.18802067 | Q14: 94.8605 | R14: 10000000 | S14: =R14*Q14/100 -> 9486050 | T14: =R14*I14*(L14/$N$1) -> 403846.15 | U14: =S14+T14 -> 9889896.2 | V14: =U14*0.01% -> 988.98962 | W14: =IF(F14="Buy",U14+V14,U14-V14) -> 9890885.1 | X14: 9889896.2 | Y14: =X14-U14 -> -0.0038461536 | AA14: Settled | AB14: 5.77 | AC14: =X14/AB14 -> 1714020.1 | AD14: 1894249.1 | AE14: =(X14+X17)/AD14 -> 5.7269273 | AF14: =(X14*100)/R14 -> 98.898961 | AG14: =(#REF!*100)/R14 -> #REF!
A15: 7 | B15: I.C Securities/EcoBank Ghana | C15: Mauritius | D15: SADF GHC | E15: Rasheed | F15: Buy | G15: GOG-BD 09/08/27 20.00 | I15: =IFERROR(VLOOKUP($G15,'Bonds Universe'!$D:$H,2,FALSE),"") -> 0.2 | J15: 44060 | K15: =J15+$O$1 -> 44242 | L15: =O15-K15 -> 14 | M15: =IFERROR(VLOOKUP($G15,'Bonds Universe'!$D:$H,3,FALSE),"") -> 46608 | N15: 44251 | O15: 44256 | P15: =IFERROR(YIELD(O15,M15,I15,Q15,100,2,0),"") -> 0.18693416 | Q15: 104.7305 | R15: 6453350 | S15: =R15*Q15/100 -> 6758625.7 | T15: =R15*I15*(L15/$N$1) -> 49641.154 | U15: =S15+T15 -> 6808266.9 | V15: =U15*0.01% -> 680.82669 | W15: =IF(F15="Buy",U15+V15,U15-V15) -> 6808947.7 | X15: 6808266.9 | Y15: =X15-U15 -> -0.0055961544 | AA15: Settled | AB15: 5.77 | AC15: =X15/AB15 -> 1179942.3 | AE15: 5.7269273 | AF15: =(X15*100)/R15 -> 105.49973 | AG15: =(#REF!*100)/R15 -> #REF!
A16: 8 | B16: I.C Securities/EcoBank Ghana | C16: Mauritius | D16: SADF GHC | E16: Rasheed | F16: Buy | G16: GOG-BD 08/11/27 20.50 | I16: =IFERROR(VLOOKUP($G16,'Bonds Universe'!$D:$H,2,FALSE),"") -> 0.205 | J16: 44151 | K16: =J16 -> 44151 | L16: =O16-K16 -> 105 | M16: =IFERROR(VLOOKUP($G16,'Bonds Universe'!$D:$H,3,FALSE),"") -> 46699 | N16: 44251 | O16: 44256 | P16: =IFERROR(YIELD(O16,M16,I16,Q16,100,2,0),"") -> 0.18697818 | Q16: 106.6138 | R16: 8498000 | S16: =R16*Q16/100 -> 9060040.7 | T16: =R16*I16*(L16/$N$1) -> 502525.96 | U16: =S16+T16 -> 9562566.7 | V16: =U16*0.01% -> 956.25667 | W16: =IF(F16="Buy",U16+V16,U16-V16) -> 9563522.9 | X16: 9562566.7 | Y16: =X16-U16 -> -0.0055384617 | AA16: Settled | AB16: 5.77 | AC16: =X16/AB16 -> 1657290.6 | AF16: =(X16*100)/R16 -> 112.52726 | AG16: =(#REF!*100)/R16 -> #REF!
A17: 9 | B17: I.C Securities/EcoBank Ghana | C17: Mauritius | D17: SADF GHC | E17: Rasheed | F17: Buy | G17: GOG-BD 29/05/28 17.50 | I17: =IFERROR(VLOOKUP($G17,'Bonds Universe'!$D:$H,2,FALSE),"") -> 0.175 | J17: 43262 | K17: =J17+(2*N1)+O1 -> 44172 | L17: =O17-K17 -> 84 | M17: =IFERROR(VLOOKUP($G17,'Bonds Universe'!$D:$H,3,FALSE),"") -> 46902 | N17: 44251 | O17: 44256 | P17: =IFERROR(YIELD(O17,M17,I17,Q17,100,2,0),"") -> 0.18802067 | Q17: 94.8605 | R17: 969000 | S17: =R17*Q17/100 -> 919198.24 | T17: =R17*I17*(L17/$N$1) -> 39132.692 | U17: =S17+T17 -> 958330.94 | V17: =U17*0.01% -> 95.833094 | W17: =IF(F17="Buy",U17+V17,U17-V17) -> 958426.77 | X17: 958330.94 | Y17: =X17-U17 -> 0.0026923076 | AA17: Settled | AB17: 5.77 | AC17: =X17/AB17 -> 166088.55 | AF17: =(X17*100)/R17 -> 98.898962 | AG17: =(#REF!*100)/R17 -> #REF!
A18: 10 | B18: I.C Securities/Access Bank Ghana | C18: Mauritius | D18: SADF GHC | E18: Rasheed | F18: Buy | G18: GOG-BD-02/11/26 19.00 | I18: =IFERROR(VLOOKUP($G18,'Bonds Universe'!$D:$H,2,FALSE),"") -> 0.19 | J18: 42688 | K18: =J18+(4*N1) -> 44144 | L18: =O18-K18 -> 162 | M18: =IFERROR(VLOOKUP($G18,'Bonds Universe'!$D:$H,3,FALSE),"") -> 46328 | N18: 44301 | O18: 44306 | P18: =IFERROR(YIELD(O18,M18,I18,Q18,100,2,0),"") -> 0.18403003 | Q18: 101.993 | R18: 8120570 | S18: =R18*Q18/100 -> 8282413 | T18: =R18*I18*(L18/$N$1) -> 686678.97 | U18: =S18+T18 -> 8969091.9 | V18: =U18*0.01% -> 896.90919 | W18: =IF(F18="Buy",U18+V18,U18-V18) -> 8969988.8 | X18: 8969091.9 | Y18: =X18-U18 -> 0.0012186803 | AA18: Settled | AB18: 5.77 | AC18: =X18/AB18 -> 1554435.3 | AF18: =(X18*100)/R18 -> 110.44904 | AG18: =(#REF!*100)/R18 -> #REF!
A19: 11 | B19: I.C Securities/Access Bank Ghana | C19: Mauritius | D19: SADF GHC | E19: Rasheed | F19: Buy | G19: GOG-BD-02/03/26 18.30 | I19: =IFERROR(VLOOKUP($G19,'Bonds Universe'!$D:$H,2,FALSE),"") -> 0.183 | J19: 44263 | K19: =J19 -> 44263 | L19: =O19-K19 -> 43 | M19: =IFERROR(VLOOKUP($G19,'Bonds Universe'!$D:$H,3,FALSE),"") -> 46083 | N19: 44301 | O19: 44306 | P19: =IFERROR(YIELD(O19,M19,I19,Q19,100,2,0),"") -> 0.18047617 | Q19: 100.7185 | R19: 8717980 | S19: =R19*Q19/100 -> 8780618.7 | T19: =R19*I19*(L19/$N$1) -> 188466.44 | U19: =S19+T19 -> 8969085.1 | V19: =U19*0.01% -> 896.90851 | W19: =IF(F19="Buy",U19+V19,U19-V19) -> 8969982 | X19: 8969085.1 | Y19: =X19-U19 -> 0.0024362635 | AA19: Settled | AB19: 5.77 | AC19: =X19/AB19 -> 1554434.2 | AF19: =(X19*100)/R19 -> 102.88031 | AG19: =(#REF!*100)/R19 -> #REF!
A20: 12 | B20: I.C Securities/Access Bank Ghana | C20: Mauritius | D20: SADF GHC | E20: Rasheed | F20: Buy | G20: GOG-BD-13/10/25 19.85 | I20: =IFERROR(VLOOKUP($G20,'Bonds Universe'!$D:$H,2,FALSE),"") -> 0.1985 | J20: 44123 | K20: =J20+O1 -> 44305 | L20: =O20-K20 -> 1 | M20: =IFERROR(VLOOKUP($G20,'Bonds Universe'!$D:$H,3,FALSE),"") -> 45943 | N20: 44301 | O20: 44306 | P20: =IFERROR(YIELD(O20,M20,I20,Q20,100,2,0),"") -> 0.17991247 | Q20: 105.5411 | R20: 11325085 | S20: =R20*Q20/100 -> 11952619 | T20: =R20*I20*(L20/$N$1) -> 6175.9049 | U20: =S20+T20 -> 11958795 | V20: =U20*0.01% -> 1195.8795 | W20: =IF(F20="Buy",U20+V20,U20-V20) -> 11959991 | X20: 11958795 | Y20: =X20-U20 -> -0.0098045059 | AA20: Settled | AB20: 5.77 | AC20: =X20/AB20 -> 2072581.5 | AF20: =(X20*100)/R20 -> 105.59563 | AG20: =(#REF!*100)/R20 -> #REF!
A21: 13 | B21: I.C Securities/Access Bank Ghana | C21: Mauritius | D21: SADF GHC | E21: Rasheed | F21: Buy | G21: GOG-BD-13/10/25 19.85 | I21: =IFERROR(VLOOKUP($G21,'Bonds Universe'!$D:$H,2,FALSE),"") -> 0.1985 | J21: 44123 | K21: =J21+$O$1 -> 44305 | L21: =O21-K21 -> 53 | M21: =IFERROR(VLOOKUP($G21,'Bonds Universe'!$D:$H,3,FALSE),"") -> 45943 | N21: 44355 | O21: 44358 | P21: =IFERROR(YIELD(O21,M21,I21,Q21,100,2,0),"") -> 0.17994025 | Q21: 105.3376 | R21: 1433000 | S21: =R21*Q21/100 -> 1509487.8 | T21: =R21*I21*(L21/$N$1) -> 41417.243 | U21: =S21+T21 -> 1550905.1 | V21: =U21*0.01% -> 155.09051 | W21: =IF(F21="Buy",U21+V21,U21-V21) -> 1551060.1 | X21: 1550905.1 | Y21: =X21-U21 -> -0.0011318678 | AA21: Settled
A22: 14 | B22: I.C Securities/Access Bank Ghana | C22: Mauritius | D22: SADF GHC | E22: Rasheed | F22: Buy | G22: GOG-BD-02/11/26 19.00 | I22: =IFERROR(VLOOKUP($G22,'Bonds Universe'!$D:$H,2,FALSE),"") -> 0.19 | J22: 42688 | K22: =J22+(4*N1)+O1 -> 44326 | L22: =O22-K22 -> 32 | M22: =IFERROR(VLOOKUP($G22,'Bonds Universe'!$D:$H,3,FALSE),"") -> 46328 | N22: 44355 | O22: 44358 | P22: =IFERROR(YIELD(O22,M22,I22,Q22,100,2,0),"") -> 0.18395595 | Q22: 101.9431 | R22: 1496750 | S22: =R22*Q22/100 -> 1525833.3 | T22: =R22*I22*(L22/$N$1) -> 25000.659 | U22: =S22+T22 -> 1550834 | V22: =U22*0.01% -> 155.0834 | W22: =IF(F22="Buy",U22+V22,U22-V22) -> 1550989.1 | X22: 1550834 | Y22: =X22-U22 -> 0.0014093404 | AA22: Settled
A23: 15 | B23: I.C Securities/EcoBank Ghana | C23: Mauritius | D23: SADF GHC | E23: Rasheed | F23: Buy | G23: GOG-BD-18/01/27 19.25 | I23: =IFERROR(VLOOKUP($G23,'Bonds Universe'!$D:$H,2,FALSE),"") -> 0.1925 | J23: 44221 | K23: =J23 -> 44221 | L23: =O23-K23 -> 137 | M23: =IFERROR(VLOOKUP($G23,'Bonds Universe'!$D:$H,3,FALSE),"") -> 46405 | N23: 44355 | O23: 44358 | P23: =IFERROR(YIELD(O23,M23,I23,Q23,100,2,0),"") -> 0.18451082 | Q23: 102.6492 | R23: 1411000 | S23: =R23*Q23/100 -> 1448380.2 | T23: =R23*I23*(L23/$N$1) -> 102229.66 | U23: =S23+T23 -> 1550609.9 | V23: =U23*0.01% -> 155.06099 | W23: =IF(F23="Buy",U23+V23,U23-V23) -> 1550764.9 | X23: 1550609.9 | Y23: =X23-U23 -> -0.0054615382 | AA23: Settled
A24: 16 | B24: I.C Securities/Access Bank Ghana | C24: Mauritius | D24: SADF GHC | E24: Rasheed | F24: Sell | G24: GOG-BD-16/01/23 20.75 | J24: 43850 | K24: =J24+$N$1 -> 44214 | L24: =O24-K24 -> 176 | N24: 44386 | O24: 44390 | P24: =IFERROR(YIELD(O24,M24,I24,Q24,100,2,0),"") | Q24: 103.4996 | R24: 3587000 | S24: =R24*Q24/100 -> 3712530.7 | T24: =R24*I24*(L24/$N$1) -> 0 | U24: =S24+T24 -> 3712530.7 | V24: =U24*0.01% -> 371.25307 | W24: =IF(F24="Buy",U24+V24,U24-V24) -> 3712159.4 | X24: 4072413.2 | Y24: =X24-U24 -> 359882.53 | Z24: 6.04302 | AA24: Settled
A25: 17 | B25: I.C Securities/Access Bank Ghana | C25: Mauritius | D25: SADF GHC | E25: Rasheed | F25: Sell | G25: GOG-BD-06/03/23 20.75 | J25: 43899 | K25: =J25+$N$1 -> 44263 | L25: =O25-K25 -> 127 | N25: 44386 | O25: 44390 | P25: =IFERROR(YIELD(O25,M25,I25,Q25,100,2,0),"") | Q25: 103.5474 | R25: 3628000 | S25: =R25*Q25/100 -> 3756699.7 | T25: =R25*I25*(L25/$N$1) -> 0 | U25: =S25+T25 -> 3756699.7 | V25: =U25*0.01% -> 375.66997 | W25: =IF(F25="Buy",U25+V25,U25-V25) -> 3756324 | X25: 4019355.9 | Y25: =X25-U25 -> 262656.24 | Z25: 6.04302 | AA25: Settled
A26: 18 | B26: I.C Securities/Access Bank Ghana | C26: Mauritius | D26: SADF GHC | E26: Rasheed | F26: Sell | G26: GOG-BD-27/11/23 19.25 | J26: 44165 | K26: =J26+$O$1 -> 44347 | L26: =O26-K26 -> 46 | N26: 44391 | O26: 44393 | P26: =IFERROR(YIELD(O26,M26,I26,Q26,100,2,0),"") | Q26: 101.7836 | R26: 3889000 | S26: =R26*Q26/100 -> 3958364.2 | T26: =R26*I26*(L26/$N$1) -> 0 | U26: =S26+T26 -> 3958364.2 | V26: =U26*0.01% -> 395.83642 | W26: =IF(F26="Buy",U26+V26,U26-V26) -> 3957968.4 | X26: 4052971.6 | Y26: =X26-U26 -> 94607.396 | Z26: 6.138228 | AA26: Settled
A27: 19 | B27: I.C Securities/Access Bank Ghana | C27: Mauritius | D27: SADF GHC | E27: Rasheed | F27: Sell | G27: GOG-BD-02/03/26 18.30 | I27: 0.183 | J27: 44263 | K27: =J27 -> 44263 | L27: =O27-K27 -> 133 | M27: 46083 | N27: 44392 | O27: 44396 | P27: 0.18047617 | Q27: 97.0872 | R27: 8717980 | S27: =R27*Q27/100 -> 8464042.7 | T27: =R27*I27*(L27/$N$1) -> 582931.09 | U27: =S27+T27 -> 9046973.8 | V27: =U27*0.01% -> 904.69738 | W27: =IF(F27="Buy",U27+V27,U27-V27) -> 9046069.1 | X27: 9046973.8 | Y27: =X27-U27 -> 0.0056707691 | Z27: 6.138228 | AA27: Settled | AB27: 5.77
A28: 20 | B28: I.C Securities/Access Bank Ghana | C28: Mauritius | D28: SADF GHC | E28: Rasheed | F28: Sell | G28: GOG-BD-13/10/25 19.85 | I28: =IFERROR(VLOOKUP($G28,'Bonds Universe'!$D:$H,2,FALSE),"") -> 0.1985 | J28: 44123 | K28: 44305 | L28: =O28-K28 -> 94 | M28: =IFERROR(VLOOKUP($G28,'Bonds Universe'!$D:$H,3,FALSE),"") -> 45943 | N28: 44396 | O28: 44399 | P28: =IFERROR(YIELD(O28,M28,I28,Q28,100,2,0),"") -> 0.18855532 | Q28: 102.7 | R28: 10000000 | S28: =R28*Q28/100 -> 10270000 | T28: =R28*I28*(L28/$N$1) -> 512609.89 | U28: =S28+T28 -> 10782610 | V28: =U28*0.01% -> 1078.261 | W28: =IF(F28="Buy",U28+V28,U28-V28) -> 10781532 | Z28: 6.138228 | AA28: Settled | AB28: 5.77
A29: 21 | B29: I.C Securities/Access Bank Ghana | C29: Mauritius | D29: SADF GHC | E29: Rasheed | F29: Sell | G29: GOG-BD-13/10/25 19.85 | I29: =IFERROR(VLOOKUP($G29,'Bonds Universe'!$D:$H,2,FALSE),"") -> 0.1985 | J29: 44123 | K29: 44305 | L29: =O29-K29 -> 94 | M29: =IFERROR(VLOOKUP($G29,'Bonds Universe'!$D:$H,3,FALSE),"") -> 45943 | N29: 44396 | O29: 44399 | P29: =IFERROR(YIELD(O29,M29,I29,Q29,100,2,0),"") -> 0.18796694 | Q29: 102.87 | R29: 6521085 | S29: =R29*Q29/100 -> 6708240.1 | T29: =R29*I29*(L29/$N$1) -> 334277.27 | U29: =S29+T29 -> 7042517.4 | V29: =U29*0.01% -> 704.25174 | W29: =IF(F29="Buy",U29+V29,U29-V29) -> 7041813.2 | Z29: 6.138228 | AA29: Settled | AB29: 5.77
A30: 22 | B30: I.C Securities/EcoBank Ghana | C30: Mauritius | D30: SADF GHC | E30: Rasheed | F30: Sell | G30: GOG-BD 08/11/27 20.50 | I30: =IFERROR(VLOOKUP($G30,'Bonds Universe'!$D:$H,2,FALSE),"") -> 0.205 | J30: 44151 | K30: =J30+O1 -> 44333 | L30: =O30-K30 -> 70 | M30: =IFERROR(VLOOKUP($G30,'Bonds Universe'!$D:$H,3,FALSE),"") -> 46699 | N30: 44399 | O30: 44403 | P30: =IFERROR(YIELD(O30,M30,I30,Q30,100,2,0),"") -> 0.19340467 | Q30: 104 | R30: 21111850 | S30: =R30*Q30/100 -> 21956324 | T30: =R30*I30*(L30/$N$1) -> 832294.09 | U30: =S30+T30 -> 22788618 | V30: =U30*0.01% -> 2278.8618 | W30: =IF(F30="Buy",U30+V30,U30-V30) -> 22786339 | X30: 22788618 | Y30: =X30-U30 -> 0 | Z30: 6.138228 | AA30: Settled | AB30: 5.77
A31: 23 | B31: I.C Securities/Access Bank Ghana | C31: Mauritius | D31: SADF GHC | E31: Rasheed | F31: Sell | G31: GOG-BD-02/11/26 19.00 | I31: =IFERROR(VLOOKUP($G31,'Bonds Universe'!$D:$H,2,FALSE),"") -> 0.19 | J31: 42688 | K31: =J31+(4*N1)+O1 -> 44326 | L31: =O31-K31 -> 77 | M31: =IFERROR(VLOOKUP($G31,'Bonds Universe'!$D:$H,3,FALSE),"") -> 46328 | N31: 44399 | O31: 44403 | P31: =IFERROR(YIELD(O31,M31,I31,Q31,100,2,0),"") -> 0.18752655 | Q31: 100.7 | R31: 5000000 | S31: =R31*Q31/100 -> 5035000 | T31: =R31*I31*(L31/$N$1) -> 200961.54 | U31: =S31+T31 -> 5235961.5 | V31: =U31*0.01% -> 523.59615 | W31: =IF(F31="Buy",U31+V31,U31-V31) -> 5235437.9 | X31: 5235961.5 | Y31: =X31-U31 -> 0.001538462 | Z31: 6.138228 | AA31: Settled | AB31: 5.77
A32: 24 | B32: I.C Securities/Access Bank Ghana | C32: Mauritius | D32: SADF GHC | E32: Rasheed | F32: Sell | G32: GOG-BD-02/11/26 19.00 | I32: =IFERROR(VLOOKUP($G32,'Bonds Universe'!$D:$H,2,FALSE),"") -> 0.19 | J32: 42688 | K32: =J32+(4*N1)+O1 -> 44326 | L32: =O32-K32 -> 87 | M32: =IFERROR(VLOOKUP($G32,'Bonds Universe'!$D:$H,3,FALSE),"") -> 46328 | N32: 44410 | O32: 44413 | P32: =IFERROR(YIELD(O32,M32,I32,Q32,100,2,0),"") -> 0.18849616 | Q32: 100.3806 | R32: 1496750 | S32: =R32*Q32/100 -> 1502446.6 | T32: =R32*I32*(L32/$N$1) -> 67970.543 | U32: =S32+T32 -> 1570417.2 | V32: =U32*0.01% -> 157.04172 | W32: =IF(F32="Buy",U32+V32,U32-V32) -> 1570260.1 | X32: 1570417.2 | Y32: =X32-U32 -> -0.0030824179 | AA32: Settled
A33: 25 | B33: I.C Securities/EcoBank Ghana | C33: Mauritius | D33: SADF GHC | E33: Rasheed | F33: Sell | G33: GOG-BD 09/08/27 20.00 | I33: =IFERROR(VLOOKUP($G33,'Bonds Universe'!$D:$H,2,FALSE),"") -> 0.2 | J33: 44060 | K33: =J33+$N$1 -> 44424 | L33: =O33-K33 -> 25 | M33: =IFERROR(VLOOKUP($G33,'Bonds Universe'!$D:$H,3,FALSE),"") -> 46608 | N33: 44447 | O33: =N33+2 -> 44449 | P33: =IFERROR(YIELD(O33,M33,I33,Q33,100,2,0),"") -> 0.19045393 | Q33: 103.2389 | R33: 16453350 | S33: =R33*Q33/100 -> 16986258 | T33: =R33*I33*(L33/$N$1) -> 226007.55 | U33: =S33+T33 -> 17212265 | V33: =U33*0.01% -> 1721.2265 | W33: =IF(F33="Buy",U33+V33,U33-V33) -> 17210544 | X33: =W33 -> 17210544 | Y33: =X33-U33 -> -1721.2265 | AA33: Settled
A34: 26 | B34: I.C Securities/Access Bank Ghana | C34: Mauritius | D34: SADF GHC | E34: Rasheed | F34: Sell | G34: GOG-BD 18/01/27 19.25 | I34: =IFERROR(VLOOKUP($G34,'Bonds Universe'!$D:$H,2,FALSE),"") -> 0.1925 | J34: 44221 | K34: =J34+$O$1 -> 44403 | L34: =O34-K34 -> 46 | M34: =IFERROR(VLOOKUP($G34,'Bonds Universe'!$D:$H,3,FALSE),"") -> 46405 | N34: 44447 | O34: 44449 | P34: =IFERROR(YIELD(O34,M34,I34,Q34,100,2,0),"") -> 0.18947199 | Q34: 100.9031 | R34: 9627450 | S34: =R34*Q34/100 -> 9714395.5 | T34: =R34*I34*(L34/$N$1) -> 234206.24 | U34: =S34+T34 -> 9948601.7 | V34: =U34*0.01% -> 994.86017 | W34: =IF(F34="Buy",U34+V34,U34-V34) -> 9947606.9 | X34: 8336547.9 | Y34: =X34-U34 -> -1612053.8 | AA34: Settled
A35: 27 | B35: I.C Securities/Access Bank Ghana | C35: Mauritius | D35: SADF GHC | E35: Rasheed | F35: Sell | G35: GOG-BD-02/11/26 19.00 | I35: =IFERROR(VLOOKUP($G35,'Bonds Universe'!$D:$H,2,FALSE),"") -> 0.19 | J35: 42688 | K35: =J35+(4*$N$1)+$O$1 -> 44326 | L35: =O35-K35 -> 123 | M35: =IFERROR(VLOOKUP($G35,'Bonds Universe'!$D:$H,3,FALSE),"") -> 46328 | N35: 44447 | O35: 44449 | P35: =IFERROR(YIELD(O35,M35,I35,Q35,100,2,0),"") -> 0.18801366 | Q35: 100.5491 | R35: 3120570 | S35: =R35*Q35/100 -> 3137705 | T35: =R35*I35*(L35/$N$1) -> 200350.88 | U35: =S35+T35 -> 3338055.9 | V35: =U35*0.01% -> 333.80559 | W35: =IF(F35="Buy",U35+V35,U35-V35) -> 3337722.1 | X35: 1570417.2 | Y35: =X35-U35 -> -1767638.8 | AA35: Settled
A36: 28 | B36: I.C Securities/Access Bank Ghana | C36: Mauritius | D36: SADF GHC | E36: Rasheed | F36: Sell | G36: GOG-BD 29/05/28 17.50 | I36: =IFERROR(VLOOKUP($G36,'Bonds Universe'!$D:$H,2,FALSE),"") -> 0.175 | J36: 43262 | K36: =J36+(3*$N$1) -> 44354 | L36: =O36-K36 -> 98 | M36: =IFERROR(VLOOKUP($G36,'Bonds Universe'!$D:$H,3,FALSE),"") -> 46902 | N36: 44449 | O36: 44452 | P36: =IFERROR(YIELD(O36,M36,I36,Q36,100,2,0),"") -> 0.19203126 | Q36: 93.6238 | R36: 10000000 | S36: =R36*Q36/100 -> 9362380 | T36: =R36*I36*(L36/$N$1) -> 471153.85 | U36: =S36+T36 -> 9833533.8 | V36: =U36*0.01% -> 983.35338 | W36: =IF(F36="Buy",U36+V36,U36-V36) -> 9832550.5 | AA36: Settled
A37: 29 | B37: I.C Securities/Access Bank Ghana | C37: Mauritius | D37: SADF GHC | E37: Rasheed | F37: Sell | G37: GOG-BD 29/05/28 17.50 | I37: =IFERROR(VLOOKUP($G37,'Bonds Universe'!$D:$H,2,FALSE),"") -> 0.175 | J37: 43262 | K37: =J37+(3*$N$1) -> 44354 | L37: =O37-K37 -> 98 | M37: =IFERROR(VLOOKUP($G37,'Bonds Universe'!$D:$H,3,FALSE),"") -> 46902 | N37: 44449 | O37: 44452 | P37: =IFERROR(YIELD(O37,M37,I37,Q37,100,2,0),"") -> 0.19203126 | Q37: 93.6238 | R37: 969000 | S37: =R37*Q37/100 -> 907214.62 | T37: =R37*I37*(L37/$N$1) -> 45654.808 | U37: =S37+T37 -> 952869.43 | V37: =U37*0.01% -> 95.286943 | W37: =IF(F37="Buy",U37+V37,U37-V37) -> 952774.14 | AA37: Settled

Sheet NGN Domestic Trade Tracker
K1: =PRICEDISC(L85,J85,M85,100,1) -> 89.628353 | L1: 86.643625 | N1: =COUPNCD(L68,J68,2,1) -> 45042 | O1: =P68*100/O68 -> 98.777143 | P1: =P65+R65 -> 2363070714 | Q1: =P1/O65 -> 1.1815354 | R1: =P65/O65*100 -> 115.25177 | S1: 0.0005375 | T1: *100
B3: S/N | C3: CP | D3: Settlement Bank | E3: Portfolio | F3: Trader | G3: Direction | H3: Name of Asset | I3: Coupon Rate | J3: Maturity Date | K3: Trade Date | L3: Settlement Date | M3: Ytm | N3: Price | O3: Face Value | P3: Consideration | Q3: Principal | R3: Accrued Interest | S3: fees | T3: Consideration | V3: Status
B4: 1 | C4: Parthian/Sterling Bank | D4: Stanbic | E4: GIF₦ | F4: Rasheed | G4: Buy | H4: FGN 2026 Bond | I4: 0.125 | J4: 46044 | K4: 44327 | L4: 44330 | M4: =IFERROR(YIELD(L4,J4,I4,N4,100,2,1),"") -> 0.1289945 | N4: 98.58 | O4: 194000000 | P4: =IFERROR((O4*N4/100)+ACCRINT(COUPPCD(L4,J4,2,1),COUPNCD(L4,J4,2,1),L4,I4,O4,2,1),O4*N4/100) -> 1.9874796e+08 | Q4: =O4*N4/100 -> 191245200 | R4: =IFERROR(ACCRINT(COUPPCD(L4,J4,2,1),COUPNCD(L4,J4,2,0),L4,I4,O4,2,1),"") -> 7502762.4 | T4: =IFERROR(Q4+R4,Q4) -> 1.9874796e+08 | V4: Settled
B5: =B4+1 -> 2 | C5: Parthian/Sterling Bank | D5: Stanbic | E5: GIF₦ | F5: Rasheed | G5: Buy | H5: FGN 2035 Bond | I5: 0.125 | J5: 49395 | K5: 44327 | L5: 44333 | M5: =IFERROR(YIELD(L5,J5,I5,N5,100,2,1),"") -> 0.13859495 | N5: 91.68 | O5: 200000000 | P5: =IFERROR((O5*N5/100)+ACCRINT(COUPPCD(L5,J5,2,1),COUPNCD(L5,J5,2,1),L5,I5,O5,2,1),O5*N5/100) -> 1.8682467e+08 | Q5: =O5*N5/100 -> 183360000 | R5: =IFERROR(ACCRINT(COUPPCD(L5,J5,2,1),COUPNCD(L5,J5,2,0),L5,I5,O5,2,1),"") -> 3464673.9 | T5: =IFERROR(Q5+R5,Q5) -> 1.8682467e+08 | V5: Settled
B6: =B5+1 -> 3 | C6: Comercio/Coronation MB | D6: Stanbic | E6: GIF₦ | F6: Rasheed | G6: Buy | H6: FGN 2045 Bond | I6: 0.098 | J6: 53167 | K6: 44334 | L6: 44336 | M6: =YIELD(L6,J6,I6,N6,100,2,1) -> 0.1399995 | N6: 71.1 | O6: 200000000 | P6: =IFERROR((O6*N6/100)+ACCRINT(COUPPCD(L6,J6,2,1),COUPNCD(L6,J6,2,1),L6,I6,O6,2,1),O6*N6/100) -> 148480663 | Q6: =O6*N6/100 -> 142200000 | R6: =IFERROR(ACCRINT(COUPPCD(L6,J6,2,1),COUPNCD(L6,J6,2,0),L6,I6,O6,2,1),"") -> 6280663 | T6: =IFERROR(Q6+R6,Q6) -> 148480663 | V6: Settled
B7: =B6+1 -> 4 | C7: Parthian/Sterling Bank | D7: Stanbic | E7: GIF₦ | F7: Rasheed | G7: Buy | H7: FGN 2027 Bond | I7: 0.162884 | J7: 46463 | K7: 44337 | L7: 44341 | M7: =YIELD(L7,J7,I7,N7,100,2,1) -> 0.13099418 | N7: 112.64 | O7: 100000000 | P7: =IFERROR((O7*N7/100)+ACCRINT(COUPPCD(L7,J7,2,1),COUPNCD(L7,J7,2,1),L7,I7,O7,2,1),O7*N7/100) -> 115694075 | Q7: =O7*N7/100 -> 112640000 | R7: =IFERROR(ACCRINT(COUPPCD(L7,J7,2,1),COUPNCD(L7,J7,2,0),L7,I7,O7,2,1),"") -> 3054075 | T7: =IFERROR(Q7+R7,Q7) -> 115694075 | V7: Settled
B8: =B7+1 -> 5 | C8: Comercio/Coronation MB | D8: Stanbic | E8: GIF₦ | F8: Rasheed | G8: Buy | H8: FGN 2049 Bond | I8: 0.148 | J8: 54539 | K8: 44347 | L8: 44349 | M8: =YIELD(L8,J8,I8,N8,100,2,1) -> 0.13980035 | N8: 105.69 | O8: 500000000 | P8: =IFERROR((O8*N8/100)+ACCRINT(COUPPCD(L8,J8,2,1),COUPNCD(L8,J8,2,1),L8,I8,O8,2,1),O8*N8/100) -> 5.3593087e+08 | Q8: =O8*N8/100 -> 528450000 | R8: =IFERROR(ACCRINT(COUPPCD(L8,J8,2,1),COUPNCD(L8,J8,2,0),L8,I8,O8,2,1),"") -> 7480874.3 | T8: =IFERROR(Q8+R8,Q8) -> 5.3593087e+08 | V8: Settled
B9: =B8+1 -> 6 | C9: Parthian/Sterling Bank | D9: Stanbic | E9: GIF₦ | F9: Rasheed | G9: Buy | H9: FGN 2035 Bond | I9: 0.125 | J9: 49395 | K9: 44348 | L9: =K9+2 -> 44350 | M9: =IFERROR(YIELD(L9,J9,I9,N9,100,2,1),"") -> 0.13819595 | N9: 91.91 | O9: 100000000 | P9: =IFERROR((O9*N9/100)+ACCRINT(COUPPCD(L9,J9,2,1),COUPNCD(L9,J9,2,1),L9,I9,O9,2,1),O9*N9/100) -> 94219783 | Q9: =O9*N9/100 -> 91910000 | R9: =IFERROR(ACCRINT(COUPPCD(L9,J9,2,1),COUPNCD(L9,J9,2,0),L9,I9,O9,2,1),"") -> 2309782.6 | T9: =IFERROR(Q9+R9,Q9) -> 94219783 | V9: Settled
B10: =B9+1 -> 7 | C10: Parthian/Sterling Bank | D10: Stanbic | E10: GIF₦ | F10: Rasheed | G10: Buy | H10: FGN 2050 Bond | I10: 0.1298 | J10: 54874 | K10: 44348 | L10: 44350 | M10: =IFERROR(YIELD(L10,J10,I10,N10,100,2,1),"") -> 0.13919423 | N10: 93.34 | O10: 300000000 | P10: =IFERROR((O10*N10/100)+ACCRINT(COUPPCD(L10,J10,2,1),COUPNCD(L10,J10,2,1),L10,I10,O10,2,1),O10*N10/100) -> 2.8721543e+08 | Q10: =O10*N10/100 -> 280020000 | R10: =IFERROR(ACCRINT(COUPPCD(L10,J10,2,1),COUPNCD(L10,J10,2,0),L10,I10,O10,2,1),"") -> 7195434.8 | T10: =IFERROR(Q10+R10,Q10) -> 2.8721543e+08 | V10: Settled
B11: =B10+1 -> 8 | C11: Parthian/Sterling Bank | D11: Stanbic | E11: GIF₦ | F11: Rasheed | G11: Buy | H11: FGN 2050 Bond | I11: 0.1298 | J11: 54874 | K11: 44348 | L11: 44350 | M11: =IFERROR(YIELD(L11,J11,I11,N11,100,2,1),"") -> 0.13919423 | N11: 93.34 | O11: 200000000 | P11: =IFERROR((O11*N11/100)+ACCRINT(COUPPCD(L11,J11,2,1),COUPNCD(L11,J11,2,1),L11,I11,O11,2,1),O11*N11/100) -> 1.9147696e+08 | Q11: =O11*N11/100 -> 186680000 | R11: =IFERROR(ACCRINT(COUPPCD(L11,J11,2,1),COUPNCD(L11,J11,2,0),L11,I11,O11,2,1),"") -> 4796956.5 | T11: =IFERROR(Q11+R11,Q11) -> 1.9147696e+08 | V11: Settled
B12: =B11+1 -> 9 | C12: Comercio/Coronation MB | D12: Stanbic | E12: GIF₦ | F12: Rasheed | G12: Buy | H12: FGN 2049 Bond | I12: 0.148 | J12: 54539 | K12: 44344 | L12: 44351 | M12: =YIELD(L12,J12,I12,N12,100,2,1) -> 0.14030202 | N12: 105.32 | O12: 500000000 | P12: =IFERROR((O12*N12/100)+ACCRINT(COUPPCD(L12,J12,2,1),COUPNCD(L12,J12,2,1),L12,I12,O12,2,1),O12*N12/100) -> 5.3448525e+08 | Q12: =O12*N12/100 -> 526600000 | R12: =IFERROR(ACCRINT(COUPPCD(L12,J12,2,1),COUPNCD(L12,J12,2,0),L12,I12,O12,2,1),"") -> 7885245.9 | T12: =IFERROR(Q12+R12,Q12) -> 5.3448525e+08 | V12: Settled
B13: =B12+1 -> 10 | C13: Comercio/Coronation MB | D13: Stanbic | E13: GIF₦ | F13: Rasheed | G13: Buy | H13: FGN 2049 Bond | I13: 0.148 | J13: 54539 | K13: 44347 | L13: 44351 | M13: =YIELD(L13,J13,I13,N13,100,2,1) -> 0.13979804 | N13: 105.69 | O13: 300000000 | P13: =IFERROR((O13*N13/100)+ACCRINT(COUPPCD(L13,J13,2,1),COUPNCD(L13,J13,2,1),L13,I13,O13,2,1),O13*N13/100) -> 3.2180115e+08 | Q13: =O13*N13/100 -> 317070000 | R13: =IFERROR(ACCRINT(COUPPCD(L13,J13,2,1),COUPNCD(L13,J13,2,0),L13,I13,O13,2,1),"") -> 4731147.5 | T13: =IFERROR(Q13+R13,Q13) -> 3.2180115e+08 | V13: Settled
B14: =B13+1 -> 11 | C14: Comercio/Coronation MB | D14: Stanbic | E14: GIF₦ | F14: Rasheed | G14: Buy | H14: FGN 2050 Bond | I14: 0.1298 | J14: 54874 | K14: 44348 | L14: 44354 | M14: =IFERROR(YIELD(L14,J14,I14,N14,100,2,1),"") -> 0.13929889 | N14: 93.27 | O14: 300000000 | P14: =IFERROR((O14*N14/100)+ACCRINT(COUPPCD(L14,J14,2,1),COUPNCD(L14,J14,2,1),L14,I14,O14,2,1),O14*N14/100) -> 2.874287e+08 | Q14: =O14*N14/100 -> 279810000 | R14: =IFERROR(ACCRINT(COUPPCD(L14,J14,2,1),COUPNCD(L14,J14,2,0),L14,I14,O14,2,1),"") -> 7618695.7 | T14: =IFERROR(Q14+R14,Q14) -> 2.874287e+08 | V14: Settled
B15: =B14+1 -> 12 | C15: Comercio/Stanbic | D15: Stanbic | E15: GIF₦ | F15: Rasheed | G15: Buy | H15: FGN 2050 Bond | I15: 0.1298 | J15: 54874 | K15: 44371 | L15: 44372 | M15: =IFERROR(YIELD(L15,J15,I15,N15,100,2,1),"") -> 0.137 | N15: 94.807168 | O15: 1000000000 | P15: =IFERROR((O15*N15/100)+ACCRINT(COUPPCD(L15,J15,2,1),COUPNCD(L15,J15,2,1),L15,I15,O15,2,1),O15*N15/100) -> 9.7981625e+08 | Q15: =O15*N15/100 -> 9.4807168e+08 | R15: =IFERROR(ACCRINT(COUPPCD(L15,J15,2,1),COUPNCD(L15,J15,2,0),L15,I15,O15,2,1),"") -> 31744565 | T15: =IFERROR(Q15+R15,Q15) -> 9.7981625e+08 | V15: Settled
B16: =B15+1 -> 13 | C16: Stanbic IBTC | D16: Stanbic | E16: GIF₦ | F16: Rasheed | G16: Buy | H16: FGN 2050 Bond | I16: 0.1298 | J16: 54874 | K16: 44378 | L16: 44382 | M16: =IFERROR(YIELD(L16,J16,I16,N16,100,2,1),"") -> 0.13000005 | N16: 99.7995 | O16: 500000000 | P16: =IFERROR((O16*N16/100)+ACCRINT(COUPPCD(L16,J16,2,1),COUPNCD(L16,J16,2,1),L16,I16,O16,2,1),O16*N16/100) -> 5.1663337e+08 | Q16: =O16*N16/100 -> 498997500 | R16: =IFERROR(ACCRINT(COUPPCD(L16,J16,2,1),COUPNCD(L16,J16,2,0),L16,I16,O16,2,1),"") -> 17635870 | T16: =IFERROR(Q16+R16,Q16) -> 5.1663337e+08 | V16: Settled
B17: =B16+1 -> 14 | C17: Comercio/Coronation MB | D17: Stanbic | E17: GIF₦ | F17: Rasheed | G17: Buy | H17: FGN 2050 Bond | I17: 0.1298 | J17: 54874 | K17: 44379 | L17: 44383 | M17: =IFERROR(YIELD(L17,J17,I17,N17,100,2,1),"") -> 0.12999951 | N17: 99.8 | O17: 1500000000 | P17: =IFERROR((O17*N17/100)+ACCRINT(COUPPCD(L17,J17,2,1),COUPNCD(L17,J17,2,1),L17,I17,O17,2,1),O17*N17/100) -> 1550436685 | Q17: =O17*N17/100 -> 1497000000 | R17: =IFERROR(ACCRINT(COUPPCD(L17,J17,2,1),COUPNCD(L17,J17,2,0),L17,I17,O17,2,1),"") -> 53436685 | T17: =IFERROR(Q17+R17,Q17) -> 1550436685 | V17: Settled
B18: =B17+1 -> 15 | C18: Comercio/Coronation MB | D18: Stanbic | E18: GIF₦ | F18: Rasheed | G18: Sell | H18: FGN 2049 Bond | I18: 0.148 | J18: 54539 | K18: 44382 | L18: 44383 | M18: =IFERROR(YIELD(L18,J18,I18,N18,100,2,1),"") -> 0.13000446 | N18: 113.37 | O18: 700000000 | P18: =IFERROR((O18*N18/100)+ACCRINT(COUPPCD(L18,J18,2,1),COUPNCD(L18,J18,2,1),L18,I18,O18,2,1),O18*N18/100) -> 8.1368727e+08 | Q18: =O18*N18/100 -> 793590000 | R18: =IFERROR(ACCRINT(COUPPCD(L18,J18,2,1),COUPNCD(L18,J18,2,0),L18,I18,O18,2,1),"") -> 20097268 | T18: =IFERROR(Q18+R18,Q18) -> 8.1368727e+08 | V18: Settled
B19: =B18+1 -> 16 | C19: Comercio/Coronation MB | D19: Stanbic | E19: GIF₦ | F19: Rasheed | G19: Sell | H19: FGN 2035 Bond | I19: 0.125 | J19: 49395 | K19: 44382 | L19: 44383 | M19: =IFERROR(YIELD(L19,J19,I19,N19,100,2,1),"") -> 0.12949569 | N19: 97.1 | O19: 100000000 | P19: =IFERROR((O19*N19/100)+ACCRINT(COUPPCD(L19,J19,2,1),COUPNCD(L19,J19,2,1),L19,I19,O19,2,1),O19*N19/100) -> 1.0053071e+08 | Q19: =O19*N19/100 -> 97100000 | R19: =IFERROR(ACCRINT(COUPPCD(L19,J19,2,1),COUPNCD(L19,J19,2,0),L19,I19,O19,2,1),"") -> 3430706.5 | T19: =IFERROR(Q19+R19,Q19) -> 1.0053071e+08 | V19: Settled
B20: =B19+1 -> 17 | C20: Comercio/Coronation MB | D20: Stanbic | E20: GIF₦ | F20: Rasheed | G20: Sell | H20: FGN 2035 Bond | I20: 0.125 | J20: 49395 | K20: 44382 | L20: 44383 | M20: =IFERROR(YIELD(L20,J20,I20,N20,100,2,1),"") -> 0.12949569 | N20: 97.1 | O20: 200000000 | P20: =IFERROR((O20*N20/100)+ACCRINT(COUPPCD(L20,J20,2,1),COUPNCD(L20,J20,2,1),L20,I20,O20,2,1),O20*N20/100) -> 201061413 | Q20: =O20*N20/100 -> 194200000 | R20: =IFERROR(ACCRINT(COUPPCD(L20,J20,2,1),COUPNCD(L20,J20,2,0),L20,I20,O20,2,1),"") -> 6861413 | T20: =IFERROR(Q20+R20,Q20) -> 201061413 | V20: Settled
B21: =B20+1 -> 18 | C21: Stanbic IBTC | D21: Stanbic | E21: GIF₦ | F21: Rasheed | G21: Buy | H21: FGN 2050 Bond | I21: 0.1298 | J21: 54874 | K21: 44378 | L21: 44383 | M21: =IFERROR(YIELD(L21,J21,I21,N21,100,2,1),"") -> 0.13000005 | N21: 99.7996 | O21: 1200000000 | P21: =IFERROR((O21*N21/100)+ACCRINT(COUPPCD(L21,J21,2,1),COUPNCD(L21,J21,2,1),L21,I21,O21,2,1),O21*N21/100) -> 1240344548 | Q21: =O21*N21/100 -> 1197595200 | R21: =IFERROR(ACCRINT(COUPPCD(L21,J21,2,1),COUPNCD(L21,J21,2,0),L21,I21,O21,2,1),"") -> 42749348 | T21: =IFERROR(Q21+R21,Q21) -> 1240344548 | V21: Settled
B22: =B21+1 -> 19 | C22: Stanbic Nominees | D22: Stanbic | E22: SADF$ | F22: Rasheed | G22: Buy | H22: FGN 2050 Bond | I22: 0.1298 | J22: 54874 | K22: 44426 | L22: =K22+2 -> 44428 | M22: =IFERROR(YIELD(L22,J22,I22,N22,100,2,1),"") -> 0.128 | N22: 101.33262 | O22: 900000000 | P22: =IFERROR((O22*N22/100)+ACCRINT(COUPPCD(L22,J22,2,1),COUPNCD(L22,J22,2,1),L22,I22,O22,2,1),O22*N22/100) -> 9.5834067e+08 | Q22: =O22*N22/100 -> 9.119936e+08 | R22: =IFERROR(ACCRINT(COUPPCD(L22,J22,2,1),COUPNCD(L22,J22,2,0),L22,I22,O22,2,1),"") -> 46347065 | T22: =IFERROR(Q22+R22,Q22) -> 9.5834067e+08 | V22: Settled
B23: =B22+1 -> 20 | C23: Comercio/Coronation MB | D23: Stanbic | E23: SADF$ | F23: Rasheed | G23: Buy | H23: FGN 2050 Bond | I23: 0.1298 | J23: 54874 | K23: 44427 | L23: 44431 | M23: =IFERROR(YIELD(L23,J23,I23,N23,100,2,1),"") -> 0.12750026 | N23: 101.72 | O23: 1000000000 | P23: =IFERROR((O23*N23/100)+ACCRINT(COUPPCD(L23,J23,2,1),COUPNCD(L23,J23,2,1),L23,I23,O23,2,1),O23*N23/100) -> 1069754891 | Q23: =O23*N23/100 -> 1017200000 | R23: =IFERROR(ACCRINT(COUPPCD(L23,J23,2,1),COUPNCD(L23,J23,2,0),L23,I23,O23,2,1),"") -> 52554891 | T23: =IFERROR(Q23+R23,Q23) -> 1069754891 | V23: Settled
B24: =B23+1 -> 21 | C24: Comercio/Access | D24: Stanbic | E24: SADF$ | F24: Rasheed | G24: Buy | H24: FGN 2050 Bond | I24: 0.1298 | J24: 54874 | K24: 44427 | L24: 44428 | M24: =IFERROR(YIELD(L24,J24,I24,N24,100,2,1),"") -> 0.12749778 | N24: 101.72 | O24: 500000000 | P24: =IFERROR((O24*N24/100)+ACCRINT(COUPPCD(L24,J24,2,1),COUPNCD(L24,J24,2,1),L24,I24,O24,2,1),O24*N24/100) -> 5.3434837e+08 | Q24: =O24*N24/100 -> 508600000 | R24: =IFERROR(ACCRINT(COUPPCD(L24,J24,2,1),COUPNCD(L24,J24,2,0),L24,I24,O24,2,1),"") -> 25748370 | T24: =IFERROR(Q24+R24,Q24) -> 5.3434837e+08 | V24: Settled
B25: =B24+1 -> 22 | C25: Comercio/Access | D25: Stanbic | E25: SADF$ | F25: Rasheed | G25: Buy | H25: FGN 2050 Bond | I25: 0.1298 | J25: 54874 | K25: 44427 | L25: 44428 | M25: =IFERROR(YIELD(L25,J25,I25,N25,100,2,1),"") -> 0.12749778 | N25: 101.72 | O25: 21106150 | P25: =IFERROR((O25*N25/100)+ACCRINT(COUPPCD(L25,J25,2,1),COUPNCD(L25,J25,2,1),L25,I25,O25,2,1),O25*N25/100) -> 22556074 | Q25: =O25*N25/100 -> 21469176 | R25: =IFERROR(ACCRINT(COUPPCD(L25,J25,2,1),COUPNCD(L25,J25,2,0),L25,I25,O25,2,1),"") -> 1086897.9 | T25: =IFERROR(Q25+R25,Q25) -> 22556074 | V25: Settled
B26: =B25+1 -> 23 | C26: Comercio/Access | D26: Stanbic | E26: GIF₦ | F26: Rasheed | G26: Buy | H26: FGN 2050 Bond | I26: 0.1298 | J26: 54874 | K26: 44427 | L26: 44428 | M26: =IFERROR(YIELD(L26,J26,I26,N26,100,2,1),"") -> 0.12749778 | N26: 101.72 | O26: 278893850 | P26: =IFERROR((O26*N26/100)+ACCRINT(COUPPCD(L26,J26,2,1),COUPNCD(L26,J26,2,1),L26,I26,O26,2,1),O26*N26/100) -> 2.9805295e+08 | Q26: =O26*N26/100 -> 2.8369082e+08 | R26: =IFERROR(ACCRINT(COUPPCD(L26,J26,2,1),COUPNCD(L26,J26,2,0),L26,I26,O26,2,1),"") -> 14362124 | T26: =IFERROR(Q26+R26,Q26) -> 2.9805295e+08 | V26: Settled
B27: =B26+1 -> 24 | C27: Parthian | D27: Stanbic | E27: GIF₦ | F27: Rasheed | G27: Sell | H27: FGN 2050 Bond | I27: 0.1298 | J27: 54874 | K27: 44448 | L27: 44452 | M27: =IFERROR(YIELD(L27,J27,I27,N27,100,2,1),"") -> 0.13119551 | N27: 98.95 | O27: 1000000000 | P27: =IFERROR((O27*N27/100)+ACCRINT(COUPPCD(L27,J27,2,1),COUPNCD(L27,J27,2,1),L27,I27,O27,2,1),O27*N27/100) -> 1049461957 | Q27: =O27*N27/100 -> 989500000 | R27: =IFERROR(ACCRINT(COUPPCD(L27,J27,2,1),COUPNCD(L27,J27,2,0),L27,I27,O27,2,1),"") -> 59961957 | T27: =IFERROR(Q27+R27,Q27) -> 1049461957 | V27: Settled
B28: =B27+1 -> 25 | C28: Parthian | D28: Stanbic | E28: GIF₦ | F28: Rasheed | G28: Sell | H28: FGN 2050 Bond | I28: 0.1298 | J28: 54874 | K28: 44448 | L28: 44452 | M28: =IFERROR(YIELD(L28,J28,I28,N28,100,2,1),"") -> 0.13119551 | N28: 98.95 | O28: 500000000 | P28: =IFERROR((O28*N28/100)+ACCRINT(COUPPCD(L28,J28,2,1),COUPNCD(L28,J28,2,1),L28,I28,O28,2,1),O28*N28/100) -> 5.2473098e+08 | Q28: =O28*N28/100 -> 494750000 | R28: =IFERROR(ACCRINT(COUPPCD(L28,J28,2,1),COUPNCD(L28,J28,2,0),L28,I28,O28,2,1),"") -> 29980978 | T28: =IFERROR(Q28+R28,Q28) -> 5.2473098e+08 | V28: Settled
B29: =B28+1 -> 26 | C29: Parthian | D29: Stanbic | E29: GIF₦ | F29: Rasheed | G29: Sell | H29: FGN 2050 Bond | I29: 0.1298 | J29: 54874 | K29: 44448 | L29: 44452 | M29: =IFERROR(YIELD(L29,J29,I29,N29,100,2,1),"") -> 0.13119551 | N29: 98.95 | O29: 200000000 | P29: =IFERROR((O29*N29/100)+ACCRINT(COUPPCD(L29,J29,2,1),COUPNCD(L29,J29,2,1),L29,I29,O29,2,1),O29*N29/100) -> 2.0989239e+08 | Q29: =O29*N29/100 -> 197900000 | R29: =IFERROR(ACCRINT(COUPPCD(L29,J29,2,1),COUPNCD(L29,J29,2,0),L29,I29,O29,2,1),"") -> 11992391 | T29: =IFERROR(Q29+R29,Q29) -> 2.0989239e+08 | V29: Settled
B30: =B29+1 -> 27 | C30: Parthian | D30: Stanbic | E30: GIF₦ | F30: Rasheed | G30: Sell | H30: FGN 2050 Bond | I30: 0.1298 | J30: 54874 | K30: 44448 | L30: 44453 | M30: =IFERROR(YIELD(L30,J30,I30,N30,100,2,1),"") -> 0.13119683 | N30: 98.95 | O30: 500000000 | P30: =IFERROR((O30*N30/100)+ACCRINT(COUPPCD(L30,J30,2,1),COUPNCD(L30,J30,2,1),L30,I30,O30,2,1),O30*N30/100) -> 524907337 | Q30: =O30*N30/100 -> 494750000 | R30: =IFERROR(ACCRINT(COUPPCD(L30,J30,2,1),COUPNCD(L30,J30,2,0),L30,I30,O30,2,1),"") -> 30157337 | T30: =IFERROR(Q30+R30,Q30) -> 524907337 | V30: Settled
B31: =B30+1 -> 28 | C31: Parthian | D31: Stanbic | E31: GIF₦ | F31: Rasheed | G31: Sell | H31: FGN 2050 Bond | I31: 0.1298 | J31: 54874 | K31: 44448 | L31: 44452 | M31: =IFERROR(YIELD(L31,J31,I31,N31,100,2,1),"") -> 0.13119551 | N31: 98.95 | O31: 300000000 | P31: =IFERROR((O31*N31/100)+ACCRINT(COUPPCD(L31,J31,2,1),COUPNCD(L31,J31,2,1),L31,I31,O31,2,1),O31*N31/100) -> 314838587 | Q31: =O31*N31/100 -> 296850000 | R31: =IFERROR(ACCRINT(COUPPCD(L31,J31,2,1),COUPNCD(L31,J31,2,0),L31,I31,O31,2,1),"") -> 17988587 | T31: =IFERROR(Q31+R31,Q31) -> 314838587 | V31: Settled
B32: =B31+1 -> 29 | C32: Parthian | D32: Stanbic | E32: GIF₦ | F32: Rasheed | G32: Sell | H32: FGN 2049 Bond | I32: 0.148 | J32: 54539 | K32: 44453 | L32: 44455 | M32: =IFERROR(YIELD(L32,J32,I32,N32,100,2,1),"") -> 0.12999814 | N32: 113.38 | O32: 500000000 | P32: =IFERROR((O32*N32/100)+ACCRINT(COUPPCD(L32,J32,2,1),COUPNCD(L32,J32,2,1),L32,I32,O32,2,1),O32*N32/100) -> 5.9581257e+08 | Q32: =O32*N32/100 -> 566900000 | R32: =IFERROR(ACCRINT(COUPPCD(L32,J32,2,1),COUPNCD(L32,J32,2,0),L32,I32,O32,2,1),"") -> 28912568 | T32: =IFERROR(Q32+R32,Q32) -> 5.9581257e+08 | V32: Settled
B33: =B32+1 -> 30 | C33: Parthian | D33: Stanbic | E33: GIF₦ | F33: Rasheed | G33: Sell | H33: FGN 2049 Bond | I33: 0.148 | J33: 54539 | K33: 44453 | L33: 44455 | M33: =IFERROR(YIELD(L33,J33,I33,N33,100,2,1),"") -> 0.12999814 | N33: 113.38 | O33: 100000000 | P33: =IFERROR((O33*N33/100)+ACCRINT(COUPPCD(L33,J33,2,1),COUPNCD(L33,J33,2,1),L33,I33,O33,2,1),O33*N33/100) -> 1.1916251e+08 | Q33: =O33*N33/100 -> 113380000 | R33: =IFERROR(ACCRINT(COUPPCD(L33,J33,2,1),COUPNCD(L33,J33,2,0),L33,I33,O33,2,1),"") -> 5782513.7 | T33: =IFERROR(Q33+R33,Q33) -> 1.1916251e+08 | V33: Settled
B34: =B33+1 -> 31 | C34: Parthian | D34: Stanbic | E34: GIF₦ | F34: Rasheed | G34: Buy | H34: FGN 2028 Bond | I34: 0.1398 | J34: 46806 | K34: 44455 | L34: 44459 | M34: =IFERROR(YIELD(L34,J34,I34,N34,100,2,1),"") -> 0.11519949 | N34: 110.93 | O34: 500000000 | P34: =IFERROR((O34*N34/100)+ACCRINT(COUPPCD(L34,J34,2,1),COUPNCD(L34,J34,2,1),L34,I34,O34,2,1),O34*N34/100) -> 5.5996848e+08 | Q34: =O34*N34/100 -> 554650000 | R34: =IFERROR(ACCRINT(COUPPCD(L34,J34,2,1),COUPNCD(L34,J34,2,0),L34,I34,O34,2,1),"") -> 5318478.3 | T34: =IFERROR(Q34+R34,Q34) -> 5.5996848e+08 | V34: Settled
... B62: =B61+1 -> 59 | C62: Union Bank | D62: Stanbic | E62: GIF₦ | F62: Rasheed | G62: Sell | H62: FGN 2028 Bond | I62: 0.1398 | J62: 46806 | K62: 44498 | L62: 44502 | M62: =IFERROR(YIELD(L62,J62,I62,N62,100,2,1),"") -> 0.123 | N62: 107.17574 | O62: 879000000 | P62: =IFERROR((O62*N62/100)+ACCRINT(COUPPCD(L62,J62,2,1),COUPNCD(L62,J62,2,1),L62,I62,O62,2,1),O62*N62/100) -> 9.6578341e+08 | Q62: =O62*N62/100 -> 9.4207477e+08 | R62: =IFERROR(ACCRINT(COUPPCD(L62,J62,2,1),COUPNCD(L62,J62,2,0),L62,I62,O62,2,1),"") -> 23708636 | T62: =IFERROR(Q62+R62,Q62) -> 9.6578341e+08 | V62: Settled
B63: =B62+1 -> 60 | C63: Parthian/Sterling Bank | D63: Stanbic | E63: GIF₦ | F63: Rasheed | G63: Sell | H63: FGN 2026 Bond | I63: 0.125 | J63: 46044 | K63: 44579 | L63: 44581 | M63: =IFERROR(YIELD(L63,J63,I63,N63,100,2,1),"") -> 0.11564837 | N63: 102.93 | O63: 194000000 | P63: =IFERROR((O63*N63/100)+ACCRINT(COUPPCD(L63,J63,2,1),COUPNCD(L63,J63,2,1),L63,I63,O63,2,1),O63*N63/100) -> 2.1167741e+08 | Q63: =O63*N63/100 -> 199684200 | R63: =IFERROR(ACCRINT(COUPPCD(L63,J63,2,1),COUPNCD(L63,J63,2,0),L63,I63,O63,2,1),"") -> 11993207 | T63: =IFERROR(Q63+R63,Q63) -> 2.1167741e+08
B64: =B63+1 -> 61 | C64: Parthian/Sterling Bank | D64: Stanbic | E64: GIF₦ | F64: Rasheed | G64: Sell | H64: FGN 2027 Bond | I64: 0.162884 | J64: 46463 | K64: 44579 | L64: 44581 | M64: =IFERROR(YIELD(L64,J64,I64,N64,100,2,1),"") -> 0.12263022 | N64: 115 | O64: 100000000 | P64: =IFERROR((O64*N64/100)+ACCRINT(COUPPCD(L64,J64,2,1),COUPNCD(L64,J64,2,1),L64,I64,O64,2,1),O64*N64/100) -> 1.2062445e+08 | Q64: =O64*N64/100 -> 115000000 | R64: =IFERROR(ACCRINT(COUPPCD(L64,J64,2,1),COUPNCD(L64,J64,2,0),L64,I64,O64,2,1),"") -> 5624447.5 | T64: =IFERROR(Q64+R64,Q64) -> 1.2062445e+08
B65: =B64+1 -> 62 | C65: Access bank | D65: Stanbic | E65: GIF₦ | F65: Victor | G65: Buy | H65: FGN 2037 bond | I65: 0.162499 | J65: 50148 | K65: 44915 | L65: 44917 | M65: =IFERROR(YIELD(L65,J65,I65,N65,100,2,1),"") -> 0.14199738 | N65: 112.35 | O65: 2000000000 | P65: =IFERROR((O65*N65/100)+ACCRINT(COUPPCD(L65,J65,2,1),COUPNCD(L65,J65,2,1),L65,I65,O65,2,1),O65*N65/100) -> 2305035357 | Q65: =O65*N65/100 -> 2247000000 | R65: =IFERROR(ACCRINT(COUPPCD(L65,J65,2,1),COUPNCD(L65,J65,2,0),L65,I65,O65,2,1),"") -> 58035357 | T65: =IFERROR(Q65+R65,Q65) -> 2305035357
B66: =B65+1 -> 63 | C66: Access bank | D66: Stanbic | E66: GIF₦ | F66: Victor | G66: Buy | H66: FGN 2037 bond | I66: 0.162499 | J66: 50148 | K66: 44944 | L66: 44946 | M66: =IFERROR(YIELD(L66,J66,I66,N66,100,2,1),"") -> 0.14550183 | N66: 110.03 | O66: 2000000000 | P66: =IFERROR((O66*N66/100)+ACCRINT(COUPPCD(L66,J66,2,1),COUPNCD(L66,J66,2,1),L66,I66,O66,2,1),O66*N66/100) -> 2284528055 | Q66: =O66*N66/100 -> 2200600000 | R66: =IFERROR(ACCRINT(COUPPCD(L66,J66,2,1),COUPNCD(L66,J66,2,0),L66,I66,O66,2,1),"") -> 83928055 | T66: =IFERROR(Q66+R66,Q66) -> 2284528055
B67: =B66+1 -> 64 | C67: Access bank | D67: Stanbic | E67: GIF₦ | F67: Victor | G67: Buy | H67: FGN 2049 bond | I67: 0.148 | J67: 54539 | K67: 44965 | L67: 44967 | M67: =IFERROR(YIELD(L67,J67,I67,N67,100,2,1),"") -> 0.15649283 | N67: 94.61 | O67: 5000000000 | P67: =IFERROR((O67*N67/100)+ACCRINT(COUPPCD(L67,J67,2,1),COUPNCD(L67,J67,2,1),L67,I67,O67,2,1),O67*N67/100) -> 4948027473 | Q67: =O67*N67/100 -> 4730500000 | R67: =IFERROR(ACCRINT(COUPPCD(L67,J67,2,1),COUPNCD(L67,J67,2,0),L67,I67,O67,2,1),"") -> 2.1752747e+08 | T67: =IFERROR(Q67+R67,Q67) -> 4948027473
B68: =B67+1 -> 65 | C68: Access bank | D68: Stanbic | E68: GIF₦ | F68: Victor | G68: Buy | H68: FGN 2049 bond | I68: 0.148 | J68: 54539 | K68: 44973 | L68: 44977 | M68: =IFERROR(YIELD(L68,J68,I68,N68,100,2,1),"") -> 0.15749594 | N68: 94.02 | O68: 1000000000 | P68: =IFERROR((O68*N68/100)+ACCRINT(COUPPCD(L68,J68,2,1),COUPNCD(L68,J68,2,1),L68,I68,O68,2,1),O68*N68/100) -> 9.8777143e+08 | Q68: =O68*N68/100 -> 940200000 | R68: =IFERROR(ACCRINT(COUPPCD(L68,J68,2,1),COUPNCD(L68,J68,2,0),L68,I68,O68,2,1),"") -> 47571429 | S68: =$S$1*O68 -> 537500 | T68: =IFERROR(Q68+R68+S68,Q68) -> 9.8830893e+08
B69: =B68+1 -> 66 | C69: Keystone bank | D69: Stanbic | E69: GIF₦ | F69: William | G69: Buy | H69: FGN 2037 bond | I69: 0.1625 | J69: 50148 | K69: 44993 | L69: 44998 | M69: =IFERROR(YIELD(L69,J69,I69,N69,100,2,1),"") -> 0.15149494 | N69: 106.29 | O69: 800000000 | P69: =IFERROR((O69*N69/100)+ACCRINT(COUPPCD(L69,J69,2,1),COUPNCD(L69,J69,2,1),L69,I69,O69,2,1),O69*N69/100) -> 9.0246286e+08 | Q69: =O69*N69/100 -> 850320000 | R69: =IFERROR(ACCRINT(COUPPCD(L69,J69,2,1),COUPNCD(L69,J69,2,0),L69,I69,O69,2,1),"") -> 52142857 | S69: =$S$1*O69 -> 430000 | T69: =IFERROR(Q69+R69+S69,Q69) -> 9.0289286e+08
B70: =B69+1 -> 67 | C70: Keystone bank | D70: Stanbic | E70: GIF₦ | F70: William | G70: Sell | H70: FGN 2049 bond | I70: 0.148 | J70: 54539 | K70: 45100 | L70: 45104 | M70: =IFERROR(YIELD(L70,J70,I70,N70,100,2,1),"") -> 0.15599279 | N70: 94.92 | O70: 6000000000 | P70: =IFERROR((O70*N70/100)+ACCRINT(COUPPCD(L70,J70,2,1),COUPNCD(L70,J70,2,1),L70,I70,O70,2,1),O70*N70/100) -> 5845626230 | Q70: =O70*N70/100 -> 5695200000 | R70: =IFERROR(ACCRINT(COUPPCD(L70,J70,2,1),COUPNCD(L70,J70,2,0),L70,I70,O70,2,1),"") -> 1.5042623e+08 | T70: =IFERROR(Q70+R70,Q70) -> 5845626230
B71: =B70+1 -> 68 | C71: Keystone bank | D71: Stanbic | E71: GIF₦ | F71: William | G71: Buy | H71: FGN 2050 Bond | I71: 0.1298 | J71: 54874 | K71: 45120 | L71: 45124 | M71: =IFERROR(YIELD(L71,J71,I71,N71,100,2,1),"") -> 0.13999768 | N71: 92.86 | O71: 5300000000 | P71: =IFERROR((O71*N71/100)+ACCRINT(COUPPCD(L71,J71,2,1),COUPNCD(L71,J71,2,1),L71,I71,O71,2,1),O71*N71/100) -> 5130953043 | Q71: =O71*N71/100 -> 4921580000 | R71: =IFERROR(ACCRINT(COUPPCD(L71,J71,2,1),COUPNCD(L71,J71,2,0),L71,I71,O71,2,1),"") -> 2.0937304e+08 | T71: =IFERROR(Q71+R71,Q71) -> 5130953043
B72: =B71+1 -> 69 | C72: Keystone bank | D72: Stanbic | E72: GIF₦ | F72: Victor | G72: Sell | H72: FGN 2037 bond | I72: 0.1625 | J72: 50148 | K72: 45230 | L72: 45231 | M72: =IFERROR(YIELD(L72,J72,I72,N72,100,2,1),"") -> 0.16500309 | N72: 98.64 | O72: 800000000 | P72: =IFERROR((O72*N72/100)+ACCRINT(COUPPCD(L72,J72,2,1),COUPNCD(L72,J72,2,1),L72,I72,O72,2,1),O72*N72/100) -> 7.9409268e+08 | Q72: =O72*N72/100 -> 789120000 | R72: =IFERROR(ACCRINT(COUPPCD(L72,J72,2,1),COUPNCD(L72,J72,2,0),L72,I72,O72,2,1),"") -> 4972677.6 | T72: =IFERROR(Q72+R72,Q72) -> 7.9409268e+08
B73: =B72+1 -> 70 | C73: Keystone bank | D73: Stanbic | E73: GIF₦ | F73: Victor | G73: Sell | H73: FGN 2037 bond | I73: 0.1625 | J73: 50148 | K73: 45230 | L73: 45232 | M73: =IFERROR(YIELD(L73,J73,I73,N73,100,2,1),"") -> 0.16500046 | N73: 98.64 | O73: 1000000000 | P73: =IFERROR((O73*N73/100)+ACCRINT(COUPPCD(L73,J73,2,1),COUPNCD(L73,J73,2,1),L73,I73,O73,2,1),O73*N73/100) -> 9.9305984e+08 | Q73: =O73*N73/100 -> 986400000 | R73: =IFERROR(ACCRINT(COUPPCD(L73,J73,2,1),COUPNCD(L73,J73,2,0),L73,I73,O73,2,1),"") -> 6659836.1 | T73: =IFERROR(Q73+R73,Q73) -> 9.9305984e+08
B74: =B73+1 -> 71 | C74: Keystone bank | D74: Stanbic | E74: GIF₦ | F74: Victor | G74: Sell | H74: FGN 2037 bond | I74: 0.1625 | J74: 50148 | K74: 45232 | L74: 45233 | M74: =IFERROR(YIELD(L74,J74,I74,N74,100,2,1),"") -> 0.16501679 | N74: 98.63 | O74: 500000000 | P74: =IFERROR((O74*N74/100)+ACCRINT(COUPPCD(L74,J74,2,1),COUPNCD(L74,J74,2,1),L74,I74,O74,2,1),O74*N74/100) -> 4.9670191e+08 | Q74: =O74*N74/100 -> 493150000 | R74: =IFERROR(ACCRINT(COUPPCD(L74,J74,2,1),COUPNCD(L74,J74,2,0),L74,I74,O74,2,1),"") -> 3551912.6 | T74: =IFERROR(Q74+R74,Q74) -> 4.9670191e+08
B75: =B74+1 -> 72 | C75: Keystone bank | D75: Stanbic | E75: GIF₦ | F75: Victor | G75: Sell | H75: FGN 2037 bond | I75: 0.1625 | J75: 50148 | K75: 45233 | L75: 45237 | M75: =IFERROR(YIELD(L75,J75,I75,N75,100,2,1),"") -> 0.16647326 | N75: 97.86 | O75: 300000000 | P75: =IFERROR((O75*N75/100)+ACCRINT(COUPPCD(L75,J75,2,1),COUPNCD(L75,J75,2,1),L75,I75,O75,2,1),O75*N75/100) -> 2.9624393e+08 | Q75: =O75*N75/100 -> 293580000 | R75: =IFERROR(ACCRINT(COUPPCD(L75,J75,2,1),COUPNCD(L75,J75,2,0),L75,I75,O75,2,1),"") -> 2663934.4 | T75: =IFERROR(Q75+R75,Q75) -> 2.9624393e+08
B76: =B75+1 -> 73 | C76: Keystone bank | D76: Stanbic | E76: GIF₦ | F76: Victor | G76: Sell | H76: FGN 2037 bond | I76: 0.1625 | J76: 50148 | K76: 45239 | L76: 45243 | M76: =IFERROR(YIELD(L76,J76,I76,N76,100,2,1),"") -> 0.16950961 | N76: 96.29 | O76: 2000000000 | P76: =IFERROR((O76*N76/100)+ACCRINT(COUPPCD(L76,J76,2,1),COUPNCD(L76,J76,2,1),L76,I76,O76,2,1),O76*N76/100) -> 1948887432 | Q76: =O76*N76/100 -> 1925800000 | R76: =IFERROR(ACCRINT(COUPPCD(L76,J76,2,1),COUPNCD(L76,J76,2,0),L76,I76,O76,2,1),"") -> 23087432 | T76: =IFERROR(Q76+R76,Q76) -> 1948887432
B77: =B76+1 -> 74 | C77: Parthian/Sterling Bank | D77: Stanbic | E77: GIF₦ | F77: Oise | G77: Buy | H77: NIGTB 7/Nov/2024 | I77: 0 | J77: 45603 | K77: 45243 | L77: 45610 | M77: =IFERROR(YIELD(L77,J77,I77,N77,100,2,1),"") | N77: 85.0852 | O77: 1000000000 | P77: =IFERROR((O77*N77/100)+ACCRINT(COUPPCD(L77,J77,2,1),COUPNCD(L77,J77,2,1),L77,I77,O77,2,1),O77*N77/100) -> 850852000 | Q77: =O77*N77/100 -> 850852000 | T77: =IFERROR(Q77+R77,Q77) -> 850852000
B78: =B77+1 -> 75 | C78: Comercio/Stanbic | D78: Stanbic | E78: GIF₦ | F78: Oise | G78: Buy | H78: NIGTB 7/Nov/2024 | I78: 0 | J78: 45603 | K78: 45243 | L78: 45610 | M78: =IFERROR(YIELD(L78,J78,I78,N78,100,2,1),"") | N78: 85.0852 | O78: 2000000000 | P78: =IFERROR((O78*N78/100)+ACCRINT(COUPPCD(L78,J78,2,1),COUPNCD(L78,J78,2,1),L78,I78,O78,2,1),O78*N78/100) -> 1701704000 | Q78: =O78*N78/100 -> 1701704000 | R78: =IFERROR(ACCRINT(COUPPCD(L78,J78,2,1),COUPNCD(L78,J78,2,0),L78,I78,O78,2,1),"") | T78: =IFERROR(Q78+R78,Q78) -> 1701704000
B79: =B78+1 -> 76 | C79: Keystone bank | D79: Stanbic | E79: GIF₦ | F79: Oise | G79: Sell | H79: FGN 2050 Bond | I79: 0.1298 | J79: 54874 | K79: 45250 | L79: 45252 | M79: =IFERROR(YIELD(L79,J79,I79,N79,100,2,1),"") -> 0.17898855 | N79: 72.76 | O79: 4800000000 | P79: =IFERROR((O79*N79/100)+ACCRINT(COUPPCD(L79,J79,2,1),COUPNCD(L79,J79,2,1),L79,I79,O79,2,1),O79*N79/100) -> 3588332308 | Q79: =O79*N79/100 -> 3492480000 | R79: =IFERROR(ACCRINT(COUPPCD(L79,J79,2,1),COUPNCD(L79,J79,2,0),L79,I79,O79,2,1),"") -> 95852308 | T79: =IFERROR(Q79+R79,Q79) -> 3588332308
B80: =B79+1 -> 77 | C80: Keystone bank | D80: Stanbic | E80: GIF₦ | F80: Oise | G80: Sell | H80: FGN 2050 Bond | I80: 0.1298 | J80: 54874 | K80: 45250 | L80: 45253 | M80: =IFERROR(YIELD(L80,J80,I80,N80,100,2,1),"") -> 0.17898746 | N80: 72.76 | O80: 500000000 | P80: =IFERROR((O80*N80/100)+ACCRINT(COUPPCD(L80,J80,2,1),COUPNCD(L80,J80,2,1),L80,I80,O80,2,1),O80*N80/100) -> 3.7396291e+08 | Q80: =O80*N80/100 -> 363800000 | R80: =IFERROR(ACCRINT(COUPPCD(L80,J80,2,1),COUPNCD(L80,J80,2,0),L80,I80,O80,2,1),"") -> 10162912 | T80: =IFERROR(Q80+R80,Q80) -> 3.7396291e+08
B81: =B80+1 -> 78 | C81: Keystone bank | D81: Stanbic | E81: GIF₦ | F81: Oise | G81: Sell | H81: FGN 2037 bond | I81: 0.162499 | J81: 50148 | K81: 45253 | L81: 45257 | M81: =IFERROR(YIELD(L81,J81,I81,N81,100,2,1),"") -> 0.16999576 | N81: 96.03 | O81: 200000000 | P81: =IFERROR((O81*N81/100)+ACCRINT(COUPPCD(L81,J81,2,1),COUPNCD(L81,J81,2,1),L81,I81,O81,2,1),O81*N81/100) -> 1.9561189e+08 | Q81: =O81*N81/100 -> 192060000 | R81: =IFERROR(ACCRINT(COUPPCD(L81,J81,2,1),COUPNCD(L81,J81,2,0),L81,I81,O81,2,1),"") -> 3551890.7 | T81: =IFERROR(Q81+R81,Q81) -> 1.9561189e+08
B82: =B81+1 -> 79 | C82: Stanbic Nominees | D82: Stanbic | E82: GIF₦ | F82: Oise | G82: Buy | H82: NIGTB 5/Dec/2024 | I82: 0 | J82: 45631 | K82: 45266 | L82: 45267 | M82: 0.155 | N82: 84.584699 | O82: 1000000000 | P82: =IFERROR((O82*N82/100)+ACCRINT(COUPPCD(L82,J82,2,1),COUPNCD(L82,J82,2,1),L82,I82,O82,2,1),O82*N82/100) -> 8.4584699e+08 | Q82: =O82*N82/100 -> 8.4584699e+08 | R82: =IFERROR(ACCRINT(COUPPCD(L82,J82,2,1),COUPNCD(L82,J82,2,0),L82,I82,O82,2,1),"") | T82: =IFERROR(Q82+R82,Q82) -> 8.4584699e+08
B83: =B82+1 -> 80 | C83: Keystone bank | D83: Stanbic | E83: GIF₦ | F83: Oise | G83: Buy | H83: FGN 2053 bond | I83: 0.157 | J83: 56056 | K83: 45274 | L83: 45275 | M83: =IFERROR(YIELD(L83,J83,I83,N83,100,2,1),"") -> 0.15949974 | N83: 98.44 | O83: 500000000 | P83: =IFERROR((O83*N83/100)+ACCRINT(COUPPCD(L83,J83,2,1),COUPNCD(L83,J83,2,1),L83,I83,O83,2,1),O83*N83/100) -> 5.3016311e+08 | Q83: =O83*N83/100 -> 492200000 | R83: =IFERROR(ACCRINT(COUPPCD(L83,J83,2,1),COUPNCD(L83,J83,2,0),L83,I83,O83,2,1),"") -> 37963115 | T83: =IFERROR(Q83+R83,Q83) -> 5.3016311e+08
B84: =B83+1 -> 81 | C84: Keystone bank | D84: Stanbic | E84: GIF₦ | F84: Oise | G84: Buy | H84: FGN 2053 bond | I84: 0.157 | J84: 56056 | K84: 45274 | L84: 45278 | M84: =IFERROR(YIELD(L84,J84,I84,N84,100,2,1),"") -> 0.15950755 | N84: 98.44 | O84: 4500000000 | P84: =IFERROR((O84*N84/100)+ACCRINT(COUPPCD(L84,J84,2,1),COUPNCD(L84,J84,2,1),L84,I84,O84,2,1),O84*N84/100) -> 4777259016 | Q84: =O84*N84/100 -> 4429800000 | R84: =IFERROR(ACCRINT(COUPPCD(L84,J84,2,1),COUPNCD(L84,J84,2,0),L84,I84,O84,2,1),"") -> 3.4745902e+08 | T84: =IFERROR(Q84+R84,Q84) -> 4777259016
B85: =B84+1 -> 82 | C85: Stanbic Nominees | D85: Stanbic | E85: GIF₦ | F85: Oise | G85: Sell | H85: NIGTB 7/Nov/2024 | I85: 0 | J85: 45603 | K85: 45280 | L85: 45280 | M85: 0.11751196 | N85: =PRICEDISC(K85,J85,M85,100,1) -> 89.628353 | O85: 2000000000 | P85: =IFERROR((O85*N85/100)+ACCRINT(COUPPCD(L85,J85,2,1),COUPNCD(L85,J85,2,1),L85,I85,O85,2,1),O85*N85/100) -> 1792567069 | Q85: =O85*N85/100 -> 1792567069 | R85: =IFERROR(ACCRINT(COUPPCD(L85,J85,2,1),COUPNCD(L85,J85,2,0),L85,I85,O85,2,1),"") | T85: =IFERROR(Q85+R85,Q85) -> 1792567069
B86: =B85+1 -> 83 | C86: Keystone bank | D86: Stanbic | E86: GIF₦ | F86: Oise | G86: Buy | H86: FGN 2053 bond | I86: 0.157 | J86: 56056 | K86: 45280 | L86: 45282 | M86: =IFERROR(YIELD(L86,J86,I86,N86,100,2,1),"") -> 0.16150088 | N86: 97.24 | O86: 1700000000 | P86: =IFERROR((O86*N86/100)+ACCRINT(COUPPCD(L86,J86,2,1),COUPNCD(L86,J86,2,1),L86,I86,O86,2,1),O86*N86/100) -> 1653809235 | Q86: =O86*N86/100 -> 1653080000 | R86: =IFERROR(ACCRINT(COUPPCD(L86,J86,2,1),COUPNCD(L86,J86,2,0),L86,I86,O86,2,1),"") -> 729234.97 | T86: =IFERROR(Q86+R86,Q86) -> 1653809235
B87: =B86+1 -> 84 | C87: Comercio/Stanbic | D87: Stanbic | E87: GIF₦ | F87: Oise | G87: Sell | H87: NIGTB 7/Nov/2024 | I87: 0 | J87: 45603 | K87: 45282 | L87: 45282 | M87: 0.117 | N87: =PRICEDISC(L87,J87,M87,100,1) -> 89.737649 | O87: 1000000000 | P87: =IFERROR((O87*N87/100)+ACCRINT(COUPPCD(L87,J87,2,1),COUPNCD(L87,J87,2,1),L87,I87,O87,2,1),O87*N87/100) -> 8.9737649e+08 | Q87: =O87*N87/100 -> 8.9737649e+08 | R87: =IFERROR(ACCRINT(COUPPCD(L87,J87,2,1),COUPNCD(L87,J87,2,0),L87,I87,O87,2,1),"") | T87: =IFERROR(Q87+R87,Q87) -> 8.9737649e+08
B88: =B87+1 -> 85 | C88: Comercio/Stanbic | D88: Stanbic | E88: GIF₦ | F88: Oise | G88: Sell | H88: NIGTB 5/Dec/2024 | I88: 0 | J88: 45631 | K88: 45282 | L88: 45282 | M88: 0.117 | N88: =PRICEDISC(L88,J88,M88,100,1) -> 88.842567 | O88: 1000000000 | P88: =IFERROR((O88*N88/100)+ACCRINT(COUPPCD(L88,J88,2,1),COUPNCD(L88,J88,2,1),L88,I88,O88,2,1),O88*N88/100) -> 8.8842567e+08 | Q88: =O88*N88/100 -> 8.8842567e+08 | R88: =IFERROR(ACCRINT(COUPPCD(L88,J88,2,1),COUPNCD(L88,J88,2,0),L88,I88,O88,2,1),"") | T88: =IFERROR(Q88+R88,Q88) -> 8.8842567e+08
B89: =B88+1 -> 86 | C89: Keystone bank | D89: Stanbic | E89: GIF₦ | F89: Oise | G89: Buy | H89: FGN 2053 bond | I89: 0.157 | J89: 56056 | K89: 45282 | L89: 45287 | M89: =IFERROR(YIELD(L89,J89,I89,N89,100,2,1),"") -> 0.16200886 | N89: 96.93 | O89: 2400000000 | P89: =IFERROR((O89*N89/100)+ACCRINT(COUPPCD(L89,J89,2,1),COUPNCD(L89,J89,2,1),L89,I89,O89,2,1),O89*N89/100) -> 2332497049 | Q89: =O89*N89/100 -> 2326320000 | R89: =IFERROR(ACCRINT(COUPPCD(L89,J89,2,1),COUPNCD(L89,J89,2,0),L89,I89,O89,2,1),"") -> 6177049.2 | T89: =IFERROR(Q89+R89,Q89) -> 2332497049
B90: =B89+1 -> 87 | C90: Keystone bank | D90: Stanbic | E90: GIF₦ | F90: Oise | G90: Sell | H90: FGN 2053 bond | I90: 0.157 | J90: 56056 | K90: 45334 | L90: 45336 | M90: =IFERROR(YIELD(L90,J90,I90,N90,100,2,1),"") -> 0.1789988 | N90: 87.72 | O90: 800000000 | P90: =IFERROR((O90*N90/100)+ACCRINT(COUPPCD(L90,J90,2,1),COUPNCD(L90,J90,2,1),L90,I90,O90,2,1),O90*N90/100) -> 7.2063432e+08 | Q90: =O90*N90/100 -> 701760000 | R90: =IFERROR(ACCRINT(COUPPCD(L90,J90,2,1),COUPNCD(L90,J90,2,0),L90,I90,O90,2,1),"") -> 18874317 | T90: =IFERROR(Q90+R90,Q90) -> 7.2063432e+08
B91: =B90+1 -> 88 | C91: Keystone bank | D91: Stanbic | E91: GIF₦ | F91: Oise | G91: Sell | H91: FGN 2053 bond | I91: 0.157 | J91: 56056 | K91: 45334 | L91: 45337 | M91: =IFERROR(YIELD(L91,J91,I91,N91,100,2,1),"") -> 0.18300665 | N91: 85.8 | O91: 1800000000 | P91: =IFERROR((O91*N91/100)+ACCRINT(COUPPCD(L91,J91,2,1),COUPNCD(L91,J91,2,1),L91,I91,O91,2,1),O91*N91/100) -> 1587639344 | Q91: =O91*N91/100 -> 1544400000 | R91: =IFERROR(ACCRINT(COUPPCD(L91,J91,2,1),COUPNCD(L91,J91,2,0),L91,I91,O91,2,1),"") -> 43239344 | T91: =IFERROR(Q91+R91,Q91) -> 1587639344
B92: =B91+1 -> 89 | C92: Keystone bank | D92: Stanbic | E92: GIF₦ | F92: Oise | G92: Sell | H92: FGN 2053 bond | I92: 0.157 | J92: 56056 | K92: 45334 | L92: 45338 | M92: =IFERROR(YIELD(L92,J92,I92,N92,100,2,1),"") -> 0.18300518 | N92: 85.8 | O92: 1000000000 | P92: =IFERROR((O92*N92/100)+ACCRINT(COUPPCD(L92,J92,2,1),COUPNCD(L92,J92,2,1),L92,I92,O92,2,1),O92*N92/100) -> 8.8245082e+08 | Q92: =O92*N92/100 -> 858000000 | R92: =IFERROR(ACCRINT(COUPPCD(L92,J92,2,1),COUPNCD(L92,J92,2,0),L92,I92,O92,2,1),"") -> 24450820 | T92: =IFERROR(Q92+R92,Q92) -> 8.8245082e+08
B93: =B92+1 -> 90 | C93: Keystone bank | D93: Stanbic | E93: GIF₦ | F93: Oise | G93: Sell | H93: FGN 2053 bond | I93: 0.157 | J93: 56056 | K93: 45334 | L93: 45341 | M93: =IFERROR(YIELD(L93,J93,I93,N93,100,2,1),"") -> 0.18300105 | N93: 85.8 | O93: 250000000 | P93: =IFERROR((O93*N93/100)+ACCRINT(COUPPCD(L93,J93,2,1),COUPNCD(L93,J93,2,1),L93,I93,O93,2,1),O93*N93/100) -> 2.2093443e+08 | Q93: =O93*N93/100 -> 214500000 | R93: =IFERROR(ACCRINT(COUPPCD(L93,J93,2,1),COUPNCD(L93,J93,2,0),L93,I93,O93,2,1),"") -> 6434426.2 | T93: =IFERROR(Q93+R93,Q93) -> 2.2093443e+08
B94: =B93+1 -> 91 | C94: Keystone bank | D94: Stanbic | E94: GIF₦ | F94: Oise | G94: Sell | H94: FGN 2053 bond | I94: 0.157 | J94: 56056 | K94: 45334 | L94: 45341 | M94: =IFERROR(YIELD(L94,J94,I94,N94,100,2,1),"") -> 0.18300105 | N94: 85.8 | O94: 300000000 | P94: =IFERROR((O94*N94/100)+ACCRINT(COUPPCD(L94,J94,2,1),COUPNCD(L94,J94,2,1),L94,I94,O94,2,1),O94*N94/100) -> 2.6512131e+08 | Q94: =O94*N94/100 -> 257400000 | R94: =IFERROR(ACCRINT(COUPPCD(L94,J94,2,1),COUPNCD(L94,J94,2,0),L94,I94,O94,2,1),"") -> 7721311.5 | T94: =IFERROR(Q94+R94,Q94) -> 2.6512131e+08
B95: =B94+1 -> 92 | C95: Keystone bank | D95: Stanbic | E95: GIF₦ | F95: Oise | G95: Buy | H95: NIGTB 20/Feb/2025 | I95: 0 | J95: 45708 | K95: 45343 | L95: 45344 | M95: 0.18195 | N95: =PRICEDISC(L95,J95,M95,100,1) -> 81.897616 | O95: 1000000000 | P95: =IFERROR((O95*N95/100)+ACCRINT(COUPPCD(L95,J95,2,1),COUPNCD(L95,J95,2,1),L95,I95,O95,2,1),O95*N95/100) -> 8.1897616e+08 | Q95: =O95*N95/100 -> 8.1897616e+08 | R95: =IFERROR(ACCRINT(COUPPCD(L95,J95,2,1),COUPNCD(L95,J95,2,0),L95,I95,O95,2,1),"") | T95: =IFERROR(Q95+R95,Q95) -> 8.1897616e+08
B96: =B95+1 -> 93 | C96: Keystone bank | D96: Stanbic | E96: GIF₦ | F96: Oise | G96: Buy | H96: NIGTB 20/Feb/2025 | I96: 0 | J96: 45708 | K96: 45343 | L96: 45344 | M96: 0.18899 | N96: =PRICEDISC(L96,J96,M96,100,1) -> 81.1972 | O96: 1000000000 | P96: =IFERROR((O96*N96/100)+ACCRINT(COUPPCD(L96,J96,2,1),COUPNCD(L96,J96,2,1),L96,I96,O96,2,1),O96*N96/100) -> 8.11972e+08 | Q96: =O96*N96/100 -> 8.11972e+08 | R96: =IFERROR(ACCRINT(COUPPCD(L96,J96,2,1),COUPNCD(L96,J96,2,0),L96,I96,O96,2,1),"") | T96: =IFERROR(Q96+R96,Q96) -> 8.11972e+08
B97: =B96+1 -> 94 | C97: Stanbic Nominees | D97: Stanbic | E97: GIF₦ | F97: Oise | G97: Buy | H97: NIGTB 20/Feb/2025 | I97: 0 | J97: 45708 | K97: 45343 | L97: 45344 | M97: 0.19 | N97: =PRICEDISC(L97,J97,M97,100,1) -> 81.096714 | O97: 1700000000 | P97: =IFERROR((O97*N97/100)+ACCRINT(COUPPCD(L97,J97,2,1),COUPNCD(L97,J97,2,1),L97,I97,O97,2,1),O97*N97/100) -> 1378644135 | Q97: =O97*N97/100 -> 1378644135 | R97: =IFERROR(ACCRINT(COUPPCD(L97,J97,2,1),COUPNCD(L97,J97,2,0),L97,I97,O97,2,1),"") | T97: =IFERROR(Q97+R97,Q97) -> 1378644135
B98: =B97+1 -> 95 | C98: Keystone bank | D98: Stanbic | E98: GIF₦ | F98: Oise | G98: Sell | H98: FGN 2053 bond | I98: 0.157 | J98: 56056 | K98: 45348 | L98: 45350 | M98: =IFERROR(YIELD(L98,J98,I98,N98,100,2,1),"") -> 0.18900209 | N98: 83.07 | O98: 3300000000 | P98: =IFERROR((O98*N98/100)+ACCRINT(COUPPCD(L98,J98,2,1),COUPNCD(L98,J98,2,1),L98,I98,O98,2,1),O98*N98/100) -> 2838984590 | Q98: =O98*N98/100 -> 2741310000 | R98: =IFERROR(ACCRINT(COUPPCD(L98,J98,2,1),COUPNCD(L98,J98,2,0),L98,I98,O98,2,1),"") -> 97674590 | T98: =IFERROR(Q98+R98,Q98) -> 2838984590
B99: =B98+1 -> 96 | C99: Keystone bank | D99: Stanbic | E99: GIF₦ | F99: Oise | G99: Sell | H99: FGN 2053 bond | I99: 0.157 | J99: 56056 | K99: 45349 | L99: 45351 | M99: =IFERROR(YIELD(L99,J99,I99,N99,100,2,1),"") -> 0.1890011 | N99: 83.07 | O99: 450000000 | P99: =IFERROR((O99*N99/100)+ACCRINT(COUPPCD(L99,J99,2,1),COUPNCD(L99,J99,2,1),L99,I99,O99,2,1),O99*N99/100) -> 3.873273e+08 | Q99: =O99*N99/100 -> 373815000 | R99: =IFERROR(ACCRINT(COUPPCD(L99,J99,2,1),COUPNCD(L99,J99,2,0),L99,I99,O99,2,1),"") -> 13512295 | T99: =IFERROR(Q99+R99,Q99) -> 3.873273e+08
B100: =B99+1 -> 97 | C100: Parthian | D100: Stanbic | E100: GIF₦ | F100: Oise | G100: Sell | H100: NIGTB 20/Feb/2025 | I100: 0 | J100: 45708 | K100: 45349 | L100: 45351 | M100: 0.1865 | N100: =PRICEDISC(L100,J100,M100,100,1) -> 81.801626 | O100: 2000000000 | P100: =IFERROR((O100*N100/100)+ACCRINT(COUPPCD(L100,J100,2,1),COUPNCD(L100,J100,2,1),L100,I100,O100,2,1),O100*N100/100) -> 1636032525 | Q100: =O100*N100/100 -> 1636032525 | R100: =IFERROR(ACCRINT(COUPPCD(L100,J100,2,1),COUPNCD(L100,J100,2,0),L100,I100,O100,2,1),"") | T100: =IFERROR(Q100+R100,Q100) -> 1636032525
B101: =B100+1 -> 98 | C101: Parthian | D101: Stanbic | E101: GIF₦ | F101: Oise | G101: Sell | H101: NIGTB 20/Feb/2025 | I101: 0 | J101: 45708 | K101: 45349 | L101: 45351 | M101: 0.187 | N101: =PRICEDISC(L101,J101,M101,100,1) -> 81.752837 | O101: 1700000000 | P101: =IFERROR((O101*N101/100)+ACCRINT(COUPPCD(L101,J101,2,1),COUPNCD(L101,J101,2,1),L101,I101,O101,2,1),O101*N101/100) -> 1389798230 | Q101: =O101*N101/100 -> 1389798230 | R101: =IFERROR(ACCRINT(COUPPCD(L101,J101,2,1),COUPNCD(L101,J101,2,0),L101,I101,O101,2,1),"") | T101: =IFERROR(Q101+R101,Q101) -> 1389798230
B102: =B101+1 -> 99 | C102: Keystone bank | D102: Stanbic | E102: GIF₦ | F102: Oise | G102: Sell | H102: FGN 2053 bond | I102: 0.157 | J102: 56056 | K102: 45350 | L102: 45352 | M102: =IFERROR(YIELD(L102,J102,I102,N102,100,2,1),"") -> 0.18900016 | N102: 83.07 | O102: 400000000 | P102: =IFERROR((O102*N102/100)+ACCRINT(COUPPCD(L102,J102,2,1),COUPNCD(L102,J102,2,1),L102,I102,O102,2,1),O102*N102/100) -> 3.4446251e+08 | Q102: =O102*N102/100 -> 332280000 | R102: =IFERROR(ACCRINT(COUPPCD(L102,J102,2,1),COUPNCD(L102,J102,2,0),L102,I102,O102,2,1),"") -> 12182514 | T102: =IFERROR(Q102+R102,Q102) -> 3.4446251e+08
B103: =B102+1 -> 100 | C103: Stanbic Nominees | D103: Stanbic | E103: GIF₦ | F103: Oise | G103: Buy | H103: NIGTB 6/Mar/2025 | I103: 0 | J103: 45722 | K103: 45357 | L103: 45358 | M103: 0.2 | N103: =PRICEDISC(L103,J103,M103,100,1) -> 80.099708 | O103: 1000000000 | P103: =IFERROR((O103*N103/100)+ACCRINT(COUPPCD(L103,J103,2,1),COUPNCD(L103,J103,2,1),L103,I103,O103,2,1),O103*N103/100) -> 8.0099708e+08 | Q103: =O103*N103/100 -> 8.0099708e+08 | R103: =IFERROR(ACCRINT(COUPPCD(L103,J103,2,1),COUPNCD(L103,J103,2,0),L103,I103,O103,2,1),"") | T103: =IFERROR(Q103+R103,Q103) -> 8.0099708e+08
B104: =B103+1 -> 101 | C104: Keystone bank | D104: Stanbic | E104: GIF₦ | F104: Oise | G104: Buy | H104: NIGTB 6/Mar/2025 | I104: 0 | J104: 45722 | K104: 45357 | L104: 45358 | M104: 0.196 | N104: =PRICEDISC(L104,J104,M104,100,1) -> 80.497714 | O104: 500000000 | P104: =IFERROR((O104*N104/100)+ACCRINT(COUPPCD(L104,J104,2,1),COUPNCD(L104,J104,2,1),L104,I104,O104,2,1),O104*N104/100) -> 4.0248857e+08 | Q104: =O104*N104/100 -> 4.0248857e+08 | R104: =IFERROR(ACCRINT(COUPPCD(L104,J104,2,1),COUPNCD(L104,J104,2,0),L104,I104,O104,2,1),"") | T104: =IFERROR(Q104+R104,Q104) -> 4.0248857e+08
B105: =B104+1 -> 102 | C105: Keystone bank | D105: Stanbic | E105: GIF₦ | F105: Oise | G105: Buy | H105: NIGTB 6/Mar/2025 | I105: 0 | J105: 45722 | K105: 45357 | L105: 45358 | M105: 0.1984 | N105: =PRICEDISC(L105,J105,M105,100,1) -> 80.25891 | O105: 500000000 | P105: =IFERROR((O105*N105/100)+ACCRINT(COUPPCD(L105,J105,2,1),COUPNCD(L105,J105,2,1),L105,I105,O105,2,1),O105*N105/100) -> 401294552 | Q105: =O105*N105/100 -> 401294552 | R105: =IFERROR(ACCRINT(COUPPCD(L105,J105,2,1),COUPNCD(L105,J105,2,0),L105,I105,O105,2,1),"") | T105: =IFERROR(Q105+R105,Q105) -> 401294552
B106: =B105+1 -> 103 | C106: Keystone bank | D106: Stanbic | E106: GIF₦ | F106: Oise | G106: Buy | H106: NIGTB 6/Mar/2025 | I106: 0 | J106: 45722 | K106: 45357 | L106: 45358 | M106: 0.2 | N106: =PRICEDISC(L106,J106,M106,100,1) -> 80.099708 | O106: 500000000 | P106: =IFERROR((O106*N106/100)+ACCRINT(COUPPCD(L106,J106,2,1),COUPNCD(L106,J106,2,1),L106,I106,O106,2,1),O106*N106/100) -> 4.0049854e+08 | Q106: =O106*N106/100 -> 4.0049854e+08 | R106: =IFERROR(ACCRINT(COUPPCD(L106,J106,2,1),COUPNCD(L106,J106,2,0),L106,I106,O106,2,1),"") | T106: =IFERROR(Q106+R106,Q106) -> 4.0049854e+08
B107: =B106+1 -> 104 | C107: Keystone bank | D107: Stanbic | E107: GIF₦ | F107: Oise | G107: Buy | H107: NIGTB 6/Mar/2025 | I107: 0 | J107: 45722 | K107: 45357 | L107: 45358 | M107: 0.1975 | N107: =PRICEDISC(L107,J107,M107,100,1) -> 80.348462 | O107: 5500000000 | P107: =IFERROR((O107*N107/100)+ACCRINT(COUPPCD(L107,J107,2,1),COUPNCD(L107,J107,2,1),L107,I107,O107,2,1),O107*N107/100) -> 4419165394 | Q107: =O107*N107/100 -> 4419165394 | R107: =IFERROR(ACCRINT(COUPPCD(L107,J107,2,1),COUPNCD(L107,J107,2,0),L107,I107,O107,2,1),"") | T107: =IFERROR(Q107+R107,Q107) -> 4419165394
B108: =B107+1 -> 105 | C108: Keystone bank | D108: Stanbic | E108: GIF₦ | F108: Oise | G108: Sell | H108: NIGTB 6/Mar/2025 | I108: 0 | J108: 45722 | K108: 45372 | L108: 45373 | M108: 0.193 | N108: =PRICEDISC(L108,J108,M108,100,1) -> 81.587202 | O108: 2000000000 | P108: =IFERROR((O108*N108/100)+ACCRINT(COUPPCD(L108,J108,2,1),COUPNCD(L108,J108,2,1),L108,I108,O108,2,1),O108*N108/100) -> 1631744038 | Q108: =O108*N108/100 -> 1631744038 | R108: =IFERROR(ACCRINT(COUPPCD(L108,J108,2,1),COUPNCD(L108,J108,2,0),L108,I108,O108,2,1),"") | T108: =IFERROR(Q108+R108,Q108) -> 1631744038
B109: =B108+1 -> 106 | C109: Keystone bank | D109: Stanbic | E109: GIF₦ | F109: Oise | G109: Sell | H109: NIGTB 6/Mar/2025 | I109: 0 | J109: 45722 | K109: 45372 | L109: 45376 | M109: 0.193 | N109: =PRICEDISC(L109,J109,M109,100,1) -> 81.745399 | O109: 2000000000 | P109: =IFERROR((O109*N109/100)+ACCRINT(COUPPCD(L109,J109,2,1),COUPNCD(L109,J109,2,1),L109,I109,O109,2,1),O109*N109/100) -> 1634907972 | Q109: =O109*N109/100 -> 1634907972 | R109: =IFERROR(ACCRINT(COUPPCD(L109,J109,2,1),COUPNCD(L109,J109,2,0),L109,I109,O109,2,1),"") | T109: =IFERROR(Q109+R109,Q109) -> 1634907972
B110: =B109+1 -> 107 | C110: Keystone bank | D110: Stanbic | E110: GIF₦ | F110: Oise | G110: Buy | H110: NIGTB 27/Mar/2025 | I110: 0 | J110: 45743 | K110: 45379 | L110: 45379 | M110: 0.1835 | N110: =PRICEDISC(L110,J110,M110,100,1) -> 81.738598 | O110: 4700000000 | P110: =IFERROR((O110*N110/100)+ACCRINT(COUPPCD(L110,J110,2,1),COUPNCD(L110,J110,2,1),L110,I110,O110,2,1),O110*N110/100) -> 3841714086 | Q110: =O110*N110/100 -> 3841714086 | R110: =IFERROR(ACCRINT(COUPPCD(L110,J110,2,1),COUPNCD(L110,J110,2,0),L110,I110,O110,2,1),"") | T110: =IFERROR(Q110+R110,Q110) -> 3841714086
B111: =B110+1 -> 108 | C111: Keystone bank | D111: Stanbic | E111: GIF₦ | F111: Ife | G111: Sell | H111: NIGTB 6/Mar/2025 | I111: 0 | J111: 45722 | K111: 45394 | L111: 45398 | M111: 0.1945 | N111: =PRICEDISC(L111,J111,M111,100,1) -> 82.772649 | O111: 4000000000 | P111: 3.310906e+09 | Q111: 3.310906e+09 | R111: =IFERROR(ACCRINT(COUPPCD(L111,J111,2,1),COUPNCD(L111,J111,2,0),L111,I111,O111,2,1),"") | T111: =IFERROR(Q111+R111,Q111) -> 3310905966
B112: =B111+1 -> 109 | C112: Stanbic Nominees | D112: Stanbic | E112: GIF₦ | F112: Ife | G112: Buy | H112: FGN 2034 bond | I112: 0.19 | J112: 48996 | K112: 45397 | L112: 45399 | M112: =IFERROR(YIELD(L112,J112,I112,N112,100,2,1),"") -> 0.2 | N112: 95.669503 | O112: 3300000000 | P112: =IFERROR((O112*N112/100)+ACCRINT(COUPPCD(L112,J112,2,1),COUPNCD(L112,J112,2,1),L112,I112,O112,2,1),O112*N112/100) -> 3253555142 | Q112: =O112*N112/100 -> 3157093604 | R112: =IFERROR(ACCRINT(COUPPCD(L112,J112,2,1),COUPNCD(L112,J112,2,0),L112,I112,O112,2,1),"") -> 96461538 | T112: =IFERROR(Q112+R112,Q112) -> 3253555142
B113: =B112+1 -> 110 | C113: Keystone bank | D113: Stanbic | E113: GIF₦ | F113: Ife | G113: Sell | H113: NIGTB 27/Mar/2025 | I113: 0 | J113: 45743 | K113: 45405 | L113: 45406 | M113: 0.2115 | N113: =PRICEDISC(L113,J113,M113,100,1) -> 80.512362 | O113: 3150000000 | P113: =IFERROR((O113*N113/100)+ACCRINT(COUPPCD(L113,J113,2,1),COUPNCD(L113,J113,2,1),L113,I113,O113,2,1),O113*N113/100) -> 2536139417 | Q113: =O113*N113/100 -> 2536139417 | R113: =IFERROR(ACCRINT(COUPPCD(L113,J113,2,1),COUPNCD(L113,J113,2,0),L113,I113,O113,2,1),"") | T113: =IFERROR(Q113+R113,Q113) -> 2536139417
B114: =B113+1 -> 111 | C114: Keystone bank | D114: Stanbic | E114: GIF₦ | F114: Ife | G114: Buy | H114: FGN 2034 bond | I114: 0.19 | J114: 48996 | K114: 45406 | L114: 45408 | M114: =IFERROR(YIELD(L114,J114,I114,N114,100,2,1),"") -> 0.19499353 | N114: 97.75 | O114: 1000000000 | P114: =IFERROR((O114*N114/100)+ACCRINT(COUPPCD(L114,J114,2,1),COUPNCD(L114,J114,2,1),L114,I114,O114,2,1),O114*N114/100) -> 1011428571 | Q114: =O114*N114/100 -> 977500000 | R114: =IFERROR(ACCRINT(COUPPCD(L114,J114,2,1),COUPNCD(L114,J114,2,0),L114,I114,O114,2,1),"") -> 33928571 | T114: =IFERROR(Q114+R114,Q114) -> 1011428571
B115: =B114+1 -> 112 | C115: Parthian | D115: Stanbic | E115: GIF₦ | F115: Ife | G115: Buy | H115: FGN 2027 bond | I115: 0.1994 | J115: 46466 | K115: 45407 | L115: 45408 | M115: =IFERROR(YIELD(L115,J115,I115,N115,100,2,1),"") -> 0.19274904 | N115: 101.35375 | O115: 1000000000 | P115: =IFERROR((O115*N115/100)+ACCRINT(COUPPCD(L115,J115,2,1),COUPNCD(L115,J115,2,1),L115,I115,O115,2,1),O115*N115/100) -> 1033585870 | Q115: =O115*N115/100 -> 1013537500 | R115: =IFERROR(ACCRINT(COUPPCD(L115,J115,2,1),COUPNCD(L115,J115,2,0),L115,I115,O115,2,1),"") -> 20048370 | T115: =IFERROR(Q115+R115,Q115) -> 1033585870
B116: =B115+1 -> 113 | C116: Keystone bank | D116: Stanbic | E116: GIF₦ | F116: Oise | G116: Sell | H116: NIGTB 27/Mar/2025 | I116: 0 | J116: 45743 | K116: 45421 | L116: 45422 | M116: 0.208 | N116: =PRICEDISC(L116,J116,M116,100,1) -> 81.744143 | O116: 1000000000 | P116: =IFERROR((O116*N116/100)+ACCRINT(COUPPCD(L116,J116,2,1),COUPNCD(L116,J116,2,1),L116,I116,O116,2,1),O116*N116/100) -> 8.1744143e+08 | Q116: =O116*N116/100 -> 8.1744143e+08 | R116: =IFERROR(ACCRINT(COUPPCD(L116,J116,2,1),COUPNCD(L116,J116,2,0),L116,I116,O116,2,1),"") | T116: =IFERROR(Q116+R116,Q116) -> 8.1744143e+08
B117: =B116+1 -> 114 | C117: Parthian | D117: Stanbic | E117: GIF₦ | F117: Victor | G117: Sell | H117: NIGTB 27/Mar/2025 | I117: 0 | J117: 45743 | K117: 45432 | L117: 45433 | M117: 0.207 | N117: =PRICEDISC(L117,J117,M117,100,1) -> 82.454042 | O117: 350000000 | P117: =IFERROR((O117*N117/100)+ACCRINT(COUPPCD(L117,J117,2,1),COUPNCD(L117,J117,2,1),L117,I117,O117,2,1),O117*N117/100) -> 2.8858915e+08 | Q117: =O117*N117/100 -> 2.8858915e+08 | R117: =IFERROR(ACCRINT(COUPPCD(L117,J117,2,1),COUPNCD(L117,J117,2,0),L117,I117,O117,2,1),"") | T117: =IFERROR(Q117+R117,Q117) -> 2.8858915e+08
B118: =B117+1 -> 115 | C118: Keystone bank | D118: Stanbic | E118: GIF₦ | F118: Victor | G118: Buy | H118: NIGTB 05/Jun/2025 | I118: 0 | J118: 45813 | K118: 45464 | L118: 45467 | M118: 0.2 | N118: =PRICEDISC(L118,J118,M118,100,1) -> 81.069691 | O118: 1650000000 | P118: =IFERROR((O118*N118/100)+ACCRINT(COUPPCD(L118,J118,2,1),COUPNCD(L118,J118,2,1),L118,I118,O118,2,1),O118*N118/100) -> 1337649899 | Q118: =O118*N118/100 -> 1337649899 | R118: =IFERROR(ACCRINT(COUPPCD(L118,J118,2,1),COUPNCD(L118,J118,2,0),L118,I118,O118,2,1),"") | T118: =IFERROR(Q118+R118,Q118) -> 1337649899
B119: =B118+1 -> 116 | C119: Keystone bank | D119: Stanbic | E119: GIF₦ | F119: Victor | G119: Sell | H119: FGN 2034 bond | I119: 0.19 | J119: 48996 | K119: 45470 | L119: 45471 | M119: =IFERROR(YIELD(L119,J119,I119,N119,100,2,1),"") -> 0.21050925 | N119: 91.57 | O119: 1500000000 | P119: =IFERROR((O119*N119/100)+ACCRINT(COUPPCD(L119,J119,2,1),COUPNCD(L119,J119,2,1),L119,I119,O119,2,1),O119*N119/100) -> 1473769780 | Q119: =O119*N119/100 -> 1373550000 | R119: =IFERROR(ACCRINT(COUPPCD(L119,J119,2,1),COUPNCD(L119,J119,2,0),L119,I119,O119,2,1),"") -> 1.0021978e+08 | T119: =IFERROR(Q119+R119,Q119) -> 1473769780
B120: =B119+1 -> 117 | C120: Keystone bank | D120: Stanbic | E120: GIF₦ | F120: Victor | G120: Sell | H120: FGN 2034 bond | I120: 0.19 | J120: 48996 | K120: 45484 | L120: 45485 | M120: =IFERROR(YIELD(L120,J120,I120,N120,100,2,1),"") -> 0.21400292 | N120: 90.29 | O120: 1000000000 | P120: =IFERROR((O120*N120/100)+ACCRINT(COUPPCD(L120,J120,2,1),COUPNCD(L120,J120,2,1),L120,I120,O120,2,1),O120*N120/100) -> 9.7702088e+08 | Q120: =O120*N120/100 -> 902900000 | R120: =IFERROR(ACCRINT(COUPPCD(L120,J120,2,1),COUPNCD(L120,J120,2,0),L120,I120,O120,2,1),"") -> 74120879 | T120: =IFERROR(Q120+R120,Q120) -> 9.7702088e+08
B121: =B120+1 -> 118 | C121: Keystone bank | D121: Stanbic | E121: GIF₦ | F121: Victor | G121: Sell | H121: FGN 2034 bond | I121: 0.19 | J121: 48996 | K121: 45485 | L121: 45488 | M121: =IFERROR(YIELD(L121,J121,I121,N121,100,2,1),"") -> 0.21402253 | N121: 90.29 | O121: 400000000 | P121: =IFERROR((O121*N121/100)+ACCRINT(COUPPCD(L121,J121,2,1),COUPNCD(L121,J121,2,1),L121,I121,O121,2,1),O121*N121/100) -> 3.9143473e+08 | Q121: =O121*N121/100 -> 361160000 | R121: =IFERROR(ACCRINT(COUPPCD(L121,J121,2,1),COUPNCD(L121,J121,2,0),L121,I121,O121,2,1),"") -> 30274725 | T121: =IFERROR(Q121+R121,Q121) -> 3.9143473e+08
B122: =B121+1 -> 119 | C122: Keystone bank | D122: Stanbic | E122: GIF₦ | F122: Victor | G122: Buy | H122: NIGTB 10/Jul/2025 | I122: 0 | J122: 45848 | K122: 45490 | L122: 45492 | M122: 0.2 | N122: =PRICEDISC(L122,J122,M122,100,1) -> 80.518003 | O122: 1600000000 | P122: =IFERROR((O122*N122/100)+ACCRINT(COUPPCD(L122,J122,2,1),COUPNCD(L122,J122,2,1),L122,I122,O122,2,1),O122*N122/100) -> 1288288046 | Q122: =O122*N122/100 -> 1288288046 | R122: =IFERROR(ACCRINT(COUPPCD(L122,J122,2,1),COUPNCD(L122,J122,2,0),L122,I122,O122,2,1),"") | T122: =IFERROR(Q122+R122,Q122) -> 1288288046
B123: =B122+1 -> 120 | C123: Keystone bank | D123: Stanbic | E123: GIF₦ | F123: Victor | G123: Sell | H123: FGN 2034 bond | I123: 0.19 | J123: 48996 | K123: 45498 | L123: 45499 | M123: =IFERROR(YIELD(L123,J123,I123,N123,100,2,1),"") -> 0.22699615 | N123: 85.72 | O123: 1400000000 | P123: =IFERROR((O123*N123/100)+ACCRINT(COUPPCD(L123,J123,2,1),COUPNCD(L123,J123,2,1),L123,I123,O123,2,1),O123*N123/100) -> 1314080000 | Q123: =O123*N123/100 -> 1200080000 | R123: =IFERROR(ACCRINT(COUPPCD(L123,J123,2,1),COUPNCD(L123,J123,2,0),L123,I123,O123,2,1),"") -> 114000000 | T123: =IFERROR(Q123+R123,Q123) -> 1314080000
B124: =B123+1 -> 121 | C124: Keystone bank | D124: Stanbic | E124: GIF₦ | F124: Victor | G124: Buy | H124: NIGTB 22/May/2025 | I124: 0 | J124: 45799 | K124: 45499 | L124: 45502 | M124: 0.222 | N124: =PRICEDISC(L124,J124,M124,100,1) -> 81.961815 | O124: 1600000000 | P124: =IFERROR((O124*N124/100)+ACCRINT(COUPPCD(L124,J124,2,1),COUPNCD(L124,J124,2,1),L124,I124,O124,2,1),O124*N124/100) -> 1311389032 | Q124: =O124*N124/100 -> 1311389032 | R124: =IFERROR(ACCRINT(COUPPCD(L124,J124,2,1),COUPNCD(L124,J124,2,0),L124,I124,O124,2,1),"") | T124: =IFERROR(Q124+R124,Q124) -> 1311389032
B125: =B124+1 -> 122 | C125: Keystone bank | D125: Stanbic | E125: GIF₦ | F125: Victor | G125: Sell | H125: NIGTB 05/Jun/2025 | I125: 0 | J125: 45813 | K125: 45510 | L125: 45511 | M125: 0.225 | N125: =PRICEDISC(L125,J125,M125,100,1) -> 81.40832 | O125: 400000000 | P125: =IFERROR((O125*N125/100)+ACCRINT(COUPPCD(L125,J125,2,1),COUPNCD(L125,J125,2,1),L125,I125,O125,2,1),O125*N125/100) -> 3.2563328e+08 | Q125: =O125*N125/100 -> 3.2563328e+08 | R125: =IFERROR(ACCRINT(COUPPCD(L125,J125,2,1),COUPNCD(L125,J125,2,0),L125,I125,O125,2,1),"") | T125: =IFERROR(Q125+R125,Q125) -> 3.2563328e+08
B126: =B125+1 -> 123 | C126: Keystone bank | D126: Stanbic | E126: GIF₦ | F126: Victor | G126: Sell | H126: NIGTB 22/May/2025 | I126: 0 | J126: 45799 | K126: 45533 | L126: 45534 | M126: 0.1975 | N126: =PRICEDISC(L126,J126,M126,100,1) -> 85.679291 | O126: 1600000000 | P126: =IFERROR((O126*N126/100)+ACCRINT(COUPPCD(L126,J126,2,1),COUPNCD(L126,J126,2,1),L126,I126,O126,2,1),O126*N126/100) -> 1370868658 | Q126: =O126*N126/100 -> 1370868658 | R126: =IFERROR(ACCRINT(COUPPCD(L126,J126,2,1),COUPNCD(L126,J126,2,0),L126,I126,O126,2,1),"") | T126: =IFERROR(Q126+R126,Q126) -> 1370868658
B127: =B126+1 -> 124 | C127: Keystone bank | D127: Stanbic | E127: GIF₦ | F127: Victor | G127: Sell | H127: NIGTB 10/Jul/2025 | I127: 0 | J127: 45848 | K127: 45533 | L127: 45534 | M127: 0.197 | N127: =PRICEDISC(L127,J127,M127,100,1) -> 83.070889 | O127: 800000000 | P127: =IFERROR((O127*N127/100)+ACCRINT(COUPPCD(L127,J127,2,1),COUPNCD(L127,J127,2,1),L127,I127,O127,2,1),O127*N127/100) -> 6.6456711e+08 | Q127: =O127*N127/100 -> 6.6456711e+08 | R127: =IFERROR(ACCRINT(COUPPCD(L127,J127,2,1),COUPNCD(L127,J127,2,0),L127,I127,O127,2,1),"") | T127: =IFERROR(Q127+R127,Q127) -> 6.6456711e+08
B128: =B127+1 -> 125 | C128: Keystone bank | D128: Stanbic | E128: GIF₦ | F128: Victor | G128: Buy | H128: FGN 2033 bond | I128: 0.1989 | J128: 48714 | K128: 45534 | L128: 45537 | M128: =IFERROR(YIELD(L128,J128,I128,N128,100,2,1),"") -> 0.19260087 | N128: 102.5 | O128: 500000000 | P128: =IFERROR((O128*N128/100)+ACCRINT(COUPPCD(L128,J128,2,1),COUPNCD(L128,J128,2,1),L128,I128,O128,2,1),O128*N128/100) -> 5.422269e+08 | Q128: =O128*N128/100 -> 512500000 | R128: =IFERROR(ACCRINT(COUPPCD(L128,J128,2,1),COUPNCD(L128,J128,2,0),L128,I128,O128,2,1),"") -> 29726902 | T128: =IFERROR(Q128+R128,Q128) -> 5.422269e+08
...

Sheet Copy of NGN Domestic Trade Trac
B1: S/N | C1: CP | D1: Settlement Bank | E1: Portfolio | F1: Trader | G1: Direction | H1: Name of Asset | I1: Coupon Rate | J1: Maturity Date | K1: Trade Date | L1: Settlement Date | M1: Ytm | N1: Price | O1: Face Value | P1: Consideration | Q1: Principal | R1: Accrued Interest | S1: fees | T1: Consideration | V1: Status
B2: 1 | C2: Parthian/Sterling Bank | D2: Stanbic | E2: GIF₦ | F2: Rasheed | G2: Buy | H2: FGN 2026 Bond | I2: 0.125 | J2: 46044 | K2: 44327 | L2: 44330 | M2: =IFERROR(YIELD(L2,J2,I2,N2,100,2,1),"") -> 0.1289945 | N2: 98.58 | O2: 194000000 | P2: =IFERROR((O2*N2/100)+ACCRINT(COUPPCD(L2,J2,2,1),COUPNCD(L2,J2,2,1),L2,I2,O2,2,1),O2*N2/100) -> 1.9874796e+08 | Q2: =O2*N2/100 -> 191245200 | R2: =IFERROR(ACCRINT(COUPPCD(L2,J2,2,1),COUPNCD(L2,J2,2,0),L2,I2,O2,2,1),"") -> 7502762.4 | T2: =IFERROR(Q2+R2,Q2) -> 1.9874796e+08 | V2: Settled
B3: =B2+1 -> 2 | C3: Parthian/Sterling Bank | D3: Stanbic | E3: GIF₦ | F3: Rasheed | G3: Buy | H3: FGN 2035 Bond | I3: 0.125 | J3: 49395 | K3: 44327 | L3: 44333 | M3: =IFERROR(YIELD(L3,J3,I3,N3,100,2,1),"") -> 0.13859495 | N3: 91.68 | O3: 200000000 | P3: =IFERROR((O3*N3/100)+ACCRINT(COUPPCD(L3,J3,2,1),COUPNCD(L3,J3,2,1),L3,I3,O3,2,1),O3*N3/100) -> 1.8682467e+08 | Q3: =O3*N3/100 -> 183360000 | R3: =IFERROR(ACCRINT(COUPPCD(L3,J3,2,1),COUPNCD(L3,J3,2,0),L3,I3,O3,2,1),"") -> 3464673.9 | T3: =IFERROR(Q3+R3,Q3) -> 1.8682467e+08 | V3: Settled
B4: =B3+1 -> 3 | C4: Comercio/Coronation MB | D4: Stanbic | E4: GIF₦ | F4: Rasheed | G4: Buy | H4: FGN 2045 Bond | I4: 0.098 | J4: 53167 | K4: 44334 | L4: 44336 | M4: =YIELD(L4,J4,I4,N4,100,2,1) -> 0.1399995 | N4: 71.1 | O4: 200000000 | P4: =IFERROR((O4*N4/100)+ACCRINT(COUPPCD(L4,J4,2,1),COUPNCD(L4,J4,2,1),L4,I4,O4,2,1),O4*N4/100) -> 148480663 | Q4: =O4*N4/100 -> 142200000 | R4: =IFERROR(ACCRINT(COUPPCD(L4,J4,2,1),COUPNCD(L4,J4,2,0),L4,I4,O4,2,1),"") -> 6280663 | T4: =IFERROR(Q4+R4,Q4) -> 148480663 | V4: Settled
B5: =B4+1 -> 4 | C5: Parthian/Sterling Bank | D5: Stanbic | E5: GIF₦ | F5: Rasheed | G5: Buy | H5: FGN 2027 Bond | I5: 0.162884 | J5: 46463 | K5: 44337 | L5: 44341 | M5: =YIELD(L5,J5,I5,N5,100,2,1) -> 0.13099418 | N5: 112.64 | O5: 100000000 | P5: =IFERROR((O5*N5/100)+ACCRINT(COUPPCD(L5,J5,2,1),COUPNCD(L5,J5,2,1),L5,I5,O5,2,1),O5*N5/100) -> 115694075 | Q5: =O5*N5/100 -> 112640000 | R5: =IFERROR(ACCRINT(COUPPCD(L5,J5,2,1),COUPNCD(L5,J5,2,0),L5,I5,O5,2,1),"") -> 3054075 | T5: =IFERROR(Q5+R5,Q5) -> 115694075 | V5: Settled
B6: =B5+1 -> 5 | C6: Comercio/Coronation MB | D6: Stanbic | E6: GIF₦ | F6: Rasheed | G6: Buy | H6: FGN 2049 Bond | I6: 0.148 | J6: 54539 | K6: 44347 | L6: 44349 | M6: =YIELD(L6,J6,I6,N6,100,2,1) -> 0.13980035 | N6: 105.69 | O6: 500000000 | P6: =IFERROR((O6*N6/100)+ACCRINT(COUPPCD(L6,J6,2,1),COUPNCD(L6,J6,2,1),L6,I6,O6,2,1),O6*N6/100) -> 5.3593087e+08 | Q6: =O6*N6/100 -> 528450000 | R6: =IFERROR(ACCRINT(COUPPCD(L6,J6,2,1),COUPNCD(L6,J6,2,0),L6,I6,O6,2,1),"") -> 7480874.3 | T6: =IFERROR(Q6+R6,Q6) -> 5.3593087e+08 | V6: Settled
B7: =B6+1 -> 6 | C7: Parthian/Sterling Bank | D7: Stanbic | E7: GIF₦ | F7: Rasheed | G7: Buy | H7: FGN 2035 Bond | I7: 0.125 | J7: 49395 | K7: 44348 | L7: =K7+2 -> 44350 | M7: =IFERROR(YIELD(L7,J7,I7,N7,100,2,1),"") -> 0.13819595 | N7: 91.91 | O7: 100000000 | P7: =IFERROR((O7*N7/100)+ACCRINT(COUPPCD(L7,J7,2,1),COUPNCD(L7,J7,2,1),L7,I7,O7,2,1),O7*N7/100) -> 94219783 | Q7: =O7*N7/100 -> 91910000 | R7: =IFERROR(ACCRINT(COUPPCD(L7,J7,2,1),COUPNCD(L7,J7,2,0),L7,I7,O7,2,1),"") -> 2309782.6 | T7: =IFERROR(Q7+R7,Q7) -> 94219783 | V7: Settled
B8: =B7+1 -> 7 | C8: Parthian/Sterling Bank | D8: Stanbic | E8: GIF₦ | F8: Rasheed | G8: Buy | H8: FGN 2050 Bond | I8: 0.1298 | J8: 54874 | K8: 44348 | L8: 44350 | M8: =IFERROR(YIELD(L8,J8,I8,N8,100,2,1),"") -> 0.13919423 | N8: 93.34 | O8: 300000000 | P8: =IFERROR((O8*N8/100)+ACCRINT(COUPPCD(L8,J8,2,1),COUPNCD(L8,J8,2,1),L8,I8,O8,2,1),O8*N8/100) -> 2.8721543e+08 | Q8: =O8*N8/100 -> 280020000 | R8: =IFERROR(ACCRINT(COUPPCD(L8,J8,2,1),COUPNCD(L8,J8,2,0),L8,I8,O8,2,1),"") -> 7195434.8 | T8: =IFERROR(Q8+R8,Q8) -> 2.8721543e+08 | V8: Settled
B9: =B8+1 -> 8 | C9: Parthian/Sterling Bank | D9: Stanbic | E9: GIF₦ | F9: Rasheed | G9: Buy | H9: FGN 2050 Bond | I9: 0.1298 | J9: 54874 | K9: 44348 | L9: 44350 | M9: =IFERROR(YIELD(L9,J9,I9,N9,100,2,1),"") -> 0.13919423 | N9: 93.34 | O9: 200000000 | P9: =IFERROR((O9*N9/100)+ACCRINT(COUPPCD(L9,J9,2,1),COUPNCD(L9,J9,2,1),L9,I9,O9,2,1),O9*N9/100) -> 1.9147696e+08 | Q9: =O9*N9/100 -> 186680000 | R9: =IFERROR(ACCRINT(COUPPCD(L9,J9,2,1),COUPNCD(L9,J9,2,0),L9,I9,O9,2,1),"") -> 4796956.5 | T9: =IFERROR(Q9+R9,Q9) -> 1.9147696e+08 | V9: Settled
B10: =B9+1 -> 9 | C10: Comercio/Coronation MB | D10: Stanbic | E10: GIF₦ | F10: Rasheed | G10: Buy | H10: FGN 2049 Bond | I10: 0.148 | J10: 54539 | K10: 44344 | L10: 44351 | M10: =YIELD(L10,J10,I10,N10,100,2,1) -> 0.14030202 | N10: 105.32 | O10: 500000000 | P10: =IFERROR((O10*N10/100)+ACCRINT(COUPPCD(L10,J10,2,1),COUPNCD(L10,J10,2,1),L10,I10,O10,2,1),O10*N10/100) -> 5.3448525e+08 | Q10: =O10*N10/100 -> 526600000 | R10: =IFERROR(ACCRINT(COUPPCD(L10,J10,2,1),COUPNCD(L10,J10,2,0),L10,I10,O10,2,1),"") -> 7885245.9 | T10: =IFERROR(Q10+R10,Q10) -> 5.3448525e+08 | V10: Settled
B11: =B10+1 -> 10 | C11: Comercio/Coronation MB | D11: Stanbic | E11: GIF₦ | F11: Rasheed | G11: Buy | H11: FGN 2049 Bond | I11: 0.148 | J11: 54539 | K11: 44347 | L11: 44351 | M11: =YIELD(L11,J11,I11,N11,100,2,1) -> 0.13979804 | N11: 105.69 | O11: 300000000 | P11: =IFERROR((O11*N11/100)+ACCRINT(COUPPCD(L11,J11,2,1),COUPNCD(L11,J11,2,1),L11,I11,O11,2,1),O11*N11/100) -> 3.2180115e+08 | Q11: =O11*N11/100 -> 317070000 | R11: =IFERROR(ACCRINT(COUPPCD(L11,J11,2,1),COUPNCD(L11,J11,2,0),L11,I11,O11,2,1),"") -> 4731147.5 | T11: =IFERROR(Q11+R11,Q11) -> 3.2180115e+08 | V11: Settled
B12: =B11+1 -> 11 | C12: Comercio/Coronation MB | D12: Stanbic | E12: GIF₦ | F12: Rasheed | G12: Buy | H12: FGN 2050 Bond | I12: 0.1298 | J12: 54874 | K12: 44348 | L12: 44354 | M12: =IFERROR(YIELD(L12,J12,I12,N12,100,2,1),"") -> 0.13929889 | N12: 93.27 | O12: 300000000 | P12: =IFERROR((O12*N12/100)+ACCRINT(COUPPCD(L12,J12,2,1),COUPNCD(L12,J12,2,1),L12,I12,O12,2,1),O12*N12/100) -> 2.874287e+08 | Q12: =O12*N12/100 -> 279810000 | R12: =IFERROR(ACCRINT(COUPPCD(L12,J12,2,1),COUPNCD(L12,J12,2,0),L12,I12,O12,2,1),"") -> 7618695.7 | T12: =IFERROR(Q12+R12,Q12) -> 2.874287e+08 | V12: Settled
B13: =B12+1 -> 12 | C13: Comercio/Stanbic | D13: Stanbic | E13: GIF₦ | F13: Rasheed | G13: Buy | H13: FGN 2050 Bond | I13: 0.1298 | J13: 54874 | K13: 44371 | L13: 44372 | M13: =IFERROR(YIELD(L13,J13,I13,N13,100,2,1),"") -> 0.137 | N13: 94.807168 | O13: 1000000000 | P13: =IFERROR((O13*N13/100)+ACCRINT(COUPPCD(L13,J13,2,1),COUPNCD(L13,J13,2,1),L13,I13,O13,2,1),O13*N13/100) -> 9.7981625e+08 | Q13: =O13*N13/100 -> 9.4807168e+08 | R13: =IFERROR(ACCRINT(COUPPCD(L13,J13,2,1),COUPNCD(L13,J13,2,0),L13,I13,O13,2,1),"") -> 31744565 | T13: =IFERROR(Q13+R13,Q13) -> 9.7981625e+08 | V13: Settled
B14: =B13+1 -> 13 | C14: Stanbic IBTC | D14: Stanbic | E14: GIF₦ | F14: Rasheed | G14: Buy | H14: FGN 2050 Bond | I14: 0.1298 | J14: 54874 | K14: 44378 | L14: 44382 | M14: =IFERROR(YIELD(L14,J14,I14,N14,100,2,1),"") -> 0.13000005 | N14: 99.7995 | O14: 500000000 | P14: =IFERROR((O14*N14/100)+ACCRINT(COUPPCD(L14,J14,2,1),COUPNCD(L14,J14,2,1),L14,I14,O14,2,1),O14*N14/100) -> 5.1663337e+08 | Q14: =O14*N14/100 -> 498997500 | R14: =IFERROR(ACCRINT(COUPPCD(L14,J14,2,1),COUPNCD(L14,J14,2,0),L14,I14,O14,2,1),"") -> 17635870 | T14: =IFERROR(Q14+R14,Q14) -> 5.1663337e+08 | V14: Settled
B15: =B14+1 -> 14 | C15: Comercio/Coronation MB | D15: Stanbic | E15: GIF₦ | F15: Rasheed | G15: Buy | H15: FGN 2050 Bond | I15: 0.1298 | J15: 54874 | K15: 44379 | L15: 44383 | M15: =IFERROR(YIELD(L15,J15,I15,N15,100,2,1),"") -> 0.12999951 | N15: 99.8 | O15: 1500000000 | P15: =IFERROR((O15*N15/100)+ACCRINT(COUPPCD(L15,J15,2,1),COUPNCD(L15,J15,2,1),L15,I15,O15,2,1),O15*N15/100) -> 1550436685 | Q15: =O15*N15/100 -> 1497000000 | R15: =IFERROR(ACCRINT(COUPPCD(L15,J15,2,1),COUPNCD(L15,J15,2,0),L15,I15,O15,2,1),"") -> 53436685 | T15: =IFERROR(Q15+R15,Q15) -> 1550436685 | V15: Settled
B16: =B15+1 -> 15 | C16: Comercio/Coronation MB | D16: Stanbic | E16: GIF₦ | F16: Rasheed | G16: Sell | H16: FGN 2049 Bond | I16: 0.148 | J16: 54539 | K16: 44382 | L16: 44383 | M16: =IFERROR(YIELD(L16,J16,I16,N16,100,2,1),"") -> 0.13000446 | N16: 113.37 | O16: 700000000 | P16: =IFERROR((O16*N16/100)+ACCRINT(COUPPCD(L16,J16,2,1),COUPNCD(L16,J16,2,1),L16,I16,O16,2,1),O16*N16/100) -> 8.1368727e+08 | Q16: =O16*N16/100 -> 793590000 | R16: =IFERROR(ACCRINT(COUPPCD(L16,J16,2,1),COUPNCD(L16,J16,2,0),L16,I16,O16,2,1),"") -> 20097268 | T16: =IFERROR(Q16+R16,Q16) -> 8.1368727e+08 | V16: Settled
B17: =B16+1 -> 16 | C17: Comercio/Coronation MB | D17: Stanbic | E17: GIF₦ | F17: Rasheed | G17: Sell | H17: FGN 2035 Bond | I17: 0.125 | J17: 49395 | K17: 44382 | L17: 44383 | M17: =IFERROR(YIELD(L17,J17,I17,N17,100,2,1),"") -> 0.12949569 | N17: 97.1 | O17: 100000000 | P17: =IFERROR((O17*N17/100)+ACCRINT(COUPPCD(L17,J17,2,1),COUPNCD(L17,J17,2,1),L17,I17,O17,2,1),O17*N17/100) -> 1.0053071e+08 | Q17: =O17*N17/100 -> 97100000 | R17: =IFERROR(ACCRINT(COUPPCD(L17,J17,2,1),COUPNCD(L17,J17,2,0),L17,I17,O17,2,1),"") -> 3430706.5 | T17: =IFERROR(Q17+R17,Q17) -> 1.0053071e+08 | V17: Settled
B18: =B17+1 -> 17 | C18: Comercio/Coronation MB | D18: Stanbic | E18: GIF₦ | F18: Rasheed | G18: Sell | H18: FGN 2035 Bond | I18: 0.125 | J18: 49395 | K18: 44382 | L18: 44383 | M18: =IFERROR(YIELD(L18,J18,I18,N18,100,2,1),"") -> 0.12949569 | N18: 97.1 | O18: 200000000 | P18: =IFERROR((O18*N18/100)+ACCRINT(COUPPCD(L18,J18,2,1),COUPNCD(L18,J18,2,1),L18,I18,O18,2,1),O18*N18/100) -> 201061413 | Q18: =O18*N18/100 -> 194200000 | R18: =IFERROR(ACCRINT(COUPPCD(L18,J18,2,1),COUPNCD(L18,J18,2,0),L18,I18,O18,2,1),"") -> 6861413 | T18: =IFERROR(Q18+R18,Q18) -> 201061413 | V18: Settled
B19: =B18+1 -> 18 | C19: Stanbic IBTC | D19: Stanbic | E19: GIF₦ | F19: Rasheed | G19: Buy | H19: FGN 2050 Bond | I19: 0.1298 | J19: 54874 | K19: 44378 | L19: 44383 | M19: =IFERROR(YIELD(L19,J19,I19,N19,100,2,1),"") -> 0.13000005 | N19: 99.7996 | O19: 1200000000 | P19: =IFERROR((O19*N19/100)+ACCRINT(COUPPCD(L19,J19,2,1),COUPNCD(L19,J19,2,1),L19,I19,O19,2,1),O19*N19/100) -> 1240344548 | Q19: =O19*N19/100 -> 1197595200 | R19: =IFERROR(ACCRINT(COUPPCD(L19,J19,2,1),COUPNCD(L19,J19,2,0),L19,I19,O19,2,1),"") -> 42749348 | T19: =IFERROR(Q19+R19,Q19) -> 1240344548 | V19: Settled
B20: =B19+1 -> 19 | C20: Stanbic Nominees | D20: Stanbic | E20: SADF$ | F20: Rasheed | G20: Buy | H20: FGN 2050 Bond | I20: 0.1298 | J20: 54874 | K20: 44426 | L20: =K20+2 -> 44428 | M20: =IFERROR(YIELD(L20,J20,I20,N20,100,2,1),"") -> 0.128 | N20: 101.33262 | O20: 900000000 | P20: =IFERROR((O20*N20/100)+ACCRINT(COUPPCD(L20,J20,2,1),COUPNCD(L20,J20,2,1),L20,I20,O20,2,1),O20*N20/100) -> 9.5834067e+08 | Q20: =O20*N20/100 -> 9.119936e+08 | R20: =IFERROR(ACCRINT(COUPPCD(L20,J20,2,1),COUPNCD(L20,J20,2,0),L20,I20,O20,2,1),"") -> 46347065 | T20: =IFERROR(Q20+R20,Q20) -> 9.5834067e+08 | V20: Settled
B21: =B20+1 -> 20 | C21: Comercio/Coronation MB | D21: Stanbic | E21: SADF$ | F21: Rasheed | G21: Buy | H21: FGN 2050 Bond | I21: 0.1298 | J21: 54874 | K21: 44427 | L21: 44431 | M21: =IFERROR(YIELD(L21,J21,I21,N21,100,2,1),"") -> 0.12750026 | N21: 101.72 | O21: 1000000000 | P21: =IFERROR((O21*N21/100)+ACCRINT(COUPPCD(L21,J21,2,1),COUPNCD(L21,J21,2,1),L21,I21,O21,2,1),O21*N21/100) -> 1069754891 | Q21: =O21*N21/100 -> 1017200000 | R21: =IFERROR(ACCRINT(COUPPCD(L21,J21,2,1),COUPNCD(L21,J21,2,0),L21,I21,O21,2,1),"") -> 52554891 | T21: =IFERROR(Q21+R21,Q21) -> 1069754891 | V21: Settled
B22: =B21+1 -> 21 | C22: Comercio/Access | D22: Stanbic | E22: SADF$ | F22: Rasheed | G22: Buy | H22: FGN 2050 Bond | I22: 0.1298 | J22: 54874 | K22: 44427 | L22: 44428 | M22: =IFERROR(YIELD(L22,J22,I22,N22,100,2,1),"") -> 0.12749778 | N22: 101.72 | O22: 500000000 | P22: =IFERROR((O22*N22/100)+ACCRINT(COUPPCD(L22,J22,2,1),COUPNCD(L22,J22,2,1),L22,I22,O22,2,1),O22*N22/100) -> 5.3434837e+08 | Q22: =O22*N22/100 -> 508600000 | R22: =IFERROR(ACCRINT(COUPPCD(L22,J22,2,1),COUPNCD(L22,J22,2,0),L22,I22,O22,2,1),"") -> 25748370 | T22: =IFERROR(Q22+R22,Q22) -> 5.3434837e+08 | V22: Settled
B23: =B22+1 -> 22 | C23: Comercio/Access | D23: Stanbic | E23: SADF$ | F23: Rasheed | G23: Buy | H23: FGN 2050 Bond | I23: 0.1298 | J23: 54874 | K23: 44427 | L23: 44428 | M23: =IFERROR(YIELD(L23,J23,I23,N23,100,2,1),"") -> 0.12749778 | N23: 101.72 | O23: 21106150 | P23: =IFERROR((O23*N23/100)+ACCRINT(COUPPCD(L23,J23,2,1),COUPNCD(L23,J23,2,1),L23,I23,O23,2,1),O23*N23/100) -> 22556074 | Q23: =O23*N23/100 -> 21469176 | R23: =IFERROR(ACCRINT(COUPPCD(L23,J23,2,1),COUPNCD(L23,J23,2,0),L23,I23,O23,2,1),"") -> 1086897.9 | T23: =IFERROR(Q23+R23,Q23) -> 22556074 | V23: Settled
B24: =B23+1 -> 23 | C24: Comercio/Access | D24: Stanbic | E24: GIF₦ | F24: Rasheed | G24: Buy | H24: FGN 2050 Bond | I24: 0.1298 | J24: 54874 | K24: 44427 | L24: 44428 | M24: =IFERROR(YIELD(L24,J24,I24,N24,100,2,1),"") -> 0.12749778 | N24: 101.72 | O24: 278893850 | P24: =IFERROR((O24*N24/100)+ACCRINT(COUPPCD(L24,J24,2,1),COUPNCD(L24,J24,2,1),L24,I24,O24,2,1),O24*N24/100) -> 2.9805295e+08 | Q24: =O24*N24/100 -> 2.8369082e+08 | R24: =IFERROR(ACCRINT(COUPPCD(L24,J24,2,1),COUPNCD(L24,J24,2,0),L24,I24,O24,2,1),"") -> 14362124 | T24: =IFERROR(Q24+R24,Q24) -> 2.9805295e+08 | V24: Settled
B25: =B24+1 -> 24 | C25: Parthian | D25: Stanbic | E25: GIF₦ | F25: Rasheed | G25: Sell | H25: FGN 2050 Bond | I25: 0.1298 | J25: 54874 | K25: 44448 | L25: 44452 | M25: =IFERROR(YIELD(L25,J25,I25,N25,100,2,1),"") -> 0.13119551 | N25: 98.95 | O25: 1000000000 | P25: =IFERROR((O25*N25/100)+ACCRINT(COUPPCD(L25,J25,2,1),COUPNCD(L25,J25,2,1),L25,I25,O25,2,1),O25*N25/100) -> 1049461957 | Q25: =O25*N25/100 -> 989500000 | R25: =IFERROR(ACCRINT(COUPPCD(L25,J25,2,1),COUPNCD(L25,J25,2,0),L25,I25,O25,2,1),"") -> 59961957 | T25: =IFERROR(Q25+R25,Q25) -> 1049461957 | V25: Settled
B26: =B25+1 -> 25 | C26: Parthian | D26: Stanbic | E26: GIF₦ | F26: Rasheed | G26: Sell | H26: FGN 2050 Bond | I26: 0.1298 | J26: 54874 | K26: 44448 | L26: 44452 | M26: =IFERROR(YIELD(L26,J26,I26,N26,100,2,1),"") -> 0.13119551 | N26: 98.95 | O26: 500000000 | P26: =IFERROR((O26*N26/100)+ACCRINT(COUPPCD(L26,J26,2,1),COUPNCD(L26,J26,2,1),L26,I26,O26,2,1),O26*N26/100) -> 5.2473098e+08 | Q26: =O26*N26/100 -> 494750000 | R26: =IFERROR(ACCRINT(COUPPCD(L26,J26,2,1),COUPNCD(L26,J26,2,0),L26,I26,O26,2,1),"") -> 29980978 | T26: =IFERROR(Q26+R26,Q26) -> 5.2473098e+08 | V26: Settled
B27: =B26+1 -> 26 | C27: Parthian | D27: Stanbic | E27: GIF₦ | F27: Rasheed | G27: Sell | H27: FGN 2050 Bond | I27: 0.1298 | J27: 54874 | K27: 44448 | L27: 44452 | M27: =IFERROR(YIELD(L27,J27,I27,N27,100,2,1),"") -> 0.13119551 | N27: 98.95 | O27: 200000000 | P27: =IFERROR((O27*N27/100)+ACCRINT(COUPPCD(L27,J27,2,1),COUPNCD(L27,J27,2,1),L27,I27,O27,2,1),O27*N27/100) -> 2.0989239e+08 | Q27: =O27*N27/100 -> 197900000 | R27: =IFERROR(ACCRINT(COUPPCD(L27,J27,2,1),COUPNCD(L27,J27,2,0),L27,I27,O27,2,1),"") -> 11992391 | T27: =IFERROR(Q27+R27,Q27) -> 2.0989239e+08 | V27: Settled
B28: =B27+1 -> 27 | C28: Parthian | D28: Stanbic | E28: GIF₦ | F28: Rasheed | G28: Sell | H28: FGN 2050 Bond | I28: 0.1298 | J28: 54874 | K28: 44448 | L28: 44453 | M28: =IFERROR(YIELD(L28,J28,I28,N28,100,2,1),"") -> 0.13119683 | N28: 98.95 | O28: 500000000 | P28: =IFERROR((O28*N28/100)+ACCRINT(COUPPCD(L28,J28,2,1),COUPNCD(L28,J28,2,1),L28,I28,O28,2,1),O28*N28/100) -> 524907337 | Q28: =O28*N28/100 -> 494750000 | R28: =IFERROR(ACCRINT(COUPPCD(L28,J28,2,1),COUPNCD(L28,J28,2,0),L28,I28,O28,2,1),"") -> 30157337 | T28: =IFERROR(Q28+R28,Q28) -> 524907337 | V28: Settled
B29: =B28+1 -> 28 | C29: Parthian | D29: Stanbic | E29: GIF₦ | F29: Rasheed | G29: Sell | H29: FGN 2050 Bond | I29: 0.1298 | J29: 54874 | K29: 44448 | L29: 44452 | M29: =IFERROR(YIELD(L29,J29,I29,N29,100,2,1),"") -> 0.13119551 | N29: 98.95 | O29: 300000000 | P29: =IFERROR((O29*N29/100)+ACCRINT(COUPPCD(L29,J29,2,1),COUPNCD(L29,J29,2,1),L29,I29,O29,2,1),O29*N29/100) -> 314838587 | Q29: =O29*N29/100 -> 296850000 | R29: =IFERROR(ACCRINT(COUPPCD(L29,J29,2,1),COUPNCD(L29,J29,2,0),L29,I29,O29,2,1),"") -> 17988587 | T29: =IFERROR(Q29+R29,Q29) -> 314838587 | V29: Settled
B30: =B29+1 -> 29 | C30: Parthian | D30: Stanbic | E30: GIF₦ | F30: Rasheed | G30: Sell | H30: FGN 2049 Bond | I30: 0.148 | J30: 54539 | K30: 44453 | L30: 44455 | M30: =IFERROR(YIELD(L30,J30,I30,N30,100,2,1),"") -> 0.12999814 | N30: 113.38 | O30: 500000000 | P30: =IFERROR((O30*N30/100)+ACCRINT(COUPPCD(L30,J30,2,1),COUPNCD(L30,J30,2,1),L30,I30,O30,2,1),O30*N30/100) -> 5.9581257e+08 | Q30: =O30*N30/100 -> 566900000 | R30: =IFERROR(ACCRINT(COUPPCD(L30,J30,2,1),COUPNCD(L30,J30,2,0),L30,I30,O30,2,1),"") -> 28912568 | T30: =IFERROR(Q30+R30,Q30) -> 5.9581257e+08 | V30: Settled
B31: =B30+1 -> 30 | C31: Parthian | D31: Stanbic | E31: GIF₦ | F31: Rasheed | G31: Sell | H31: FGN 2049 Bond | I31: 0.148 | J31: 54539 | K31: 44453 | L31: 44455 | M31: =IFERROR(YIELD(L31,J31,I31,N31,100,2,1),"") -> 0.12999814 | N31: 113.38 | O31: 100000000 | P31: =IFERROR((O31*N31/100)+ACCRINT(COUPPCD(L31,J31,2,1),COUPNCD(L31,J31,2,1),L31,I31,O31,2,1),O31*N31/100) -> 1.1916251e+08 | Q31: =O31*N31/100 -> 113380000 | R31: =IFERROR(ACCRINT(COUPPCD(L31,J31,2,1),COUPNCD(L31,J31,2,0),L31,I31,O31,2,1),"") -> 5782513.7 | T31: =IFERROR(Q31+R31,Q31) -> 1.1916251e+08 | V31: Settled
B32: =B31+1 -> 31 | C32: Parthian | D32: Stanbic | E32: GIF₦ | F32: Rasheed | G32: Buy | H32: FGN 2028 Bond | I32: 0.1398 | J32: 46806 | K32: 44455 | L32: 44459 | M32: =IFERROR(YIELD(L32,J32,I32,N32,100,2,1),"") -> 0.11519949 | N32: 110.93 | O32: 500000000 | P32: =IFERROR((O32*N32/100)+ACCRINT(COUPPCD(L32,J32,2,1),COUPNCD(L32,J32,2,1),L32,I32,O32,2,1),O32*N32/100) -> 5.5996848e+08 | Q32: =O32*N32/100 -> 554650000 | R32: =IFERROR(ACCRINT(COUPPCD(L32,J32,2,1),COUPNCD(L32,J32,2,0),L32,I32,O32,2,1),"") -> 5318478.3 | T32: =IFERROR(Q32+R32,Q32) -> 5.5996848e+08 | V32: Settled
... B60: =B59+1 -> 59 | C60: Union Bank | D60: Stanbic | E60: GIF₦ | F60: Rasheed | G60: Sell | H60: FGN 2028 Bond | I60: 0.1398 | J60: 46806 | K60: 44498 | L60: 44502 | M60: =IFERROR(YIELD(L60,J60,I60,N60,100,2,1),"") -> 0.123 | N60: 107.17574 | O60: 879000000 | P60: =IFERROR((O60*N60/100)+ACCRINT(COUPPCD(L60,J60,2,1),COUPNCD(L60,J60,2,1),L60,I60,O60,2,1),O60*N60/100) -> 9.6578341e+08 | Q60: =O60*N60/100 -> 9.4207477e+08 | R60: =IFERROR(ACCRINT(COUPPCD(L60,J60,2,1),COUPNCD(L60,J60,2,0),L60,I60,O60,2,1),"") -> 23708636 | T60: =IFERROR(Q60+R60,Q60) -> 9.6578341e+08 | V60: Settled
B61: =B60+1 -> 60 | C61: Parthian/Sterling Bank | D61: Stanbic | E61: GIF₦ | F61: Rasheed | G61: Sell | H61: FGN 2026 Bond | I61: 0.125 | J61: 46044 | K61: 44579 | L61: 44581 | M61: =IFERROR(YIELD(L61,J61,I61,N61,100,2,1),"") -> 0.11564837 | N61: 102.93 | O61: 194000000 | P61: =IFERROR((O61*N61/100)+ACCRINT(COUPPCD(L61,J61,2,1),COUPNCD(L61,J61,2,1),L61,I61,O61,2,1),O61*N61/100) -> 2.1167741e+08 | Q61: =O61*N61/100 -> 199684200 | R61: =IFERROR(ACCRINT(COUPPCD(L61,J61,2,1),COUPNCD(L61,J61,2,0),L61,I61,O61,2,1),"") -> 11993207 | T61: =IFERROR(Q61+R61,Q61) -> 2.1167741e+08
B62: =B61+1 -> 61 | C62: Parthian/Sterling Bank | D62: Stanbic | E62: GIF₦ | F62: Rasheed | G62: Sell | H62: FGN 2027 Bond | I62: 0.162884 | J62: 46463 | K62: 44579 | L62: 44581 | M62: =IFERROR(YIELD(L62,J62,I62,N62,100,2,1),"") -> 0.12263022 | N62: 115 | O62: 100000000 | P62: =IFERROR((O62*N62/100)+ACCRINT(COUPPCD(L62,J62,2,1),COUPNCD(L62,J62,2,1),L62,I62,O62,2,1),O62*N62/100) -> 1.2062445e+08 | Q62: =O62*N62/100 -> 115000000 | R62: =IFERROR(ACCRINT(COUPPCD(L62,J62,2,1),COUPNCD(L62,J62,2,0),L62,I62,O62,2,1),"") -> 5624447.5 | T62: =IFERROR(Q62+R62,Q62) -> 1.2062445e+08
B63: =B62+1 -> 62 | C63: Access bank | D63: Stanbic | E63: GIF₦ | F63: Victor | G63: Buy | H63: FGN 2037 bond | I63: 0.162499 | J63: 50148 | K63: 44915 | L63: 44917 | M63: =IFERROR(YIELD(L63,J63,I63,N63,100,2,1),"") -> 0.14199738 | N63: 112.35 | O63: 2000000000 | P63: =IFERROR((O63*N63/100)+ACCRINT(COUPPCD(L63,J63,2,1),COUPNCD(L63,J63,2,1),L63,I63,O63,2,1),O63*N63/100) -> 2305035357 | Q63: =O63*N63/100 -> 2247000000 | R63: =IFERROR(ACCRINT(COUPPCD(L63,J63,2,1),COUPNCD(L63,J63,2,0),L63,I63,O63,2,1),"") -> 58035357 | T63: =IFERROR(Q63+R63,Q63) -> 2305035357
B64: =B63+1 -> 63 | C64: Access bank | D64: Stanbic | E64: GIF₦ | F64: Victor | G64: Buy | H64: FGN 2037 bond | I64: 0.162499 | J64: 50148 | K64: 44944 | L64: 44946 | M64: =IFERROR(YIELD(L64,J64,I64,N64,100,2,1),"") -> 0.14550183 | N64: 110.03 | O64: 2000000000 | P64: =IFERROR((O64*N64/100)+ACCRINT(COUPPCD(L64,J64,2,1),COUPNCD(L64,J64,2,1),L64,I64,O64,2,1),O64*N64/100) -> 2284528055 | Q64: =O64*N64/100 -> 2200600000 | R64: =IFERROR(ACCRINT(COUPPCD(L64,J64,2,1),COUPNCD(L64,J64,2,0),L64,I64,O64,2,1),"") -> 83928055 | T64: =IFERROR(Q64+R64,Q64) -> 2284528055
B65: =B64+1 -> 64 | C65: Access bank | D65: Stanbic | E65: GIF₦ | F65: Victor | G65: Buy | H65: FGN 2049 bond | I65: 0.148 | J65: 54539 | K65: 44965 | L65: 44967 | M65: =IFERROR(YIELD(L65,J65,I65,N65,100,2,1),"") -> 0.15649283 | N65: 94.61 | O65: 5000000000 | P65: =IFERROR((O65*N65/100)+ACCRINT(COUPPCD(L65,J65,2,1),COUPNCD(L65,J65,2,1),L65,I65,O65,2,1),O65*N65/100) -> 4948027473 | Q65: =O65*N65/100 -> 4730500000 | R65: =IFERROR(ACCRINT(COUPPCD(L65,J65,2,1),COUPNCD(L65,J65,2,0),L65,I65,O65,2,1),"") -> 2.1752747e+08 | T65: =IFERROR(Q65+R65,Q65) -> 4948027473
B66: =B65+1 -> 65 | C66: Access bank | D66: Stanbic | E66: GIF₦ | F66: Victor | G66: Buy | H66: FGN 2049 bond | I66: 0.148 | J66: 54539 | K66: 44973 | L66: 44977 | M66: =IFERROR(YIELD(L66,J66,I66,N66,100,2,1),"") -> 0.15749594 | N66: 94.02 | O66: 1000000000 | P66: =IFERROR((O66*N66/100)+ACCRINT(COUPPCD(L66,J66,2,1),COUPNCD(L66,J66,2,1),L66,I66,O66,2,1),O66*N66/100) -> 9.8777143e+08 | Q66: =O66*N66/100 -> 940200000 | R66: =IFERROR(ACCRINT(COUPPCD(L66,J66,2,1),COUPNCD(L66,J66,2,0),L66,I66,O66,2,1),"") -> 47571429 | S66: =#REF!*O66 -> #REF! | T66: =IFERROR(Q66+R66+S66,Q66) -> 940200000
B67: =B66+1 -> 66 | C67: Keystone bank | D67: Stanbic | E67: GIF₦ | F67: William | G67: Buy | H67: FGN 2037 bond | I67: 0.1625 | J67: 50148 | K67: 44993 | L67: 44998 | M67: =IFERROR(YIELD(L67,J67,I67,N67,100,2,1),"") -> 0.15149494 | N67: 106.29 | O67: 800000000 | P67: =IFERROR((O67*N67/100)+ACCRINT(COUPPCD(L67,J67,2,1),COUPNCD(L67,J67,2,1),L67,I67,O67,2,1),O67*N67/100) -> 9.0246286e+08 | Q67: =O67*N67/100 -> 850320000 | R67: =IFERROR(ACCRINT(COUPPCD(L67,J67,2,1),COUPNCD(L67,J67,2,0),L67,I67,O67,2,1),"") -> 52142857 | S67: =#REF!*O67 -> #REF! | T67: =IFERROR(Q67+R67+S67,Q67) -> 850320000
B68: =B67+1 -> 67 | C68: Keystone bank | D68: Stanbic | E68: GIF₦ | F68: William | G68: Sell | H68: FGN 2049 bond | I68: 0.148 | J68: 54539 | K68: 45100 | L68: 45104 | M68: =IFERROR(YIELD(L68,J68,I68,N68,100,2,1),"") -> 0.15599279 | N68: 94.92 | O68: 6000000000 | P68: =IFERROR((O68*N68/100)+ACCRINT(COUPPCD(L68,J68,2,1),COUPNCD(L68,J68,2,1),L68,I68,O68,2,1),O68*N68/100) -> 5845626230 | Q68: =O68*N68/100 -> 5695200000 | R68: =IFERROR(ACCRINT(COUPPCD(L68,J68,2,1),COUPNCD(L68,J68,2,0),L68,I68,O68,2,1),"") -> 1.5042623e+08 | T68: =IFERROR(Q68+R68,Q68) -> 5845626230
B69: =B68+1 -> 68 | C69: Keystone bank | D69: Stanbic | E69: GIF₦ | F69: William | G69: Buy | H69: FGN 2050 Bond | I69: 0.1298 | J69: 54874 | K69: 45120 | L69: 45124 | M69: =IFERROR(YIELD(L69,J69,I69,N69,100,2,1),"") -> 0.13999768 | N69: 92.86 | O69: 5300000000 | P69: =IFERROR((O69*N69/100)+ACCRINT(COUPPCD(L69,J69,2,1),COUPNCD(L69,J69,2,1),L69,I69,O69,2,1),O69*N69/100) -> 5130953043 | Q69: =O69*N69/100 -> 4921580000 | R69: =IFERROR(ACCRINT(COUPPCD(L69,J69,2,1),COUPNCD(L69,J69,2,0),L69,I69,O69,2,1),"") -> 2.0937304e+08 | T69: =IFERROR(Q69+R69,Q69) -> 5130953043
B70: =B69+1 -> 69 | C70: Keystone bank | D70: Stanbic | E70: GIF₦ | F70: Victor | G70: Sell | H70: FGN 2037 bond | I70: 0.1625 | J70: 50148 | K70: 45230 | L70: 45231 | M70: =IFERROR(YIELD(L70,J70,I70,N70,100,2,1),"") -> 0.16500309 | N70: 98.64 | O70: 800000000 | P70: =IFERROR((O70*N70/100)+ACCRINT(COUPPCD(L70,J70,2,1),COUPNCD(L70,J70,2,1),L70,I70,O70,2,1),O70*N70/100) -> 7.9409268e+08 | Q70: =O70*N70/100 -> 789120000 | R70: =IFERROR(ACCRINT(COUPPCD(L70,J70,2,1),COUPNCD(L70,J70,2,0),L70,I70,O70,2,1),"") -> 4972677.6 | T70: =IFERROR(Q70+R70,Q70) -> 7.9409268e+08
B71: =B70+1 -> 70 | C71: Keystone bank | D71: Stanbic | E71: GIF₦ | F71: Victor | G71: Sell | H71: FGN 2037 bond | I71: 0.1625 | J71: 50148 | K71: 45230 | L71: 45232 | M71: =IFERROR(YIELD(L71,J71,I71,N71,100,2,1),"") -> 0.16500046 | N71: 98.64 | O71: 1000000000 | P71: =IFERROR((O71*N71/100)+ACCRINT(COUPPCD(L71,J71,2,1),COUPNCD(L71,J71,2,1),L71,I71,O71,2,1),O71*N71/100) -> 9.9305984e+08 | Q71: =O71*N71/100 -> 986400000 | R71: =IFERROR(ACCRINT(COUPPCD(L71,J71,2,1),COUPNCD(L71,J71,2,0),L71,I71,O71,2,1),"") -> 6659836.1 | T71: =IFERROR(Q71+R71,Q71) -> 9.9305984e+08
B72: =B71+1 -> 71 | C72: Keystone bank | D72: Stanbic | E72: GIF₦ | F72: Victor | G72: Sell | H72: FGN 2037 bond | I72: 0.1625 | J72: 50148 | K72: 45232 | L72: 45233 | M72: =IFERROR(YIELD(L72,J72,I72,N72,100,2,1),"") -> 0.16501679 | N72: 98.63 | O72: 500000000 | P72: =IFERROR((O72*N72/100)+ACCRINT(COUPPCD(L72,J72,2,1),COUPNCD(L72,J72,2,1),L72,I72,O72,2,1),O72*N72/100) -> 4.9670191e+08 | Q72: =O72*N72/100 -> 493150000 | R72: =IFERROR(ACCRINT(COUPPCD(L72,J72,2,1),COUPNCD(L72,J72,2,0),L72,I72,O72,2,1),"") -> 3551912.6 | T72: =IFERROR(Q72+R72,Q72) -> 4.9670191e+08
B73: =B72+1 -> 72 | C73: Keystone bank | D73: Stanbic | E73: GIF₦ | F73: Victor | G73: Sell | H73: FGN 2037 bond | I73: 0.1625 | J73: 50148 | K73: 45233 | L73: 45237 | M73: =IFERROR(YIELD(L73,J73,I73,N73,100,2,1),"") -> 0.16647326 | N73: 97.86 | O73: 300000000 | P73: =IFERROR((O73*N73/100)+ACCRINT(COUPPCD(L73,J73,2,1),COUPNCD(L73,J73,2,1),L73,I73,O73,2,1),O73*N73/100) -> 2.9624393e+08 | Q73: =O73*N73/100 -> 293580000 | R73: =IFERROR(ACCRINT(COUPPCD(L73,J73,2,1),COUPNCD(L73,J73,2,0),L73,I73,O73,2,1),"") -> 2663934.4 | T73: =IFERROR(Q73+R73,Q73) -> 2.9624393e+08
B74: =B73+1 -> 73 | C74: Keystone bank | D74: Stanbic | E74: GIF₦ | F74: Victor | G74: Sell | H74: FGN 2037 bond | I74: 0.1625 | J74: 50148 | K74: 45239 | L74: 45243 | M74: =IFERROR(YIELD(L74,J74,I74,N74,100,2,1),"") -> 0.16950961 | N74: 96.29 | O74: 2000000000 | P74: =IFERROR((O74*N74/100)+ACCRINT(COUPPCD(L74,J74,2,1),COUPNCD(L74,J74,2,1),L74,I74,O74,2,1),O74*N74/100) -> 1948887432 | Q74: =O74*N74/100 -> 1925800000 | R74: =IFERROR(ACCRINT(COUPPCD(L74,J74,2,1),COUPNCD(L74,J74,2,0),L74,I74,O74,2,1),"") -> 23087432 | T74: =IFERROR(Q74+R74,Q74) -> 1948887432
B75: =B74+1 -> 74 | C75: Parthian/Sterling Bank | D75: Stanbic | E75: GIF₦ | F75: Oise | G75: Buy | H75: NIGTB 7/Nov/2024 | I75: 0 | J75: 45603 | K75: 45243 | L75: 45610 | M75: =IFERROR(YIELD(L75,J75,I75,N75,100,2,1),"") | N75: 85.0852 | O75: 1000000000 | P75: =IFERROR((O75*N75/100)+ACCRINT(COUPPCD(L75,J75,2,1),COUPNCD(L75,J75,2,1),L75,I75,O75,2,1),O75*N75/100) -> 850852000 | Q75: =O75*N75/100 -> 850852000 | T75: =IFERROR(Q75+R75,Q75) -> 850852000
B76: =B75+1 -> 75 | C76: Comercio/Stanbic | D76: Stanbic | E76: GIF₦ | F76: Oise | G76: Buy | H76: NIGTB 7/Nov/2024 | I76: 0 | J76: 45603 | K76: 45243 | L76: 45610 | M76: =IFERROR(YIELD(L76,J76,I76,N76,100,2,1),"") | N76: 85.0852 | O76: 2000000000 | P76: =IFERROR((O76*N76/100)+ACCRINT(COUPPCD(L76,J76,2,1),COUPNCD(L76,J76,2,1),L76,I76,O76,2,1),O76*N76/100) -> 1701704000 | Q76: =O76*N76/100 -> 1701704000 | R76: =IFERROR(ACCRINT(COUPPCD(L76,J76,2,1),COUPNCD(L76,J76,2,0),L76,I76,O76,2,1),"") | T76: =IFERROR(Q76+R76,Q76) -> 1701704000
B77: =B76+1 -> 76 | C77: Keystone bank | D77: Stanbic | E77: GIF₦ | F77: Oise | G77: Sell | H77: FGN 2050 Bond | I77: 0.1298 | J77: 54874 | K77: 45250 | L77: 45252 | M77: =IFERROR(YIELD(L77,J77,I77,N77,100,2,1),"") -> 0.17898855 | N77: 72.76 | O77: 4800000000 | P77: =IFERROR((O77*N77/100)+ACCRINT(COUPPCD(L77,J77,2,1),COUPNCD(L77,J77,2,1),L77,I77,O77,2,1),O77*N77/100) -> 3588332308 | Q77: =O77*N77/100 -> 3492480000 | R77: =IFERROR(ACCRINT(COUPPCD(L77,J77,2,1),COUPNCD(L77,J77,2,0),L77,I77,O77,2,1),"") -> 95852308 | T77: =IFERROR(Q77+R77,Q77) -> 3588332308
B78: =B77+1 -> 77 | C78: Keystone bank | D78: Stanbic | E78: GIF₦ | F78: Oise | G78: Sell | H78: FGN 2050 Bond | I78: 0.1298 | J78: 54874 | K78: 45250 | L78: 45253 | M78: =IFERROR(YIELD(L78,J78,I78,N78,100,2,1),"") -> 0.17898746 | N78: 72.76 | O78: 500000000 | P78: =IFERROR((O78*N78/100)+ACCRINT(COUPPCD(L78,J78,2,1),COUPNCD(L78,J78,2,1),L78,I78,O78,2,1),O78*N78/100) -> 3.7396291e+08 | Q78: =O78*N78/100 -> 363800000 | R78: =IFERROR(ACCRINT(COUPPCD(L78,J78,2,1),COUPNCD(L78,J78,2,0),L78,I78,O78,2,1),"") -> 10162912 | T78: =IFERROR(Q78+R78,Q78) -> 3.7396291e+08
B79: =B78+1 -> 78 | C79: Keystone bank | D79: Stanbic | E79: GIF₦ | F79: Oise | G79: Sell | H79: FGN 2037 bond | I79: 0.162499 | J79: 50148 | K79: 45253 | L79: 45257 | M79: =IFERROR(YIELD(L79,J79,I79,N79,100,2,1),"") -> 0.16999576 | N79: 96.03 | O79: 200000000 | P79: =IFERROR((O79*N79/100)+ACCRINT(COUPPCD(L79,J79,2,1),COUPNCD(L79,J79,2,1),L79,I79,O79,2,1),O79*N79/100) -> 1.9561189e+08 | Q79: =O79*N79/100 -> 192060000 | R79: =IFERROR(ACCRINT(COUPPCD(L79,J79,2,1),COUPNCD(L79,J79,2,0),L79,I79,O79,2,1),"") -> 3551890.7 | T79: =IFERROR(Q79+R79,Q79) -> 1.9561189e+08
B80: =B79+1 -> 79 | C80: Stanbic Nominees | D80: Stanbic | E80: GIF₦ | F80: Oise | G80: Buy | H80: NIGTB 5/Dec/2024 | I80: 0 | J80: 45631 | K80: 45266 | L80: 45267 | M80: 0.155 | N80: 84.584699 | O80: 1000000000 | P80: =IFERROR((O80*N80/100)+ACCRINT(COUPPCD(L80,J80,2,1),COUPNCD(L80,J80,2,1),L80,I80,O80,2,1),O80*N80/100) -> 8.4584699e+08 | Q80: =O80*N80/100 -> 8.4584699e+08 | R80: =IFERROR(ACCRINT(COUPPCD(L80,J80,2,1),COUPNCD(L80,J80,2,0),L80,I80,O80,2,1),"") | T80: =IFERROR(Q80+R80,Q80) -> 8.4584699e+08
B81: =B80+1 -> 80 | C81: Keystone bank | D81: Stanbic | E81: GIF₦ | F81: Oise | G81: Buy | H81: FGN 2053 bond | I81: 0.157 | J81: 56056 | K81: 45274 | L81: 45275 | M81: =IFERROR(YIELD(L81,J81,I81,N81,100,2,1),"") -> 0.15949974 | N81: 98.44 | O81: 500000000 | P81: =IFERROR((O81*N81/100)+ACCRINT(COUPPCD(L81,J81,2,1),COUPNCD(L81,J81,2,1),L81,I81,O81,2,1),O81*N81/100) -> 5.3016311e+08 | Q81: =O81*N81/100 -> 492200000 | R81: =IFERROR(ACCRINT(COUPPCD(L81,J81,2,1),COUPNCD(L81,J81,2,0),L81,I81,O81,2,1),"") -> 37963115 | T81: =IFERROR(Q81+R81,Q81) -> 5.3016311e+08
B82: =B81+1 -> 81 | C82: Keystone bank | D82: Stanbic | E82: GIF₦ | F82: Oise | G82: Buy | H82: FGN 2053 bond | I82: 0.157 | J82: 56056 | K82: 45274 | L82: 45278 | M82: =IFERROR(YIELD(L82,J82,I82,N82,100,2,1),"") -> 0.15950755 | N82: 98.44 | O82: 4500000000 | P82: =IFERROR((O82*N82/100)+ACCRINT(COUPPCD(L82,J82,2,1),COUPNCD(L82,J82,2,1),L82,I82,O82,2,1),O82*N82/100) -> 4777259016 | Q82: =O82*N82/100 -> 4429800000 | R82: =IFERROR(ACCRINT(COUPPCD(L82,J82,2,1),COUPNCD(L82,J82,2,0),L82,I82,O82,2,1),"") -> 3.4745902e+08 | T82: =IFERROR(Q82+R82,Q82) -> 4777259016
B83: =B82+1 -> 82 | C83: Stanbic Nominees | D83: Stanbic | E83: GIF₦ | F83: Oise | G83: Sell | H83: NIGTB 7/Nov/2024 | I83: 0 | J83: 45603 | K83: 45280 | L83: 45280 | M83: 0.11751196 | N83: =PRICEDISC(K83,J83,M83,100,1) -> 89.628353 | O83: 2000000000 | P83: =IFERROR((O83*N83/100)+ACCRINT(COUPPCD(L83,J83,2,1),COUPNCD(L83,J83,2,1),L83,I83,O83,2,1),O83*N83/100) -> 1792567069 | Q83: =O83*N83/100 -> 1792567069 | R83: =IFERROR(ACCRINT(COUPPCD(L83,J83,2,1),COUPNCD(L83,J83,2,0),L83,I83,O83,2,1),"") | T83: =IFERROR(Q83+R83,Q83) -> 1792567069
B84: =B83+1 -> 83 | C84: Keystone bank | D84: Stanbic | E84: GIF₦ | F84: Oise | G84: Buy | H84: FGN 2053 bond | I84: 0.157 | J84: 56056 | K84: 45280 | L84: 45282 | M84: =IFERROR(YIELD(L84,J84,I84,N84,100,2,1),"") -> 0.16150088 | N84: 97.24 | O84: 1700000000 | P84: =IFERROR((O84*N84/100)+ACCRINT(COUPPCD(L84,J84,2,1),COUPNCD(L84,J84,2,1),L84,I84,O84,2,1),O84*N84/100) -> 1653809235 | Q84: =O84*N84/100 -> 1653080000 | R84: =IFERROR(ACCRINT(COUPPCD(L84,J84,2,1),COUPNCD(L84,J84,2,0),L84,I84,O84,2,1),"") -> 729234.97 | T84: =IFERROR(Q84+R84,Q84) -> 1653809235
B85: =B84+1 -> 84 | C85: Comercio/Stanbic | D85: Stanbic | E85: GIF₦ | F85: Oise | G85: Sell | H85: NIGTB 7/Nov/2024 | I85: 0 | J85: 45603 | K85: 45282 | L85: 45282 | M85: 0.117 | N85: =PRICEDISC(L85,J85,M85,100,1) -> 89.737649 | O85: 1000000000 | P85: =IFERROR((O85*N85/100)+ACCRINT(COUPPCD(L85,J85,2,1),COUPNCD(L85,J85,2,1),L85,I85,O85,2,1),O85*N85/100) -> 8.9737649e+08 | Q85: =O85*N85/100 -> 8.9737649e+08 | R85: =IFERROR(ACCRINT(COUPPCD(L85,J85,2,1),COUPNCD(L85,J85,2,0),L85,I85,O85,2,1),"") | T85: =IFERROR(Q85+R85,Q85) -> 8.9737649e+08
B86: =B85+1 -> 85 | C86: Comercio/Stanbic | D86: Stanbic | E86: GIF₦ | F86: Oise | G86: Sell | H86: NIGTB 5/Dec/2024 | I86: 0 | J86: 45631 | K86: 45282 | L86: 45282 | M86: 0.117 | N86: =PRICEDISC(L86,J86,M86,100,1) -> 88.842567 | O86: 1000000000 | P86: =IFERROR((O86*N86/100)+ACCRINT(COUPPCD(L86,J86,2,1),COUPNCD(L86,J86,2,1),L86,I86,O86,2,1),O86*N86/100) -> 8.8842567e+08 | Q86: =O86*N86/100 -> 8.8842567e+08 | R86: =IFERROR(ACCRINT(COUPPCD(L86,J86,2,1),COUPNCD(L86,J86,2,0),L86,I86,O86,2,1),"") | T86: =IFERROR(Q86+R86,Q86) -> 8.8842567e+08
B87: =B86+1 -> 86 | C87: Keystone bank | D87: Stanbic | E87: GIF₦ | F87: Oise | G87: Buy | H87: FGN 2053 bond | I87: 0.157 | J87: 56056 | K87: 45282 | L87: 45287 | M87: =IFERROR(YIELD(L87,J87,I87,N87,100,2,1),"") -> 0.16200886 | N87: 96.93 | O87: 1600000000 | P87: =IFERROR((O87*N87/100)+ACCRINT(COUPPCD(L87,J87,2,1),COUPNCD(L87,J87,2,1),L87,I87,O87,2,1),O87*N87/100) -> 1554998033 | Q87: =O87*N87/100 -> 1550880000 | R87: =IFERROR(ACCRINT(COUPPCD(L87,J87,2,1),COUPNCD(L87,J87,2,0),L87,I87,O87,2,1),"") -> 4118032.8 | T87: =IFERROR(Q87+R87,Q87) -> 1554998033
B88: =B87+1 -> 87 | C88: Keystone bank | D88: Stanbic | E88: GIF₦ | F88: Oise | G88: Sell | H88: FGN 2053 bond | I88: 0.157 | J88: 56056 | K88: 45334 | L88: 45336 | M88: =IFERROR(YIELD(L88,J88,I88,N88,100,2,1),"") -> 0.1789988 | N88: 87.72 | O88: 800000000 | P88: =IFERROR((O88*N88/100)+ACCRINT(COUPPCD(L88,J88,2,1),COUPNCD(L88,J88,2,1),L88,I88,O88,2,1),O88*N88/100) -> 7.2063432e+08 | Q88: =O88*N88/100 -> 701760000 | R88: =IFERROR(ACCRINT(COUPPCD(L88,J88,2,1),COUPNCD(L88,J88,2,0),L88,I88,O88,2,1),"") -> 18874317 | T88: =IFERROR(Q88+R88,Q88) -> 7.2063432e+08
B89: =B88+1 -> 88 | C89: Keystone bank | D89: Stanbic | E89: GIF₦ | F89: Oise | G89: Sell | H89: FGN 2053 bond | I89: 0.157 | J89: 56056 | K89: 45334 | L89: 45337 | M89: =IFERROR(YIELD(L89,J89,I89,N89,100,2,1),"") -> 0.18300665 | N89: 85.8 | O89: 1800000000 | P89: =IFERROR((O89*N89/100)+ACCRINT(COUPPCD(L89,J89,2,1),COUPNCD(L89,J89,2,1),L89,I89,O89,2,1),O89*N89/100) -> 1587639344 | Q89: =O89*N89/100 -> 1544400000 | R89: =IFERROR(ACCRINT(COUPPCD(L89,J89,2,1),COUPNCD(L89,J89,2,0),L89,I89,O89,2,1),"") -> 43239344 | T89: =IFERROR(Q89+R89,Q89) -> 1587639344
B90: =B89+1 -> 89 | C90: Keystone bank | D90: Stanbic | E90: GIF₦ | F90: Oise | G90: Sell | H90: FGN 2053 bond | I90: 0.157 | J90: 56056 | K90: 45334 | L90: 45338 | M90: =IFERROR(YIELD(L90,J90,I90,N90,100,2,1),"") -> 0.18300518 | N90: 85.8 | O90: 1000000000 | P90: =IFERROR((O90*N90/100)+ACCRINT(COUPPCD(L90,J90,2,1),COUPNCD(L90,J90,2,1),L90,I90,O90,2,1),O90*N90/100) -> 8.8245082e+08 | Q90: =O90*N90/100 -> 858000000 | R90: =IFERROR(ACCRINT(COUPPCD(L90,J90,2,1),COUPNCD(L90,J90,2,0),L90,I90,O90,2,1),"") -> 24450820 | T90: =IFERROR(Q90+R90,Q90) -> 8.8245082e+08
B91: =B90+1 -> 90 | C91: Keystone bank | D91: Stanbic | E91: GIF₦ | F91: Oise | G91: Sell | H91: FGN 2053 bond | I91: 0.157 | J91: 56056 | K91: 45334 | L91: 45341 | M91: =IFERROR(YIELD(L91,J91,I91,N91,100,2,1),"") -> 0.18300105 | N91: 85.8 | O91: 250000000 | P91: =IFERROR((O91*N91/100)+ACCRINT(COUPPCD(L91,J91,2,1),COUPNCD(L91,J91,2,1),L91,I91,O91,2,1),O91*N91/100) -> 2.2093443e+08 | Q91: =O91*N91/100 -> 214500000 | R91: =IFERROR(ACCRINT(COUPPCD(L91,J91,2,1),COUPNCD(L91,J91,2,0),L91,I91,O91,2,1),"") -> 6434426.2 | T91: =IFERROR(Q91+R91,Q91) -> 2.2093443e+08
B92: =B91+1 -> 91 | C92: Keystone bank | D92: Stanbic | E92: GIF₦ | F92: Oise | G92: Sell | H92: FGN 2053 bond | I92: 0.157 | J92: 56056 | K92: 45334 | L92: 45341 | M92: =IFERROR(YIELD(L92,J92,I92,N92,100,2,1),"") -> 0.18300105 | N92: 85.8 | O92: 300000000 | P92: =IFERROR((O92*N92/100)+ACCRINT(COUPPCD(L92,J92,2,1),COUPNCD(L92,J92,2,1),L92,I92,O92,2,1),O92*N92/100) -> 2.6512131e+08 | Q92: =O92*N92/100 -> 257400000 | R92: =IFERROR(ACCRINT(COUPPCD(L92,J92,2,1),COUPNCD(L92,J92,2,0),L92,I92,O92,2,1),"") -> 7721311.5 | T92: =IFERROR(Q92+R92,Q92) -> 2.6512131e+08
B93: =B92+1 -> 92 | C93: Keystone bank | D93: Stanbic | E93: GIF₦ | F93: Oise | G93: Buy | H93: NIGTB 20/Feb/2025 | I93: 0 | J93: 45708 | K93: 45343 | L93: 45344 | M93: 0.18195 | N93: =PRICEDISC(L93,J93,M93,100,1) -> 81.897616 | O93: 1000000000 | P93: =IFERROR((O93*N93/100)+ACCRINT(COUPPCD(L93,J93,2,1),COUPNCD(L93,J93,2,1),L93,I93,O93,2,1),O93*N93/100) -> 8.1897616e+08 | Q93: =O93*N93/100 -> 8.1897616e+08 | R93: =IFERROR(ACCRINT(COUPPCD(L93,J93,2,1),COUPNCD(L93,J93,2,0),L93,I93,O93,2,1),"") | T93: =IFERROR(Q93+R93,Q93) -> 8.1897616e+08
B94: =B93+1 -> 93 | C94: Keystone bank | D94: Stanbic | E94: GIF₦ | F94: Oise | G94: Buy | H94: NIGTB 20/Feb/2025 | I94: 0 | J94: 45708 | K94: 45343 | L94: 45344 | M94: 0.18899 | N94: =PRICEDISC(L94,J94,M94,100,1) -> 81.1972 | O94: 1000000000 | P94: =IFERROR((O94*N94/100)+ACCRINT(COUPPCD(L94,J94,2,1),COUPNCD(L94,J94,2,1),L94,I94,O94,2,1),O94*N94/100) -> 8.11972e+08 | Q94: =O94*N94/100 -> 8.11972e+08 | R94: =IFERROR(ACCRINT(COUPPCD(L94,J94,2,1),COUPNCD(L94,J94,2,0),L94,I94,O94,2,1),"") | T94: =IFERROR(Q94+R94,Q94) -> 8.11972e+08
B95: =B94+1 -> 94 | C95: Stanbic Nominees | D95: Stanbic | E95: GIF₦ | F95: Oise | G95: Buy | H95: NIGTB 20/Feb/2025 | I95: 0 | J95: 45708 | K95: 45343 | L95: 45344 | M95: 0.19 | N95: =PRICEDISC(L95,J95,M95,100,1) -> 81.096714 | O95: 1700000000 | P95: =IFERROR((O95*N95/100)+ACCRINT(COUPPCD(L95,J95,2,1),COUPNCD(L95,J95,2,1),L95,I95,O95,2,1),O95*N95/100) -> 1378644135 | Q95: =O95*N95/100 -> 1378644135 | R95: =IFERROR(ACCRINT(COUPPCD(L95,J95,2,1),COUPNCD(L95,J95,2,0),L95,I95,O95,2,1),"") | T95: =IFERROR(Q95+R95,Q95) -> 1378644135
B96: =B95+1 -> 95 | C96: Keystone bank | D96: Stanbic | E96: GIF₦ | F96: Oise | G96: Sell | H96: FGN 2053 bond | I96: 0.157 | J96: 56056 | K96: 45348 | L96: 45350 | M96: =IFERROR(YIELD(L96,J96,I96,N96,100,2,1),"") -> 0.18900209 | N96: 83.07 | O96: 3300000000 | P96: =IFERROR((O96*N96/100)+ACCRINT(COUPPCD(L96,J96,2,1),COUPNCD(L96,J96,2,1),L96,I96,O96,2,1),O96*N96/100) -> 2838984590 | Q96: =O96*N96/100 -> 2741310000 | R96: =IFERROR(ACCRINT(COUPPCD(L96,J96,2,1),COUPNCD(L96,J96,2,0),L96,I96,O96,2,1),"") -> 97674590 | T96: =IFERROR(Q96+R96,Q96) -> 2838984590
B97: =B96+1 -> 96 | C97: Keystone bank | D97: Stanbic | E97: GIF₦ | F97: Oise | G97: Sell | H97: FGN 2053 bond | I97: 0.157 | J97: 56056 | K97: 45349 | L97: 45351 | M97: =IFERROR(YIELD(L97,J97,I97,N97,100,2,1),"") -> 0.1890011 | N97: 83.07 | O97: 450000000 | P97: =IFERROR((O97*N97/100)+ACCRINT(COUPPCD(L97,J97,2,1),COUPNCD(L97,J97,2,1),L97,I97,O97,2,1),O97*N97/100) -> 3.873273e+08 | Q97: =O97*N97/100 -> 373815000 | R97: =IFERROR(ACCRINT(COUPPCD(L97,J97,2,1),COUPNCD(L97,J97,2,0),L97,I97,O97,2,1),"") -> 13512295 | T97: =IFERROR(Q97+R97,Q97) -> 3.873273e+08
B98: =B97+1 -> 97 | C98: Parthian | D98: Stanbic | E98: GIF₦ | F98: Oise | G98: Sell | H98: NIGTB 20/Feb/2025 | I98: 0 | J98: 45708 | K98: 45349 | L98: 45351 | M98: 0.1865 | N98: =PRICEDISC(L98,J98,M98,100,1) -> 81.801626 | O98: 2000000000 | P98: =IFERROR((O98*N98/100)+ACCRINT(COUPPCD(L98,J98,2,1),COUPNCD(L98,J98,2,1),L98,I98,O98,2,1),O98*N98/100) -> 1636032525 | Q98: =O98*N98/100 -> 1636032525 | R98: =IFERROR(ACCRINT(COUPPCD(L98,J98,2,1),COUPNCD(L98,J98,2,0),L98,I98,O98,2,1),"") | T98: =IFERROR(Q98+R98,Q98) -> 1636032525
B99: =B98+1 -> 98 | C99: Parthian | D99: Stanbic | E99: GIF₦ | F99: Oise | G99: Sell | H99: NIGTB 20/Feb/2025 | I99: 0 | J99: 45708 | K99: 45349 | L99: 45351 | M99: 0.187 | N99: =PRICEDISC(L99,J99,M99,100,1) -> 81.752837 | O99: 1700000000 | P99: =IFERROR((O99*N99/100)+ACCRINT(COUPPCD(L99,J99,2,1),COUPNCD(L99,J99,2,1),L99,I99,O99,2,1),O99*N99/100) -> 1389798230 | Q99: =O99*N99/100 -> 1389798230 | R99: =IFERROR(ACCRINT(COUPPCD(L99,J99,2,1),COUPNCD(L99,J99,2,0),L99,I99,O99,2,1),"") | T99: =IFERROR(Q99+R99,Q99) -> 1389798230
B100: =B99+1 -> 99 | C100: Keystone bank | D100: Stanbic | E100: GIF₦ | F100: Oise | G100: Sell | H100: FGN 2053 bond | I100: 0.157 | J100: 56056 | K100: 45350 | L100: 45352 | M100: =IFERROR(YIELD(L100,J100,I100,N100,100,2,1),"") -> 0.18900016 | N100: 83.07 | O100: 400000000 | P100: =IFERROR((O100*N100/100)+ACCRINT(COUPPCD(L100,J100,2,1),COUPNCD(L100,J100,2,1),L100,I100,O100,2,1),O100*N100/100) -> 3.4446251e+08 | Q100: =O100*N100/100 -> 332280000 | R100: =IFERROR(ACCRINT(COUPPCD(L100,J100,2,1),COUPNCD(L100,J100,2,0),L100,I100,O100,2,1),"") -> 12182514 | T100: =IFERROR(Q100+R100,Q100) -> 3.4446251e+08
B101: =B100+1 -> 100 | C101: Stanbic Nominees | D101: Stanbic | E101: GIF₦ | F101: Oise | G101: Buy | H101: NIGTB 6/Mar/2025 | I101: 0 | J101: 45722 | K101: 45357 | L101: 45358 | M101: 0.2 | N101: =PRICEDISC(L101,J101,M101,100,1) -> 80.099708 | O101: 1000000000 | P101: =IFERROR((O101*N101/100)+ACCRINT(COUPPCD(L101,J101,2,1),COUPNCD(L101,J101,2,1),L101,I101,O101,2,1),O101*N101/100) -> 8.0099708e+08 | Q101: =O101*N101/100 -> 8.0099708e+08 | R101: =IFERROR(ACCRINT(COUPPCD(L101,J101,2,1),COUPNCD(L101,J101,2,0),L101,I101,O101,2,1),"") | T101: =IFERROR(Q101+R101,Q101) -> 8.0099708e+08
B102: =B101+1 -> 101 | C102: Keystone bank | D102: Stanbic | E102: GIF₦ | F102: Oise | G102: Buy | H102: NIGTB 6/Mar/2025 | I102: 0 | J102: 45722 | K102: 45357 | L102: 45358 | M102: 0.196 | N102: =PRICEDISC(L102,J102,M102,100,1) -> 80.497714 | O102: 500000000 | P102: =IFERROR((O102*N102/100)+ACCRINT(COUPPCD(L102,J102,2,1),COUPNCD(L102,J102,2,1),L102,I102,O102,2,1),O102*N102/100) -> 4.0248857e+08 | Q102: =O102*N102/100 -> 4.0248857e+08 | R102: =IFERROR(ACCRINT(COUPPCD(L102,J102,2,1),COUPNCD(L102,J102,2,0),L102,I102,O102,2,1),"") | T102: =IFERROR(Q102+R102,Q102) -> 4.0248857e+08
B103: =B102+1 -> 102 | C103: Keystone bank | D103: Stanbic | E103: GIF₦ | F103: Oise | G103: Buy | H103: NIGTB 6/Mar/2025 | I103: 0 | J103: 45722 | K103: 45357 | L103: 45358 | M103: 0.1984 | N103: =PRICEDISC(L103,J103,M103,100,1) -> 80.25891 | O103: 500000000 | P103: =IFERROR((O103*N103/100)+ACCRINT(COUPPCD(L103,J103,2,1),COUPNCD(L103,J103,2,1),L103,I103,O103,2,1),O103*N103/100) -> 401294552 | Q103: =O103*N103/100 -> 401294552 | R103: =IFERROR(ACCRINT(COUPPCD(L103,J103,2,1),COUPNCD(L103,J103,2,0),L103,I103,O103,2,1),"") | T103: =IFERROR(Q103+R103,Q103) -> 401294552
B104: =B103+1 -> 103 | C104: Keystone bank | D104: Stanbic | E104: GIF₦ | F104: Oise | G104: Buy | H104: NIGTB 6/Mar/2025 | I104: 0 | J104: 45722 | K104: 45357 | L104: 45358 | M104: 0.2 | N104: =PRICEDISC(L104,J104,M104,100,1) -> 80.099708 | O104: 500000000 | P104: =IFERROR((O104*N104/100)+ACCRINT(COUPPCD(L104,J104,2,1),COUPNCD(L104,J104,2,1),L104,I104,O104,2,1),O104*N104/100) -> 4.0049854e+08 | Q104: =O104*N104/100 -> 4.0049854e+08 | R104: =IFERROR(ACCRINT(COUPPCD(L104,J104,2,1),COUPNCD(L104,J104,2,0),L104,I104,O104,2,1),"") | T104: =IFERROR(Q104+R104,Q104) -> 4.0049854e+08
B105: =B104+1 -> 104 | C105: Keystone bank | D105: Stanbic | E105: GIF₦ | F105: Oise | G105: Buy | H105: NIGTB 6/Mar/2025 | I105: 0 | J105: 45722 | K105: 45357 | L105: 45358 | M105: 0.1975 | N105: =PRICEDISC(L105,J105,M105,100,1) -> 80.348462 | O105: 5500000000 | P105: =IFERROR((O105*N105/100)+ACCRINT(COUPPCD(L105,J105,2,1),COUPNCD(L105,J105,2,1),L105,I105,O105,2,1),O105*N105/100) -> 4419165394 | Q105: =O105*N105/100 -> 4419165394 | R105: =IFERROR(ACCRINT(COUPPCD(L105,J105,2,1),COUPNCD(L105,J105,2,0),L105,I105,O105,2,1),"") | T105: =IFERROR(Q105+R105,Q105) -> 4419165394
B106: =B105+1 -> 105 | C106: Keystone bank | D106: Stanbic | E106: GIF₦ | F106: Oise | G106: Sell | H106: NIGTB 6/Mar/2025 | I106: 0 | J106: 45722 | K106: 45372 | L106: 45373 | M106: 0.193 | N106: =PRICEDISC(L106,J106,M106,100,1) -> 81.587202 | O106: 2000000000 | P106: =IFERROR((O106*N106/100)+ACCRINT(COUPPCD(L106,J106,2,1),COUPNCD(L106,J106,2,1),L106,I106,O106,2,1),O106*N106/100) -> 1631744038 | Q106: =O106*N106/100 -> 1631744038 | R106: =IFERROR(ACCRINT(COUPPCD(L106,J106,2,1),COUPNCD(L106,J106,2,0),L106,I106,O106,2,1),"") | T106: =IFERROR(Q106+R106,Q106) -> 1631744038
B107: =B106+1 -> 106 | C107: Keystone bank | D107: Stanbic | E107: GIF₦ | F107: Oise | G107: Sell | H107: NIGTB 6/Mar/2025 | I107: 0 | J107: 45722 | K107: 45372 | L107: 45376 | M107: 0.193 | N107: =PRICEDISC(L107,J107,M107,100,1) -> 81.745399 | O107: 2000000000 | P107: =IFERROR((O107*N107/100)+ACCRINT(COUPPCD(L107,J107,2,1),COUPNCD(L107,J107,2,1),L107,I107,O107,2,1),O107*N107/100) -> 1634907972 | Q107: =O107*N107/100 -> 1634907972 | R107: =IFERROR(ACCRINT(COUPPCD(L107,J107,2,1),COUPNCD(L107,J107,2,0),L107,I107,O107,2,1),"") | T107: =IFERROR(Q107+R107,Q107) -> 1634907972
B108: =B107+1 -> 107 | C108: Keystone bank | D108: Stanbic | E108: GIF₦ | F108: Oise | G108: Buy | H108: NIGTB 27/Mar/2025 | I108: 0 | J108: 45743 | K108: 45379 | L108: 45379 | M108: 0.1835 | N108: =PRICEDISC(L108,J108,M108,100,1) -> 81.738598 | O108: 4700000000 | P108: =IFERROR((O108*N108/100)+ACCRINT(COUPPCD(L108,J108,2,1),COUPNCD(L108,J108,2,1),L108,I108,O108,2,1),O108*N108/100) -> 3841714086 | Q108: =O108*N108/100 -> 3841714086 | R108: =IFERROR(ACCRINT(COUPPCD(L108,J108,2,1),COUPNCD(L108,J108,2,0),L108,I108,O108,2,1),"") | T108: =IFERROR(Q108+R108,Q108) -> 3841714086
B109: =B108+1 -> 108 | C109: Keystone bank | D109: Stanbic | E109: GIF₦ | F109: Ife | G109: Sell | H109: NIGTB 6/Mar/2025 | I109: 0 | J109: 45722 | K109: 45394 | L109: 45398 | M109: 0.1945 | N109: =PRICEDISC(L109,J109,M109,100,1) -> 82.772649 | O109: 4000000000 | P109: 3.310906e+09 | Q109: 3.310906e+09 | R109: =IFERROR(ACCRINT(COUPPCD(L109,J109,2,1),COUPNCD(L109,J109,2,0),L109,I109,O109,2,1),"") | T109: =IFERROR(Q109+R109,Q109) -> 3310905966
B110: =B109+1 -> 109 | C110: Stanbic Nominees | D110: Stanbic | E110: GIF₦ | F110: Ife | G110: Buy | H110: FGN 2034 bond | I110: 0.19 | J110: 48996 | K110: 45397 | L110: 45399 | M110: =IFERROR(YIELD(L110,J110,I110,N110,100,2,1),"") -> 0.2 | N110: 95.669503 | O110: 3300000000 | P110: =IFERROR((O110*N110/100)+ACCRINT(COUPPCD(L110,J110,2,1),COUPNCD(L110,J110,2,1),L110,I110,O110,2,1),O110*N110/100) -> 3253555142 | Q110: =O110*N110/100 -> 3157093604 | R110: =IFERROR(ACCRINT(COUPPCD(L110,J110,2,1),COUPNCD(L110,J110,2,0),L110,I110,O110,2,1),"") -> 96461538 | T110: =IFERROR(Q110+R110,Q110) -> 3253555142
B111: =B110+1 -> 110 | C111: Keystone bank | D111: Stanbic | E111: GIF₦ | F111: Ife | G111: Sell | H111: NIGTB 27/Mar/2025 | I111: 0 | J111: 45743 | K111: 45405 | L111: 45406 | M111: 0.2115 | N111: =PRICEDISC(L111,J111,M111,100,1) -> 80.512362 | O111: 3150000000 | P111: =IFERROR((O111*N111/100)+ACCRINT(COUPPCD(L111,J111,2,1),COUPNCD(L111,J111,2,1),L111,I111,O111,2,1),O111*N111/100) -> 2536139417 | Q111: =O111*N111/100 -> 2536139417 | R111: =IFERROR(ACCRINT(COUPPCD(L111,J111,2,1),COUPNCD(L111,J111,2,0),L111,I111,O111,2,1),"") | T111: =IFERROR(Q111+R111,Q111) -> 2536139417
B112: =B111+1 -> 111 | C112: Keystone bank | D112: Stanbic | E112: GIF₦ | F112: Ife | G112: Buy | H112: FGN 2034 bond | I112: 0.19 | J112: 48996 | K112: 45406 | L112: 45408 | M112: =IFERROR(YIELD(L112,J112,I112,N112,100,2,1),"") -> 0.19499353 | N112: 97.75 | O112: 1000000000 | P112: =IFERROR((O112*N112/100)+ACCRINT(COUPPCD(L112,J112,2,1),COUPNCD(L112,J112,2,1),L112,I112,O112,2,1),O112*N112/100) -> 1011428571 | Q112: =O112*N112/100 -> 977500000 | R112: =IFERROR(ACCRINT(COUPPCD(L112,J112,2,1),COUPNCD(L112,J112,2,0),L112,I112,O112,2,1),"") -> 33928571 | T112: =IFERROR(Q112+R112,Q112) -> 1011428571
B113: =B112+1 -> 112 | C113: Parthian | D113: Stanbic | E113: GIF₦ | F113: Ife | G113: Buy | H113: FGN 2027 bond | I113: 0.1994 | J113: 46466 | K113: 45407 | L113: 45408 | M113: =IFERROR(YIELD(L113,J113,I113,N113,100,2,1),"") -> 0.19274904 | N113: 101.35375 | O113: 1000000000 | P113: =IFERROR((O113*N113/100)+ACCRINT(COUPPCD(L113,J113,2,1),COUPNCD(L113,J113,2,1),L113,I113,O113,2,1),O113*N113/100) -> 1033585870 | Q113: =O113*N113/100 -> 1013537500 | R113: =IFERROR(ACCRINT(COUPPCD(L113,J113,2,1),COUPNCD(L113,J113,2,0),L113,I113,O113,2,1),"") -> 20048370 | T113: =IFERROR(Q113+R113,Q113) -> 1033585870
B114: =B113+1 -> 113 | C114: Keystone bank | D114: Stanbic | E114: GIF₦ | F114: Oise | G114: Sell | H114: NIGTB 27/Mar/2025 | I114: 0 | J114: 45743 | K114: 45421 | L114: 45422 | M114: 0.208 | N114: =PRICEDISC(L114,J114,M114,100,1) -> 81.744143 | O114: 1000000000 | P114: =IFERROR((O114*N114/100)+ACCRINT(COUPPCD(L114,J114,2,1),COUPNCD(L114,J114,2,1),L114,I114,O114,2,1),O114*N114/100) -> 8.1744143e+08 | Q114: =O114*N114/100 -> 8.1744143e+08 | R114: =IFERROR(ACCRINT(COUPPCD(L114,J114,2,1),COUPNCD(L114,J114,2,0),L114,I114,O114,2,1),"") | T114: =IFERROR(Q114+R114,Q114) -> 8.1744143e+08
B115: =B114+1 -> 114 | C115: Parthian | D115: Stanbic | E115: GIF₦ | F115: Victor | G115: Sell | H115: NIGTB 27/Mar/2025 | I115: 0 | J115: 45743 | K115: 45432 | L115: 45433 | M115: 0.207 | N115: =PRICEDISC(L115,J115,M115,100,1) -> 82.454042 | O115: 350000000 | P115: =IFERROR((O115*N115/100)+ACCRINT(COUPPCD(L115,J115,2,1),COUPNCD(L115,J115,2,1),L115,I115,O115,2,1),O115*N115/100) -> 2.8858915e+08 | Q115: =O115*N115/100 -> 2.8858915e+08 | R115: =IFERROR(ACCRINT(COUPPCD(L115,J115,2,1),COUPNCD(L115,J115,2,0),L115,I115,O115,2,1),"") | T115: =IFERROR(Q115+R115,Q115) -> 2.8858915e+08
B116: =B115+1 -> 115 | C116: Keystone bank | D116: Stanbic | E116: GIF₦ | F116: Victor | G116: Buy | H116: NIGTB 05/Jun/2025 | I116: 0 | J116: 45813 | K116: 45464 | L116: 45467 | M116: 0.2 | N116: =PRICEDISC(L116,J116,M116,100,1) -> 81.069691 | O116: 1650000000 | P116: =IFERROR((O116*N116/100)+ACCRINT(COUPPCD(L116,J116,2,1),COUPNCD(L116,J116,2,1),L116,I116,O116,2,1),O116*N116/100) -> 1337649899 | Q116: =O116*N116/100 -> 1337649899 | R116: =IFERROR(ACCRINT(COUPPCD(L116,J116,2,1),COUPNCD(L116,J116,2,0),L116,I116,O116,2,1),"") | T116: =IFERROR(Q116+R116,Q116) -> 1337649899
B117: =B116+1 -> 116 | C117: Keystone bank | D117: Stanbic | E117: GIF₦ | F117: Victor | G117: Sell | H117: FGN 2034 bond | I117: 0.19 | J117: 48996 | K117: 45470 | L117: 45471 | M117: =IFERROR(YIELD(L117,J117,I117,N117,100,2,1),"") -> 0.21050925 | N117: 91.57 | O117: 1500000000 | P117: =IFERROR((O117*N117/100)+ACCRINT(COUPPCD(L117,J117,2,1),COUPNCD(L117,J117,2,1),L117,I117,O117,2,1),O117*N117/100) -> 1473769780 | Q117: =O117*N117/100 -> 1373550000 | R117: =IFERROR(ACCRINT(COUPPCD(L117,J117,2,1),COUPNCD(L117,J117,2,0),L117,I117,O117,2,1),"") -> 1.0021978e+08 | T117: =IFERROR(Q117+R117,Q117) -> 1473769780
B118: =B117+1 -> 117 | C118: Keystone bank | D118: Stanbic | E118: GIF₦ | F118: Victor | G118: Sell | H118: FGN 2034 bond | I118: 0.19 | J118: 48996 | K118: 45484 | L118: 45485 | M118: =IFERROR(YIELD(L118,J118,I118,N118,100,2,1),"") -> 0.21400292 | N118: 90.29 | O118: 1000000000 | P118: =IFERROR((O118*N118/100)+ACCRINT(COUPPCD(L118,J118,2,1),COUPNCD(L118,J118,2,1),L118,I118,O118,2,1),O118*N118/100) -> 9.7702088e+08 | Q118: =O118*N118/100 -> 902900000 | R118: =IFERROR(ACCRINT(COUPPCD(L118,J118,2,1),COUPNCD(L118,J118,2,0),L118,I118,O118,2,1),"") -> 74120879 | T118: =IFERROR(Q118+R118,Q118) -> 9.7702088e+08
B119: =B118+1 -> 118 | C119: Keystone bank | D119: Stanbic | E119: GIF₦ | F119: Victor | G119: Sell | H119: FGN 2034 bond | I119: 0.19 | J119: 48996 | K119: 45485 | L119: 45488 | M119: =IFERROR(YIELD(L119,J119,I119,N119,100,2,1),"") -> 0.21402253 | N119: 90.29 | O119: 400000000 | P119: =IFERROR((O119*N119/100)+ACCRINT(COUPPCD(L119,J119,2,1),COUPNCD(L119,J119,2,1),L119,I119,O119,2,1),O119*N119/100) -> 3.9143473e+08 | Q119: =O119*N119/100 -> 361160000 | R119: =IFERROR(ACCRINT(COUPPCD(L119,J119,2,1),COUPNCD(L119,J119,2,0),L119,I119,O119,2,1),"") -> 30274725 | T119: =IFERROR(Q119+R119,Q119) -> 3.9143473e+08
B120: =B119+1 -> 119 | C120: Keystone bank | D120: Stanbic | E120: GIF₦ | F120: Victor | G120: Buy | H120: NIGTB 10/Jul/2025 | I120: 0 | J120: 45848 | K120: 45490 | L120: 45492 | M120: 0.2 | N120: =PRICEDISC(L120,J120,M120,100,1) -> 80.518003 | O120: 1600000000 | P120: =IFERROR((O120*N120/100)+ACCRINT(COUPPCD(L120,J120,2,1),COUPNCD(L120,J120,2,1),L120,I120,O120,2,1),O120*N120/100) -> 1288288046 | Q120: =O120*N120/100 -> 1288288046 | R120: =IFERROR(ACCRINT(COUPPCD(L120,J120,2,1),COUPNCD(L120,J120,2,0),L120,I120,O120,2,1),"") | T120: =IFERROR(Q120+R120,Q120) -> 1288288046
B121: =B120+1 -> 120 | C121: Keystone bank | D121: Stanbic | E121: GIF₦ | F121: Victor | G121: Sell | H121: FGN 2034 bond | I121: 0.19 | J121: 48996 | K121: 45498 | L121: 45499 | M121: =IFERROR(YIELD(L121,J121,I121,N121,100,2,1),"") -> 0.22699615 | N121: 85.72 | O121: 1400000000 | P121: =IFERROR((O121*N121/100)+ACCRINT(COUPPCD(L121,J121,2,1),COUPNCD(L121,J121,2,1),L121,I121,O121,2,1),O121*N121/100) -> 1314080000 | Q121: =O121*N121/100 -> 1200080000 | R121: =IFERROR(ACCRINT(COUPPCD(L121,J121,2,1),COUPNCD(L121,J121,2,0),L121,I121,O121,2,1),"") -> 114000000 | T121: =IFERROR(Q121+R121,Q121) -> 1314080000
B122: =B121+1 -> 121 | C122: Keystone bank | D122: Stanbic | E122: GIF₦ | F122: Victor | G122: Buy | H122: NIGTB 22/May/2025 | I122: 0 | J122: 45799 | K122: 45499 | L122: 45502 | M122: 0.222 | N122: =PRICEDISC(L122,J122,M122,100,1) -> 81.961815 | O122: 1600000000 | P122: =IFERROR((O122*N122/100)+ACCRINT(COUPPCD(L122,J122,2,1),COUPNCD(L122,J122,2,1),L122,I122,O122,2,1),O122*N122/100) -> 1311389032 | Q122: =O122*N122/100 -> 1311389032 | R122: =IFERROR(ACCRINT(COUPPCD(L122,J122,2,1),COUPNCD(L122,J122,2,0),L122,I122,O122,2,1),"") | T122: =IFERROR(Q122+R122,Q122) -> 1311389032
B123: =B122+1 -> 122 | C123: Keystone bank | D123: Stanbic | E123: GIF₦ | F123: Victor | G123: Sell | H123: NIGTB 05/Jun/2025 | I123: 0 | J123: 45813 | K123: 45510 | L123: 45511 | M123: 0.225 | N123: =PRICEDISC(L123,J123,M123,100,1) -> 81.40832 | O123: 400000000 | P123: =IFERROR((O123*N123/100)+ACCRINT(COUPPCD(L123,J123,2,1),COUPNCD(L123,J123,2,1),L123,I123,O123,2,1),O123*N123/100) -> 3.2563328e+08 | Q123: =O123*N123/100 -> 3.2563328e+08 | R123: =IFERROR(ACCRINT(COUPPCD(L123,J123,2,1),COUPNCD(L123,J123,2,0),L123,I123,O123,2,1),"") | T123: =IFERROR(Q123+R123,Q123) -> 3.2563328e+08
B124: =B123+1 -> 123 | C124: Keystone bank | D124: Stanbic | E124: GIF₦ | F124: Victor | G124: Sell | H124: NIGTB 22/May/2025 | I124: 0 | J124: 45799 | K124: 45533 | L124: 45534 | M124: 0.1975 | N124: =PRICEDISC(L124,J124,M124,100,1) -> 85.679291 | O124: 1600000000 | P124: =IFERROR((O124*N124/100)+ACCRINT(COUPPCD(L124,J124,2,1),COUPNCD(L124,J124,2,1),L124,I124,O124,2,1),O124*N124/100) -> 1370868658 | Q124: =O124*N124/100 -> 1370868658 | R124: =IFERROR(ACCRINT(COUPPCD(L124,J124,2,1),COUPNCD(L124,J124,2,0),L124,I124,O124,2,1),"") | T124: =IFERROR(Q124+R124,Q124) -> 1370868658
B125: =B124+1 -> 124 | C125: Keystone bank | D125: Stanbic | E125: GIF₦ | F125: Victor | G125: Sell | H125: NIGTB 10/Jul/2025 | I125: 0 | J125: 45848 | K125: 45533 | L125: 45534 | M125: 0.197 | N125: =PRICEDISC(L125,J125,M125,100,1) -> 83.070889 | O125: 800000000 | P125: =IFERROR((O125*N125/100)+ACCRINT(COUPPCD(L125,J125,2,1),COUPNCD(L125,J125,2,1),L125,I125,O125,2,1),O125*N125/100) -> 6.6456711e+08 | Q125: =O125*N125/100 -> 6.6456711e+08 | R125: =IFERROR(ACCRINT(COUPPCD(L125,J125,2,1),COUPNCD(L125,J125,2,0),L125,I125,O125,2,1),"") | T125: =IFERROR(Q125+R125,Q125) -> 6.6456711e+08
B126: =B125+1 -> 125 | C126: Keystone bank | D126: Stanbic | E126: GIF₦ | F126: Victor | G126: Buy | H126: FGN 2033 bond | I126: 0.1989 | J126: 48714 | K126: 45534 | L126: 45537 | M126: =IFERROR(YIELD(L126,J126,I126,N126,100,2,1),"") -> 0.19260087 | N126: 102.5 | O126: 500000000 | P126: =IFERROR((O126*N126/100)+ACCRINT(COUPPCD(L126,J126,2,1),COUPNCD(L126,J126,2,1),L126,I126,O126,2,1),O126*N126/100) -> 5.422269e+08 | Q126: =O126*N126/100 -> 512500000 | R126: =IFERROR(ACCRINT(COUPPCD(L126,J126,2,1),COUPNCD(L126,J126,2,0),L126,I126,O126,2,1),"") -> 29726902 | T126: =IFERROR(Q126+R126,Q126) -> 5.422269e+08
B127: =B126+1 -> 126 | C127: Keystone bank | D127: Stanbic | E127: GIF₦ | F127: Victor | G127: Buy | H127: FGN 2033 bond | I127: 0.1989 | J127: 48714 | K127: 45534 | L127: 45538 | M127: =IFERROR(YIELD(L127,J127,I127,N127,100,2,1),"") -> 0.19260124 | N127: 102.5 | O127: 1500000000 | P127: =IFERROR((O127*N127/100)+ACCRINT(COUPPCD(L127,J127,2,1),COUPNCD(L127,J127,2,1),L127,I127,O127,2,1),O127*N127/100) -> 1627491440 | Q127: =O127*N127/100 -> 1537500000 | R127: =IFERROR(ACCRINT(COUPPCD(L127,J127,2,1),COUPNCD(L127,J127,2,0),L127,I127,O127,2,1),"") -> 89991440 | T127: =IFERROR(Q127+R127,Q127) -> 1627491440
...

Sheet Sheet4
A1: Direction | B1: Name of Asset | C1: Coupon Rate | D1: Maturity Date | E1: Trade Date | F1: Settlement Date | G1: Ytm | H1: Price | I1: Face Value | J1: Consideration | K1: Principal | L1: Accrued Interest
A2: Buy | B2: FGN 2026 Bond | C2: 0.125 | D2: 46044 | E2: 44327 | F2: 44330 | G2: =IFERROR(YIELD(F2,D2,C2,H2,100,2,1),"") -> 0.1289945 | H2: 98.58 | I2: 194000000 | J2: =IFERROR((I2*H2/100)+ACCRINT(COUPPCD(F2,D2,2,1),COUPNCD(F2,D2,2,1),F2,C2,I2,2,1),I2*H2/100) -> 1.9874796e+08 | K2: =I2*H2/100 -> 191245200 | L2: =IFERROR(ACCRINT(COUPPCD(F2,D2,2,1),COUPNCD(F2,D2,2,0),F2,C2,I2,2,1),"") -> 7502762.4
A3: Buy | B3: FGN 2035 Bond | C3: 0.125 | D3: 49395 | E3: 44327 | F3: 44333 | G3: =IFERROR(YIELD(F3,D3,C3,H3,100,2,1),"") -> 0.13859495 | H3: 91.68 | I3: 200000000 | J3: =IFERROR((I3*H3/100)+ACCRINT(COUPPCD(F3,D3,2,1),COUPNCD(F3,D3,2,1),F3,C3,I3,2,1),I3*H3/100) -> 1.8682467e+08 | K3: =I3*H3/100 -> 183360000 | L3: =IFERROR(ACCRINT(COUPPCD(F3,D3,2,1),COUPNCD(F3,D3,2,0),F3,C3,I3,2,1),"") -> 3464673.9
A4: Buy | B4: FGN 2045 Bond | C4: 0.098 | D4: 53167 | E4: 44334 | F4: 44336 | G4: =YIELD(F4,D4,C4,H4,100,2,1) -> 0.1399995 | H4: 71.1 | I4: 200000000 | J4: =IFERROR((I4*H4/100)+ACCRINT(COUPPCD(F4,D4,2,1),COUPNCD(F4,D4,2,1),F4,C4,I4,2,1),I4*H4/100) -> 148480663 | K4: =I4*H4/100 -> 142200000 | L4: =IFERROR(ACCRINT(COUPPCD(F4,D4,2,1),COUPNCD(F4,D4,2,0),F4,C4,I4,2,1),"") -> 6280663
A5: Buy | B5: FGN 2027 Bond | C5: 0.162884 | D5: 46463 | E5: 44337 | F5: 44341 | G5: =YIELD(F5,D5,C5,H5,100,2,1) -> 0.13099418 | H5: 112.64 | I5: 100000000 | J5: =IFERROR((I5*H5/100)+ACCRINT(COUPPCD(F5,D5,2,1),COUPNCD(F5,D5,2,1),F5,C5,I5,2,1),I5*H5/100) -> 115694075 | K5: =I5*H5/100 -> 112640000 | L5: =IFERROR(ACCRINT(COUPPCD(F5,D5,2,1),COUPNCD(F5,D5,2,0),F5,C5,I5,2,1),"") -> 3054075
A6: Buy | B6: FGN 2049 Bond | C6: 0.148 | D6: 54539 | E6: 44347 | F6: 44349 | G6: =YIELD(F6,D6,C6,H6,100,2,1) -> 0.13980035 | H6: 105.69 | I6: 500000000 | J6: =IFERROR((I6*H6/100)+ACCRINT(COUPPCD(F6,D6,2,1),COUPNCD(F6,D6,2,1),F6,C6,I6,2,1),I6*H6/100) -> 5.3593087e+08 | K6: =I6*H6/100 -> 528450000 | L6: =IFERROR(ACCRINT(COUPPCD(F6,D6,2,1),COUPNCD(F6,D6,2,0),F6,C6,I6,2,1),"") -> 7480874.3
A7: Buy | B7: FGN 2035 Bond | C7: 0.125 | D7: 49395 | E7: 44348 | F7: =E7+2 -> 44350 | G7: =IFERROR(YIELD(F7,D7,C7,H7,100,2,1),"") -> 0.13819595 | H7: 91.91 | I7: 100000000 | J7: =IFERROR((I7*H7/100)+ACCRINT(COUPPCD(F7,D7,2,1),COUPNCD(F7,D7,2,1),F7,C7,I7,2,1),I7*H7/100) -> 94219783 | K7: =I7*H7/100 -> 91910000 | L7: =IFERROR(ACCRINT(COUPPCD(F7,D7,2,1),COUPNCD(F7,D7,2,0),F7,C7,I7,2,1),"") -> 2309782.6
A8: Buy | B8: FGN 2050 Bond | C8: 0.1298 | D8: 54874 | E8: 44348 | F8: 44350 | G8: =IFERROR(YIELD(F8,D8,C8,H8,100,2,1),"") -> 0.13919423 | H8: 93.34 | I8: 300000000 | J8: =IFERROR((I8*H8/100)+ACCRINT(COUPPCD(F8,D8,2,1),COUPNCD(F8,D8,2,1),F8,C8,I8,2,1),I8*H8/100) -> 2.8721543e+08 | K8: =I8*H8/100 -> 280020000 | L8: =IFERROR(ACCRINT(COUPPCD(F8,D8,2,1),COUPNCD(F8,D8,2,0),F8,C8,I8,2,1),"") -> 7195434.8
A9: Buy | B9: FGN 2050 Bond | C9: 0.1298 | D9: 54874 | E9: 44348 | F9: 44350 | G9: =IFERROR(YIELD(F9,D9,C9,H9,100,2,1),"") -> 0.13919423 | H9: 93.34 | I9: 200000000 | J9: =IFERROR((I9*H9/100)+ACCRINT(COUPPCD(F9,D9,2,1),COUPNCD(F9,D9,2,1),F9,C9,I9,2,1),I9*H9/100) -> 1.9147696e+08 | K9: =I9*H9/100 -> 186680000 | L9: =IFERROR(ACCRINT(COUPPCD(F9,D9,2,1),COUPNCD(F9,D9,2,0),F9,C9,I9,2,1),"") -> 4796956.5
A10: Buy | B10: FGN 2049 Bond | C10: 0.148 | D10: 54539 | E10: 44344 | F10: 44351 | G10: =YIELD(F10,D10,C10,H10,100,2,1) -> 0.14030202 | H10: 105.32 | I10: 500000000 | J10: =IFERROR((I10*H10/100)+ACCRINT(COUPPCD(F10,D10,2,1),COUPNCD(F10,D10,2,1),F10,C10,I10,2,1),I10*H10/100) -> 5.3448525e+08 | K10: =I10*H10/100 -> 526600000 | L10: =IFERROR(ACCRINT(COUPPCD(F10,D10,2,1),COUPNCD(F10,D10,2,0),F10,C10,I10,2,1),"") -> 7885245.9
A11: Buy | B11: FGN 2049 Bond | C11: 0.148 | D11: 54539 | E11: 44347 | F11: 44351 | G11: =YIELD(F11,D11,C11,H11,100,2,1) -> 0.13979804 | H11: 105.69 | I11: 300000000 | J11: =IFERROR((I11*H11/100)+ACCRINT(COUPPCD(F11,D11,2,1),COUPNCD(F11,D11,2,1),F11,C11,I11,2,1),I11*H11/100) -> 3.2180115e+08 | K11: =I11*H11/100 -> 317070000 | L11: =IFERROR(ACCRINT(COUPPCD(F11,D11,2,1),COUPNCD(F11,D11,2,0),F11,C11,I11,2,1),"") -> 4731147.5
A12: Buy | B12: FGN 2050 Bond | C12: 0.1298 | D12: 54874 | E12: 44348 | F12: 44354 | G12: =IFERROR(YIELD(F12,D12,C12,H12,100,2,1),"") -> 0.13929889 | H12: 93.27 | I12: 300000000 | J12: =IFERROR((I12*H12/100)+ACCRINT(COUPPCD(F12,D12,2,1),COUPNCD(F12,D12,2,1),F12,C12,I12,2,1),I12*H12/100) -> 2.874287e+08 | K12: =I12*H12/100 -> 279810000 | L12: =IFERROR(ACCRINT(COUPPCD(F12,D12,2,1),COUPNCD(F12,D12,2,0),F12,C12,I12,2,1),"") -> 7618695.7
A13: Buy | B13: FGN 2050 Bond | C13: 0.1298 | D13: 54874 | E13: 44371 | F13: 44372 | G13: =IFERROR(YIELD(F13,D13,C13,H13,100,2,1),"") -> 0.137 | H13: 94.807168 | I13: 1000000000 | J13: =IFERROR((I13*H13/100)+ACCRINT(COUPPCD(F13,D13,2,1),COUPNCD(F13,D13,2,1),F13,C13,I13,2,1),I13*H13/100) -> 9.7981625e+08 | K13: =I13*H13/100 -> 9.4807168e+08 | L13: =IFERROR(ACCRINT(COUPPCD(F13,D13,2,1),COUPNCD(F13,D13,2,0),F13,C13,I13,2,1),"") -> 31744565
A14: Buy | B14: FGN 2050 Bond | C14: 0.1298 | D14: 54874 | E14: 44378 | F14: 44382 | G14: =IFERROR(YIELD(F14,D14,C14,H14,100,2,1),"") -> 0.13000005 | H14: 99.7995 | I14: 500000000 | J14: =IFERROR((I14*H14/100)+ACCRINT(COUPPCD(F14,D14,2,1),COUPNCD(F14,D14,2,1),F14,C14,I14,2,1),I14*H14/100) -> 5.1663337e+08 | K14: =I14*H14/100 -> 498997500 | L14: =IFERROR(ACCRINT(COUPPCD(F14,D14,2,1),COUPNCD(F14,D14,2,0),F14,C14,I14,2,1),"") -> 17635870
A15: Buy | B15: FGN 2050 Bond | C15: 0.1298 | D15: 54874 | E15: 44379 | F15: 44383 | G15: =IFERROR(YIELD(F15,D15,C15,H15,100,2,1),"") -> 0.12999951 | H15: 99.8 | I15: 1500000000 | J15: =IFERROR((I15*H15/100)+ACCRINT(COUPPCD(F15,D15,2,1),COUPNCD(F15,D15,2,1),F15,C15,I15,2,1),I15*H15/100) -> 1550436685 | K15: =I15*H15/100 -> 1497000000 | L15: =IFERROR(ACCRINT(COUPPCD(F15,D15,2,1),COUPNCD(F15,D15,2,0),F15,C15,I15,2,1),"") -> 53436685
A16: Sell | B16: FGN 2049 Bond | C16: 0.148 | D16: 54539 | E16: 44382 | F16: 44383 | G16: =IFERROR(YIELD(F16,D16,C16,H16,100,2,1),"") -> 0.13000446 | H16: 113.37 | I16: 700000000 | J16: =IFERROR((I16*H16/100)+ACCRINT(COUPPCD(F16,D16,2,1),COUPNCD(F16,D16,2,1),F16,C16,I16,2,1),I16*H16/100) -> 8.1368727e+08 | K16: =I16*H16/100 -> 793590000 | L16: =IFERROR(ACCRINT(COUPPCD(F16,D16,2,1),COUPNCD(F16,D16,2,0),F16,C16,I16,2,1),"") -> 20097268
A17: Sell | B17: FGN 2035 Bond | C17: 0.125 | D17: 49395 | E17: 44382 | F17: 44383 | G17: =IFERROR(YIELD(F17,D17,C17,H17,100,2,1),"") -> 0.12949569 | H17: 97.1 | I17: 100000000 | J17: =IFERROR((I17*H17/100)+ACCRINT(COUPPCD(F17,D17,2,1),COUPNCD(F17,D17,2,1),F17,C17,I17,2,1),I17*H17/100) -> 1.0053071e+08 | K17: =I17*H17/100 -> 97100000 | L17: =IFERROR(ACCRINT(COUPPCD(F17,D17,2,1),COUPNCD(F17,D17,2,0),F17,C17,I17,2,1),"") -> 3430706.5
A18: Sell | B18: FGN 2035 Bond | C18: 0.125 | D18: 49395 | E18: 44382 | F18: 44383 | G18: =IFERROR(YIELD(F18,D18,C18,H18,100,2,1),"") -> 0.12949569 | H18: 97.1 | I18: 200000000 | J18: =IFERROR((I18*H18/100)+ACCRINT(COUPPCD(F18,D18,2,1),COUPNCD(F18,D18,2,1),F18,C18,I18,2,1),I18*H18/100) -> 201061413 | K18: =I18*H18/100 -> 194200000 | L18: =IFERROR(ACCRINT(COUPPCD(F18,D18,2,1),COUPNCD(F18,D18,2,0),F18,C18,I18,2,1),"") -> 6861413
